Workbook

Sheet 🧮 TÍNH NHANH
A1: 🧮 BẢNG TÍNH NHANH — CÔNG CỤ KINH DOANH
A2: Phụ tùng động cơ diesel • Báo giá · Tính kênh giá · Phiếu VAT 8% | H2: Ngày: | I2: =TODAY()
A3: 🧭 Nhảy tới: | C3: ① MÁY TÍNH GIÁ | E3: ② TÍNH KÊNH GIÁ | G3: ③ PHIẾU ĐẶT HÀNG VAT | I3: 🟡 Ô vàng = nhập
A5: ① MÁY TÍNH GIÁ GỢI Ý — Nhập GIÁ VỐN, tự tính 5 mức giá để báo khách (Copy → Paste vào sheet kho)
A6: Ngày: | B6: =TODAY() | C6: Người lập: | D6: Luân Nguyễn | E6: Khách hàng: | I6: Số phiếu:
A7: STT | B7: MÃ SP | C7: TÊN SẢN PHẨM | D7: ĐVT | E7: SL | F7: 💰 GIÁ VỐN (VNĐ) | G7: 🟢 VIP (+20%) | H7: 🟡 Ư.ĐÃI (+25%) | I7: 🔵 ĐẠI LÝ (+20%) | J7: 🟣 GARA (+25%) | K7: 🔴 BÁN LẺ (+30%)
A8: 1 | D8: Cái | E8: 1 | F8: 840000 | G8: =IFERROR(IF(F8="","",ROUND(F8*1.2*IF(E8="",1,E8),0)),"") | H8: =IFERROR(IF(F8="","",ROUND(F8*1.25*IF(E8="",1,E8),0)),"") | I8: =IFERROR(IF(F8="","",ROUND(F8*1.2*IF(E8="",1,E8),0)),"") | J8: =IFERROR(IF(F8="","",ROUND(F8*1.25*IF(E8="",1,E8),0)),"") | K8: =IFERROR(IF(F8="","",ROUND(F8*1.3*IF(E8="",1,E8),0)),"")
A9: 2 | G9: =IFERROR(IF(F9="","",ROUND(F9*1.2*IF(E9="",1,E9),0)),"") | H9: =IFERROR(IF(F9="","",ROUND(F9*1.25*IF(E9="",1,E9),0)),"") | I9: =IFERROR(IF(F9="","",ROUND(F9*1.2*IF(E9="",1,E9),0)),"") | J9: =IFERROR(IF(F9="","",ROUND(F9*1.25*IF(E9="",1,E9),0)),"") | K9: =IFERROR(IF(F9="","",ROUND(F9*1.3*IF(E9="",1,E9),0)),"")
A10: 3 | G10: =IFERROR(IF(F10="","",ROUND(F10*1.2*IF(E10="",1,E10),0)),"") | H10: =IFERROR(IF(F10="","",ROUND(F10*1.25*IF(E10="",1,E10),0)),"") | I10: =IFERROR(IF(F10="","",ROUND(F10*1.2*IF(E10="",1,E10),0)),"") | J10: =IFERROR(IF(F10="","",ROUND(F10*1.25*IF(E10="",1,E10),0)),"") | K10: =IFERROR(IF(F10="","",ROUND(F10*1.3*IF(E10="",1,E10),0)),"")
A11: 4 | G11: =IFERROR(IF(F11="","",ROUND(F11*1.2*IF(E11="",1,E11),0)),"") | H11: =IFERROR(IF(F11="","",ROUND(F11*1.25*IF(E11="",1,E11),0)),"") | I11: =IFERROR(IF(F11="","",ROUND(F11*1.2*IF(E11="",1,E11),0)),"") | J11: =IFERROR(IF(F11="","",ROUND(F11*1.25*IF(E11="",1,E11),0)),"") | K11: =IFERROR(IF(F11="","",ROUND(F11*1.3*IF(E11="",1,E11),0)),"")
A12: 5 | G12: =IFERROR(IF(F12="","",ROUND(F12*1.2*IF(E12="",1,E12),0)),"") | H12: =IFERROR(IF(F12="","",ROUND(F12*1.25*IF(E12="",1,E12),0)),"") | I12: =IFERROR(IF(F12="","",ROUND(F12*1.2*IF(E12="",1,E12),0)),"") | J12: =IFERROR(IF(F12="","",ROUND(F12*1.25*IF(E12="",1,E12),0)),"") | K12: =IFERROR(IF(F12="","",ROUND(F12*1.3*IF(E12="",1,E12),0)),"")
A13: TỔNG CỘNG | F13: =SUM(F8:F12) | G13: =SUM(G8:G12) | H13: =SUM(H8:H12) | I13: =SUM(I8:I12) | J13: =SUM(J8:J12) | K13: =SUM(K8:K12)
A14: 💡 Chỉ nhập GIÁ VỐN (cột F) — 5 mức giá tự nhảy. Copy số → Paste vào sheet kho (PISTON, SÉC MĂNG, ...)
A16: ② TÍNH TIỀN KÊNH GIÁ — Khi khách chuyển cao hơn giá thực (VAT 8%, công ty giữ 20%, trả khách 80%)
A17: 💡 Chỉ nhập 2 cột VÀNG: [Tiền khách chuyển] và [Tiền hàng thực xuất] — Các cột còn lại tự động tính
A18: STT | B18: KHÁCH HÀNG | C18: MÔ TẢ GIAO DỊCH | D18: NGÀY | E18: KHÁCH CHUYỂN (có VAT) | F18: HÀNG THỰC (chưa VAT) | G18: GIÁ HÀNG ÷ 1.08 | H18: VAT 8% | I18: PHẦN KÊNH | K18: TRẢ KHÁCH (80%)
A19: 1 | E19: 15000000 | F19: 10000000 | G19: =IFERROR(IF(E19="","",E19/1.08),"") | H19: =IFERROR(IF(E19="","",E19-G19),"") | I19: =IFERROR(IF(OR(E19="",F19=""),"",MAX(0,G19-F19)),"") | K19: =IFERROR(IF(I19="","",I19*0.8),"")
A20: 2 | G20: =IFERROR(IF(E20="","",E20/1.08),"") | H20: =IFERROR(IF(E20="","",E20-G20),"") | I20: =IFERROR(IF(OR(E20="",F20=""),"",MAX(0,G20-F20)),"") | K20: =IFERROR(IF(I20="","",I20*0.8),"")
A21: 3 | G21: =IFERROR(IF(E21="","",E21/1.08),"") | H21: =IFERROR(IF(E21="","",E21-G21),"") | I21: =IFERROR(IF(OR(E21="",F21=""),"",MAX(0,G21-F21)),"") | K21: =IFERROR(IF(I21="","",I21*0.8),"")
A22: 4 | G22: =IFERROR(IF(E22="","",E22/1.08),"") | H22: =IFERROR(IF(E22="","",E22-G22),"") | I22: =IFERROR(IF(OR(E22="",F22=""),"",MAX(0,G22-F22)),"") | K22: =IFERROR(IF(I22="","",I22*0.8),"")
A23: TỔNG CỘNG 4 GIAO DỊCH | E23: =IFERROR(SUM(E19:E22),0) | F23: =IFERROR(SUM(F19:F22),0) | G23: =IFERROR(SUM(G19:G22),0) | H23: =IFERROR(SUM(H19:H22),0) | I23: =IFERROR(SUM(I19:I22),0) | K23: =IFERROR(SUM(J19:J22),0)
A24: 🧾 Công thức: VAT = Tiền chuyển × 8/108 • Phần kênh = Giá chưa VAT − Giá thực • Trả khách = Phần kênh × 80%
A26: ③ PHIẾU ĐẶT HÀNG CÓ VAT 8% — Xuất hóa đơn cho khách
A27: Khách hàng: | G27: Số phiếu:
A28: Địa chỉ: | G28: Ngày: | H28: =TODAY()
A29: STT | B29: MÃ SP | C29: TÊN SẢN PHẨM | D29: ĐVT | E29: SỐ LƯỢNG | F29: ĐƠN GIÁ (VNĐ) | G29: THÀNH TIỀN (VNĐ) | H29: VAT 8% (VNĐ) | I29: TỔNG CỘNG (VNĐ) | K29: GHI CHÚ
A30: 1 | E30: 1 | F30: 5150000 | G30: =IFERROR(E30*F30,0) | H30: =IFERROR(G30*0.08,0) | I30: =IFERROR(G30+H30,0)
A31: 2 | G31: =IFERROR(E31*F31,0) | H31: =IFERROR(G31*0.08,0) | I31: =IFERROR(G31+H31,0)
A32: 3 | G32: =IFERROR(E32*F32,0) | H32: =IFERROR(G32*0.08,0) | I32: =IFERROR(G32+H32,0)
A33: 4 | G33: =IFERROR(E33*F33,0) | H33: =IFERROR(G33*0.08,0) | I33: =IFERROR(G33+H33,0)
A34: 5 | G34: =IFERROR(E34*F34,0) | H34: =IFERROR(G34*0.08,0) | I34: =IFERROR(G34+H34,0)
A35: 6 | G35: =IFERROR(E35*F35,0) | H35: =IFERROR(G35*0.08,0) | I35: =IFERROR(G35+H35,0)
A36: 7 | G36: =IFERROR(E36*F36,0) | H36: =IFERROR(G36*0.08,0) | I36: =IFERROR(G36+H36,0)
A37: 8 | G37: =IFERROR(E37*F37,0) | H37: =IFERROR(G37*0.08,0) | I37: =IFERROR(G37+H37,0)
A38: 9 | G38: =IFERROR(E38*F38,0) | H38: =IFERROR(G38*0.08,0) | I38: =IFERROR(G38+H38,0)
A39: 10 | G39: =IFERROR(E39*F39,0) | H39: =IFERROR(G39*0.08,0) | I39: =IFERROR(G39+H39,0)
A40: TỔNG CỘNG | G40: =SUM(G30:G39) | H40: =SUM(H30:H39) | I40: =SUM(I30:I39)
A41: Tổng tiền hàng (chưa VAT): | I41: =G40
A42: Tổng VAT 8%: | I42: =H40
A43: 💰 TỔNG THANH TOÁN: | I43: =I40
A44: 📝 SỐ TIỀN THANH TOÁN BẰNG CHỮ:
A46: Người lập | D46: Kế toán | F46: Khách ký nhận | I46: Giám đốc
A47: (Ký, ghi rõ họ tên) | D47: (Ký, ghi rõ họ tên) | F47: (Ký, ghi rõ họ tên) | I47: (Ký, ghi rõ họ tên)

Sheet 💰 BÁO GIÁ
B1: CÔNG TY TNHH MÁY CÔNG TRÌNH MIỀN NAM | N1: =MATCH($C$9,{"Giá vốn";"Giá VIP";"Giá ưu đãi";"Giá đại lý";"Giá gara"},0)+4
B2: Địa chỉ: ………………… | ĐT: ………………… | MST: …………………
B4: PHIẾU BÁO GIÁ
B5: Số: | C5: BG-001 | G5: Ngày: | H5: =TODAY() | I5: VAT (%): | J5: 0.08
B6: Khách hàng: | G6: Điện thoại: | H6: =IFERROR(VLOOKUP($C$6,'👥 KHÁCH HÀNG'!$A:$E,2,0),"")
B7: Địa chỉ: | C7: =IFERROR(VLOOKUP($C$6,'👥 KHÁCH HÀNG'!$A:$E,3,0),"") | G7: MST: | H7: =IFERROR(VLOOKUP($C$6,'👥 KHÁCH HÀNG'!$A:$E,4,0),"")
B8: Nhà xe: | C8: =IFERROR(VLOOKUP($C$6,'👥 KHÁCH HÀNG'!$A:$I,9,0),"") | G8: Giờ nhận: | H8: =IFERROR(VLOOKUP($C$8,'🚛 NHÀ XE'!$A:$F,2,0)&" · "&VLOOKUP($C$8,'🚛 NHÀ XE'!$A:$F,3,0),"")
B9: Bảng giá áp dụng: | C9: Giá VIP
B10: STT | C10: Mã HH | D10: Tên vật tư sản phẩm | E10: ĐVT | F10: Số lượng | G10: Đơn giá (chưa VAT) | H10: Thành tiền (chưa VAT) | I10: Thuế VAT (8%) | J10: Tổng tiền (gồm VAT) | K10: 🎚️ Cấp giá
B11: 1 | D11: =IFERROR(VLOOKUP($C11,'📂 DATA'!$A:$I,2,0),"") | E11: =IFERROR(VLOOKUP($C11,'📂 DATA'!$A:$I,4,0),"") | G11: =IFERROR(VLOOKUP($C11,'📂 DATA'!$A:$J,MATCH(IF($K11="",$C$9,$K11),{"Giá vốn";"Giá VIP";"Giá ưu đãi";"Giá đại lý";"Giá gara"},0)+4,0),"") | H11: =IF($C11="","",N($F11)*N($G11)) | I11: =IF($C11="","",$H11*$J$5) | J11: =IF($C11="","",$H11+$I11)
B12: 2 | D12: =IFERROR(VLOOKUP($C12,'📂 DATA'!$A:$I,2,0),"") | E12: =IFERROR(VLOOKUP($C12,'📂 DATA'!$A:$I,4,0),"") | G12: =IFERROR(VLOOKUP($C12,'📂 DATA'!$A:$J,MATCH(IF($K12="",$C$9,$K12),{"Giá vốn";"Giá VIP";"Giá ưu đãi";"Giá đại lý";"Giá gara"},0)+4,0),"") | H12: =IF($C12="","",N($F12)*N($G12)) | I12: =IF($C12="","",$H12*$J$5) | J12: =IF($C12="","",$H12+$I12)
B13: 3 | D13: =IFERROR(VLOOKUP($C13,'📂 DATA'!$A:$I,2,0),"") | E13: =IFERROR(VLOOKUP($C13,'📂 DATA'!$A:$I,4,0),"") | G13: =IFERROR(VLOOKUP($C13,'📂 DATA'!$A:$J,MATCH(IF($K13="",$C$9,$K13),{"Giá vốn";"Giá VIP";"Giá ưu đãi";"Giá đại lý";"Giá gara"},0)+4,0),"") | H13: =IF($C13="","",N($F13)*N($G13)) | I13: =IF($C13="","",$H13*$J$5) | J13: =IF($C13="","",$H13+$I13)
B14: 4 | D14: =IFERROR(VLOOKUP($C14,'📂 DATA'!$A:$I,2,0),"") | E14: =IFERROR(VLOOKUP($C14,'📂 DATA'!$A:$I,4,0),"") | G14: =IFERROR(VLOOKUP($C14,'📂 DATA'!$A:$J,MATCH(IF($K14="",$C$9,$K14),{"Giá vốn";"Giá VIP";"Giá ưu đãi";"Giá đại lý";"Giá gara"},0)+4,0),"") | H14: =IF($C14="","",N($F14)*N($G14)) | I14: =IF($C14="","",$H14*$J$5) | J14: =IF($C14="","",$H14+$I14)
B15: 5 | D15: =IFERROR(VLOOKUP($C15,'📂 DATA'!$A:$I,2,0),"") | E15: =IFERROR(VLOOKUP($C15,'📂 DATA'!$A:$I,4,0),"") | G15: =IFERROR(VLOOKUP($C15,'📂 DATA'!$A:$J,MATCH(IF($K15="",$C$9,$K15),{"Giá vốn";"Giá VIP";"Giá ưu đãi";"Giá đại lý";"Giá gara"},0)+4,0),"") | H15: =IF($C15="","",N($F15)*N($G15)) | I15: =IF($C15="","",$H15*$J$5) | J15: =IF($C15="","",$H15+$I15)
B16: 6 | D16: =IFERROR(VLOOKUP($C16,'📂 DATA'!$A:$I,2,0),"") | E16: =IFERROR(VLOOKUP($C16,'📂 DATA'!$A:$I,4,0),"") | G16: =IFERROR(VLOOKUP($C16,'📂 DATA'!$A:$J,MATCH(IF($K16="",$C$9,$K16),{"Giá vốn";"Giá VIP";"Giá ưu đãi";"Giá đại lý";"Giá gara"},0)+4,0),"") | H16: =IF($C16="","",N($F16)*N($G16)) | I16: =IF($C16="","",$H16*$J$5) | J16: =IF($C16="","",$H16+$I16)
B17: 7 | D17: =IFERROR(VLOOKUP($C17,'📂 DATA'!$A:$I,2,0),"") | E17: =IFERROR(VLOOKUP($C17,'📂 DATA'!$A:$I,4,0),"") | G17: =IFERROR(VLOOKUP($C17,'📂 DATA'!$A:$J,MATCH(IF($K17="",$C$9,$K17),{"Giá vốn";"Giá VIP";"Giá ưu đãi";"Giá đại lý";"Giá gara"},0)+4,0),"") | H17: =IF($C17="","",N($F17)*N($G17)) | I17: =IF($C17="","",$H17*$J$5) | J17: =IF($C17="","",$H17+$I17)
B18: 8 | D18: =IFERROR(VLOOKUP($C18,'📂 DATA'!$A:$I,2,0),"") | E18: =IFERROR(VLOOKUP($C18,'📂 DATA'!$A:$I,4,0),"") | G18: =IFERROR(VLOOKUP($C18,'📂 DATA'!$A:$J,MATCH(IF($K18="",$C$9,$K18),{"Giá vốn";"Giá VIP";"Giá ưu đãi";"Giá đại lý";"Giá gara"},0)+4,0),"") | H18: =IF($C18="","",N($F18)*N($G18)) | I18: =IF($C18="","",$H18*$J$5) | J18: =IF($C18="","",$H18+$I18)
B19: Tổng cộng | F19: =SUM($F$11:$F$18) | H19: =SUM($H$11:$H$18) | I19: =SUM($I$11:$I$18) | J19: =SUM($J$11:$J$18)
B20: ="Bằng chữ: "&IFERROR(IF(OR($J$19="",$J$19=0),"Không đồng./.",UPPER(LEFT(TRIM(IF(INT($J$19/1000000000)>0,VLOOKUP(INT($J$19/1000000000),_LOOKUP_VND!A:C,3,FALSE())&" tỷ ","")&IF(MOD(INT($J$19/1000000),1000)>0,IF(INT($J$19/1000000000)>0,VLOOKUP(MOD(INT($J$19/1000000),1000),_LOOKUP_VND!A:C,2,FALSE()),VLOOKUP(MOD(INT($J$19/1000000),1000),_LOOKUP_VND!A:C,3,FALSE()))&" triệu ","")&IF(MOD(INT($J$19/1000),1000)>0,IF(OR(INT($J$19/1000000000)>0,MOD(INT($J$19/1000000),1000)>0),VLOOKUP(MOD(INT($J$19/1000),1000),_LOOKUP_VND!A:C,2,FALSE()),VLOOKUP(MOD(INT($J$19/1000),1000),_LOOKUP_VND!A:C,3,FALSE()))&" nghìn ","")&IF(MOD($J$19,1000)>0,IF(OR(INT($J$19/1000000000)>0,MOD(INT($J$19/1000000),1000)>0,MOD(INT($J$19/1000),1000)>0),VLOOKUP(MOD($J$19,1000),_LOOKUP_VND!A:C,2,FALSE()),VLOOKUP(MOD($J$19,1000),_LOOKUP_VND!A:C,3,FALSE()))&" ","")),1))&MID(TRIM(IF(INT($J$19/1000000000)>0,VLOOKUP(INT($J$19/1000000000),_LOOKUP_VND!A:C,3,FALSE())&" tỷ ","")&IF(MOD(INT($J$19/1000000),1000)>0,IF(INT($J$19/1000000000)>0,VLOOKUP(MOD(INT($J$19/1000000),1000),_LOOKUP_VND!A:C,2,FALSE()),VLOOKUP(MOD(INT($J$19/1000000),1000),_LOOKUP_VND!A:C,3,FALSE()))&" triệu ","")&IF(MOD(INT($J$19/1000),1000)>0,IF(OR(INT($J$19/1000000000)>0,MOD(INT($J$19/1000000),1000)>0),VLOOKUP(MOD(INT($J$19/1000),1000),_LOOKUP_VND!A:C,2,FALSE()),VLOOKUP(MOD(INT($J$19/1000),1000),_LOOKUP_VND!A:C,3,FALSE()))&" nghìn ","")&IF(MOD($J$19,1000)>0,IF(OR(INT($J$19/1000000000)>0,MOD(INT($J$19/1000000),1000)>0,MOD(INT($J$19/1000),1000)>0),VLOOKUP(MOD($J$19,1000),_LOOKUP_VND!A:C,2,FALSE()),VLOOKUP(MOD($J$19,1000),_LOOKUP_VND!A:C,3,FALSE()))&" ","")),2,LEN(TRIM(IF(INT($J$19/1000000000)>0,VLOOKUP(INT($J$19/1000000000),_LOOKUP_VND!A:C,3,FALSE())&" tỷ ","")&IF(MOD(INT($J$19/1000000),1000)>0,IF(INT($J$19/1000000000)>0,VLOOKUP(MOD(INT($J$19/1000000),1000),_LOOKUP_VND!A:C,2,FALSE()),VLOOKUP(MOD(INT($J$19/1000000),1000),_LOOKUP_VND!A:C,3,FALSE()))&" triệu ","")&IF(MOD(INT($J$19/1000),1000)>0,IF(OR(INT($J$19/1000000000)>0,MOD(INT($J$19/1000000),1000)>0),VLOOKUP(MOD(INT($J$19/1000),1000),_LOOKUP_VND!A:C,2,FALSE()),VLOOKUP(MOD(INT($J$19/1000),1000),_LOOKUP_VND!A:C,3,FALSE()))&" nghìn ","")&IF(MOD($J$19,1000)>0,IF(OR(INT($J$19/1000000000)>0,MOD(INT($J$19/1000000),1000)>0,MOD(INT($J$19/1000),1000)>0),VLOOKUP(MOD($J$19,1000),_LOOKUP_VND!A:C,2,FALSE()),VLOOKUP(MOD($J$19,1000),_LOOKUP_VND!A:C,3,FALSE()))&" ",""))))&" đồng chẵn./."),"⚠ Lỗi đọc số")
C22: KHÁCH HÀNG | H22: NGƯỜI BÁO GIÁ
H23: Luân Nguyễn
B26: ──────── 🔎 TÌM NHANH (không in ra) ────────
B27: 🔎 Gõ:
C28: Mã HH | D28: Tên hàng | E28: ĐVT | F28: ĐK | G28: Giá vốn | H28: Giá VIP | I28: Giá ưu đãi | J28: Giá đại lý | K28: Giá gara
C29: =IF(M29="","",INDEX('📂 DATA'!$A$2:$A$7684,M29)) | D29: =IF(M29="","",INDEX('📂 DATA'!$B$2:$B$7684,M29)) | E29: =IF(M29="","",INDEX('📂 DATA'!$D$2:$D$7684,M29)) | F29: =IF(M29="","",INDEX('📂 DATA'!$J$2:$J$7684,M29)) | G29: =IF(M29="","",INDEX('📂 DATA'!$E$2:$E$7684,M29)) | H29: =IF(M29="","",INDEX('📂 DATA'!$F$2:$F$7684,M29)) | I29: =IF(M29="","",INDEX('📂 DATA'!$G$2:$G$7684,M29)) | J29: =IF(M29="","",INDEX('📂 DATA'!$H$2:$H$7684,M29)) | K29: =IF(M29="","",INDEX('📂 DATA'!$I$2:$I$7684,M29)) | M29: =IFERROR(MATCH(1,'📂 DATA'!$O$2:$O$7684,0),"")
C30: =IF(M30="","",INDEX('📂 DATA'!$A$2:$A$7684,M30)) | D30: =IF(M30="","",INDEX('📂 DATA'!$B$2:$B$7684,M30)) | E30: =IF(M30="","",INDEX('📂 DATA'!$D$2:$D$7684,M30)) | F30: =IF(M30="","",INDEX('📂 DATA'!$J$2:$J$7684,M30)) | G30: =IF(M30="","",INDEX('📂 DATA'!$E$2:$E$7684,M30)) | H30: =IF(M30="","",INDEX('📂 DATA'!$F$2:$F$7684,M30)) | I30: =IF(M30="","",INDEX('📂 DATA'!$G$2:$G$7684,M30)) | J30: =IF(M30="","",INDEX('📂 DATA'!$H$2:$H$7684,M30)) | K30: =IF(M30="","",INDEX('📂 DATA'!$I$2:$I$7684,M30)) | M30: =IFERROR(MATCH(2,'📂 DATA'!$O$2:$O$7684,0),"")
C31: =IF(M31="","",INDEX('📂 DATA'!$A$2:$A$7684,M31)) | D31: =IF(M31="","",INDEX('📂 DATA'!$B$2:$B$7684,M31)) | E31: =IF(M31="","",INDEX('📂 DATA'!$D$2:$D$7684,M31)) | F31: =IF(M31="","",INDEX('📂 DATA'!$J$2:$J$7684,M31)) | G31: =IF(M31="","",INDEX('📂 DATA'!$E$2:$E$7684,M31)) | H31: =IF(M31="","",INDEX('📂 DATA'!$F$2:$F$7684,M31)) | I31: =IF(M31="","",INDEX('📂 DATA'!$G$2:$G$7684,M31)) | J31: =IF(M31="","",INDEX('📂 DATA'!$H$2:$H$7684,M31)) | K31: =IF(M31="","",INDEX('📂 DATA'!$I$2:$I$7684,M31)) | M31: =IFERROR(MATCH(3,'📂 DATA'!$O$2:$O$7684,0),"")
C32: =IF(M32="","",INDEX('📂 DATA'!$A$2:$A$7684,M32)) | D32: =IF(M32="","",INDEX('📂 DATA'!$B$2:$B$7684,M32)) | E32: =IF(M32="","",INDEX('📂 DATA'!$D$2:$D$7684,M32)) | F32: =IF(M32="","",INDEX('📂 DATA'!$J$2:$J$7684,M32)) | G32: =IF(M32="","",INDEX('📂 DATA'!$E$2:$E$7684,M32)) | H32: =IF(M32="","",INDEX('📂 DATA'!$F$2:$F$7684,M32)) | I32: =IF(M32="","",INDEX('📂 DATA'!$G$2:$G$7684,M32)) | J32: =IF(M32="","",INDEX('📂 DATA'!$H$2:$H$7684,M32)) | K32: =IF(M32="","",INDEX('📂 DATA'!$I$2:$I$7684,M32)) | M32: =IFERROR(MATCH(4,'📂 DATA'!$O$2:$O$7684,0),"")
C33: =IF(M33="","",INDEX('📂 DATA'!$A$2:$A$7684,M33)) | D33: =IF(M33="","",INDEX('📂 DATA'!$B$2:$B$7684,M33)) | E33: =IF(M33="","",INDEX('📂 DATA'!$D$2:$D$7684,M33)) | F33: =IF(M33="","",INDEX('📂 DATA'!$J$2:$J$7684,M33)) | G33: =IF(M33="","",INDEX('📂 DATA'!$E$2:$E$7684,M33)) | H33: =IF(M33="","",INDEX('📂 DATA'!$F$2:$F$7684,M33)) | I33: =IF(M33="","",INDEX('📂 DATA'!$G$2:$G$7684,M33)) | J33: =IF(M33="","",INDEX('📂 DATA'!$H$2:$H$7684,M33)) | K33: =IF(M33="","",INDEX('📂 DATA'!$I$2:$I$7684,M33)) | M33: =IFERROR(MATCH(5,'📂 DATA'!$O$2:$O$7684,0),"")
C34: =IF(M34="","",INDEX('📂 DATA'!$A$2:$A$7684,M34)) | D34: =IF(M34="","",INDEX('📂 DATA'!$B$2:$B$7684,M34)) | E34: =IF(M34="","",INDEX('📂 DATA'!$D$2:$D$7684,M34)) | F34: =IF(M34="","",INDEX('📂 DATA'!$J$2:$J$7684,M34)) | G34: =IF(M34="","",INDEX('📂 DATA'!$E$2:$E$7684,M34)) | H34: =IF(M34="","",INDEX('📂 DATA'!$F$2:$F$7684,M34)) | I34: =IF(M34="","",INDEX('📂 DATA'!$G$2:$G$7684,M34)) | J34: =IF(M34="","",INDEX('📂 DATA'!$H$2:$H$7684,M34)) | K34: =IF(M34="","",INDEX('📂 DATA'!$I$2:$I$7684,M34)) | M34: =IFERROR(MATCH(6,'📂 DATA'!$O$2:$O$7684,0),"")
C35: =IF(M35="","",INDEX('📂 DATA'!$A$2:$A$7684,M35)) | D35: =IF(M35="","",INDEX('📂 DATA'!$B$2:$B$7684,M35)) | E35: =IF(M35="","",INDEX('📂 DATA'!$D$2:$D$7684,M35)) | F35: =IF(M35="","",INDEX('📂 DATA'!$J$2:$J$7684,M35)) | G35: =IF(M35="","",INDEX('📂 DATA'!$E$2:$E$7684,M35)) | H35: =IF(M35="","",INDEX('📂 DATA'!$F$2:$F$7684,M35)) | I35: =IF(M35="","",INDEX('📂 DATA'!$G$2:$G$7684,M35)) | J35: =IF(M35="","",INDEX('📂 DATA'!$H$2:$H$7684,M35)) | K35: =IF(M35="","",INDEX('📂 DATA'!$I$2:$I$7684,M35)) | M35: =IFERROR(MATCH(7,'📂 DATA'!$O$2:$O$7684,0),"")
C36: =IF(M36="","",INDEX('📂 DATA'!$A$2:$A$7684,M36)) | D36: =IF(M36="","",INDEX('📂 DATA'!$B$2:$B$7684,M36)) | E36: =IF(M36="","",INDEX('📂 DATA'!$D$2:$D$7684,M36)) | F36: =IF(M36="","",INDEX('📂 DATA'!$J$2:$J$7684,M36)) | G36: =IF(M36="","",INDEX('📂 DATA'!$E$2:$E$7684,M36)) | H36: =IF(M36="","",INDEX('📂 DATA'!$F$2:$F$7684,M36)) | I36: =IF(M36="","",INDEX('📂 DATA'!$G$2:$G$7684,M36)) | J36: =IF(M36="","",INDEX('📂 DATA'!$H$2:$H$7684,M36)) | K36: =IF(M36="","",INDEX('📂 DATA'!$I$2:$I$7684,M36)) | M36: =IFERROR(MATCH(8,'📂 DATA'!$O$2:$O$7684,0),"")
C37: =IF(M37="","",INDEX('📂 DATA'!$A$2:$A$7684,M37)) | D37: =IF(M37="","",INDEX('📂 DATA'!$B$2:$B$7684,M37)) | E37: =IF(M37="","",INDEX('📂 DATA'!$D$2:$D$7684,M37)) | F37: =IF(M37="","",INDEX('📂 DATA'!$J$2:$J$7684,M37)) | G37: =IF(M37="","",INDEX('📂 DATA'!$E$2:$E$7684,M37)) | H37: =IF(M37="","",INDEX('📂 DATA'!$F$2:$F$7684,M37)) | I37: =IF(M37="","",INDEX('📂 DATA'!$G$2:$G$7684,M37)) | J37: =IF(M37="","",INDEX('📂 DATA'!$H$2:$H$7684,M37)) | K37: =IF(M37="","",INDEX('📂 DATA'!$I$2:$I$7684,M37)) | M37: =IFERROR(MATCH(9,'📂 DATA'!$O$2:$O$7684,0),"")
C38: =IF(M38="","",INDEX('📂 DATA'!$A$2:$A$7684,M38)) | D38: =IF(M38="","",INDEX('📂 DATA'!$B$2:$B$7684,M38)) | E38: =IF(M38="","",INDEX('📂 DATA'!$D$2:$D$7684,M38)) | F38: =IF(M38="","",INDEX('📂 DATA'!$J$2:$J$7684,M38)) | G38: =IF(M38="","",INDEX('📂 DATA'!$E$2:$E$7684,M38)) | H38: =IF(M38="","",INDEX('📂 DATA'!$F$2:$F$7684,M38)) | I38: =IF(M38="","",INDEX('📂 DATA'!$G$2:$G$7684,M38)) | J38: =IF(M38="","",INDEX('📂 DATA'!$H$2:$H$7684,M38)) | K38: =IF(M38="","",INDEX('📂 DATA'!$I$2:$I$7684,M38)) | M38: =IFERROR(MATCH(10,'📂 DATA'!$O$2:$O$7684,0),"")
C39: =IF(M39="","",INDEX('📂 DATA'!$A$2:$A$7684,M39)) | D39: =IF(M39="","",INDEX('📂 DATA'!$B$2:$B$7684,M39)) | E39: =IF(M39="","",INDEX('📂 DATA'!$D$2:$D$7684,M39)) | F39: =IF(M39="","",INDEX('📂 DATA'!$J$2:$J$7684,M39)) | G39: =IF(M39="","",INDEX('📂 DATA'!$E$2:$E$7684,M39)) | H39: =IF(M39="","",INDEX('📂 DATA'!$F$2:$F$7684,M39)) | I39: =IF(M39="","",INDEX('📂 DATA'!$G$2:$G$7684,M39)) | J39: =IF(M39="","",INDEX('📂 DATA'!$H$2:$H$7684,M39)) | K39: =IF(M39="","",INDEX('📂 DATA'!$I$2:$I$7684,M39)) | M39: =IFERROR(MATCH(11,'📂 DATA'!$O$2:$O$7684,0),"")
C40: =IF(M40="","",INDEX('📂 DATA'!$A$2:$A$7684,M40)) | D40: =IF(M40="","",INDEX('📂 DATA'!$B$2:$B$7684,M40)) | E40: =IF(M40="","",INDEX('📂 DATA'!$D$2:$D$7684,M40)) | F40: =IF(M40="","",INDEX('📂 DATA'!$J$2:$J$7684,M40)) | G40: =IF(M40="","",INDEX('📂 DATA'!$E$2:$E$7684,M40)) | H40: =IF(M40="","",INDEX('📂 DATA'!$F$2:$F$7684,M40)) | I40: =IF(M40="","",INDEX('📂 DATA'!$G$2:$G$7684,M40)) | J40: =IF(M40="","",INDEX('📂 DATA'!$H$2:$H$7684,M40)) | K40: =IF(M40="","",INDEX('📂 DATA'!$I$2:$I$7684,M40)) | M40: =IFERROR(MATCH(12,'📂 DATA'!$O$2:$O$7684,0),"")

Sheet ⚙️ BỘ HƠI
B1: ⚙️ GOM BỘ HƠI (Piston + Séc măng + Xy lanh)
B2: Chọn Piston → Xy lanh → Séc măng. Báo theo BỘ; SL = số máy. Cảnh báo nếu lệch đời máy / sai mạ. | H2: =IF($H$40=0,"",IFERROR(IF(INDEX('🔩 PISTON'!$C$3:$C$1371,$H$40)=0,"",INDEX('🔩 PISTON'!$C$3:$C$1371,$H$40)),""))
H3: =IF($H$40=0,"",IFERROR(IF(INDEX('🔩 PISTON'!$D$3:$D$1371,$H$40)=0,"",INDEX('🔩 PISTON'!$D$3:$D$1371,$H$40)),""))
B4: ① Chọn Piston: | C4: KOMATSU 4D130 · ĐK130 (A) | E4: Mã HH: | H4: =IF($H$40=0,0,IFERROR(INDEX('🔩 PISTON'!$N$3:$N$1371,$H$40),0))
B5: ② Chọn Xy lanh: | C5: Xy lanh 4D130 (123503/N-6115-21-2211) - NSP | E5: Mã HH: | H5: =IF($H$6="kiếng","Không mạ",IF($H$6="gang","Có mạ","—"))
B6: ③ Chọn Séc măng: | C6: Séc măng 4D130/ 3.5-2.5-5.5 (SDK04011ZZ) - NPR | E6: Mã HH: | H6: =IF($H$41=0,"",IFERROR(IF(INDEX('🔧 XY LANH'!$F$3:$F$1100,$H$41)=0,"",INDEX('🔧 XY LANH'!$F$3:$F$1100,$H$41)),""))
H7: =IF($H$41=0,0,IFERROR(INDEX('🔧 XY LANH'!$J$3:$J$1100,$H$41),0))
B8: Thành phần | C8: Mã HH | D8: Chi tiết | F8: Giá (bộ) | H8: =IF($H$42=0,0,IFERROR(INDEX('⚙️ SÉC MĂNG'!$K$3:$K$1100,$H$42),0))
B9: 🔩 Piston | C9: =$H$34 | D9: =IF($H$40=0,"(chưa chọn)",$H$2&IF($H$21=""," "," · "&$H$21)&IF($H$11=""," "," · "&$H$11)&IF($H$12=""," "," · Ắc "&$H$12)&IF($H$13=""," "," · Ắc đỉnh "&$H$13)&IF($H$14=""," "," · Dài "&$H$14)&IF($H$33=""," "," · "&$H$33)&IF($H$15=""," "," ("&$H$15&")")) | F9: =$H$4
B10: 🔧 Xy lanh | C10: =$H$35 | D10: =IF($H$41=0,IF($H$40=0,"(chưa chọn)","⚠️ Đời máy này chưa tự dò ra — chọn tay ở ② hoặc gõ Mã HH"),$H$37) | F10: =$H$7 | H10: =IF($H$40=0,"",IFERROR(IF(INDEX('🔩 PISTON'!$E$3:$E$1371,$H$40)=0,"",INDEX('🔩 PISTON'!$E$3:$E$1371,$H$40)),""))
B11: ⚙️ Séc măng | C11: =$H$36 | D11: =IF($H$42=0,IF($H$40=0,"(chưa chọn)","⚠️ chưa tự dò ra — chọn tay ở ③ hoặc gõ Mã HH"),$H$26&" · "&IF($H$19=""," ",$H$19&" · ")&"Ring "&$H$18&" · "&$H$17) | F11: =$H$8 | H11: =IF($H$40=0,"",IFERROR(IF(INDEX('🔩 PISTON'!$F$3:$F$1371,$H$40)=0,"",INDEX('🔩 PISTON'!$F$3:$F$1371,$H$40)),""))
B12: 📦 Đơn vị | C12: =IF($H$41=0,"(chọn xy lanh)","BỘ "&$H$20&" MÁY") | H12: =IF($H$40=0,"",IFERROR(IF(INDEX('🔩 PISTON'!$G$3:$G$1371,$H$40)=0,"",INDEX('🔩 PISTON'!$G$3:$G$1371,$H$40)),""))
B13: 💰 ĐƠN GIÁ 1 BỘ | F13: =$H$4+$H$7+$H$8 | H13: =IF($H$40=0,"",IFERROR(IF(INDEX('🔩 PISTON'!$H$3:$H$1371,$H$40)=0,"",INDEX('🔩 PISTON'!$H$3:$H$1371,$H$40)),""))
B14: 🔢 Số lượng (bộ) | F14: 1 | H14: =IF($H$40=0,"",IFERROR(IF(INDEX('🔩 PISTON'!$I$3:$I$1371,$H$40)=0,"",INDEX('🔩 PISTON'!$I$3:$I$1371,$H$40)),""))
B15: 💵 THÀNH TIỀN | F15: =$F$13*$F$14 | H15: =IF($H$40=0,"",IFERROR(IF(INDEX('🔩 PISTON'!$J$3:$J$1371,$H$40)=0,"",INDEX('🔩 PISTON'!$J$3:$J$1371,$H$40)),""))
B16: 📝 Bằng chữ | C16: =IFERROR(IF(OR($F$15="",$F$15=0),"Không đồng./.",UPPER(LEFT(TRIM(IF(INT($F$15/1000000000)>0,VLOOKUP(INT($F$15/1000000000),_LOOKUP_VND!A:C,3,FALSE())&" tỷ ","")&IF(MOD(INT($F$15/1000000),1000)>0,IF(INT($F$15/1000000000)>0,VLOOKUP(MOD(INT($F$15/1000000),1000),_LOOKUP_VND!A:C,2,FALSE()),VLOOKUP(MOD(INT($F$15/1000000),1000),_LOOKUP_VND!A:C,3,FALSE()))&" triệu ","")&IF(MOD(INT($F$15/1000),1000)>0,IF(OR(INT($F$15/1000000000)>0,MOD(INT($F$15/1000000),1000)>0),VLOOKUP(MOD(INT($F$15/1000),1000),_LOOKUP_VND!A:C,2,FALSE()),VLOOKUP(MOD(INT($F$15/1000),1000),_LOOKUP_VND!A:C,3,FALSE()))&" nghìn ","")&IF(MOD($F$15,1000)>0,IF(OR(INT($F$15/1000000000)>0,MOD(INT($F$15/1000000),1000)>0,MOD(INT($F$15/1000),1000)>0),VLOOKUP(MOD($F$15,1000),_LOOKUP_VND!A:C,2,FALSE()),VLOOKUP(MOD($F$15,1000),_LOOKUP_VND!A:C,3,FALSE()))&" ","")),1))&MID(TRIM(IF(INT($F$15/1000000000)>0,VLOOKUP(INT($F$15/1000000000),_LOOKUP_VND!A:C,3,FALSE())&" tỷ ","")&IF(MOD(INT($F$15/1000000),1000)>0,IF(INT($F$15/1000000000)>0,VLOOKUP(MOD(INT($F$15/1000000),1000),_LOOKUP_VND!A:C,2,FALSE()),VLOOKUP(MOD(INT($F$15/1000000),1000),_LOOKUP_VND!A:C,3,FALSE()))&" triệu ","")&IF(MOD(INT($F$15/1000),1000)>0,IF(OR(INT($F$15/1000000000)>0,MOD(INT($F$15/1000000),1000)>0),VLOOKUP(MOD(INT($F$15/1000),1000),_LOOKUP_VND!A:C,2,FALSE()),VLOOKUP(MOD(INT($F$15/1000),1000),_LOOKUP_VND!A:C,3,FALSE()))&" nghìn ","")&IF(MOD($F$15,1000)>0,IF(OR(INT($F$15/1000000000)>0,MOD(INT($F$15/1000000),1000)>0,MOD(INT($F$15/1000),1000)>0),VLOOKUP(MOD($F$15,1000),_LOOKUP_VND!A:C,2,FALSE()),VLOOKUP(MOD($F$15,1000),_LOOKUP_VND!A:C,3,FALSE()))&" ","")),2,LEN(TRIM(IF(INT($F$15/1000000000)>0,VLOOKUP(INT($F$15/1000000000),_LOOKUP_VND!A:C,3,FALSE())&" tỷ ","")&IF(MOD(INT($F$15/1000000),1000)>0,IF(INT($F$15/1000000000)>0,VLOOKUP(MOD(INT($F$15/1000000),1000),_LOOKUP_VND!A:C,2,FALSE()),VLOOKUP(MOD(INT($F$15/1000000),1000),_LOOKUP_VND!A:C,3,FALSE()))&" triệu ","")&IF(MOD(INT($F$15/1000),1000)>0,IF(OR(INT($F$15/1000000000)>0,MOD(INT($F$15/1000000),1000)>0),VLOOKUP(MOD(INT($F$15/1000),1000),_LOOKUP_VND!A:C,2,FALSE()),VLOOKUP(MOD(INT($F$15/1000),1000),_LOOKUP_VND!A:C,3,FALSE()))&" nghìn ","")&IF(MOD($F$15,1000)>0,IF(OR(INT($F$15/1000000000)>0,MOD(INT($F$15/1000000),1000)>0,MOD(INT($F$15/1000),1000)>0),VLOOKUP(MOD($F$15,1000),_LOOKUP_VND!A:C,2,FALSE()),VLOOKUP(MOD($F$15,1000),_LOOKUP_VND!A:C,3,FALSE()))&" ",""))))&" đồng chẵn./."),"⚠ Lỗi đọc số")
H17: =IF($H$42=0,"",IFERROR(IF(INDEX('⚙️ SÉC MĂNG'!$H$3:$H$1100,$H$42)=0,"",INDEX('⚙️ SÉC MĂNG'!$H$3:$H$1100,$H$42)),""))
B18: =IF(OR($H$40=0,$H$41=0,$H$42=0),"⬆ Chọn đủ Piston + Xy lanh + Séc măng (theo tên hoặc Mã HH).",IF($H$32="SAI","⛔ XY LANH ("&$H$29&" ĐK"&$H$30&") KHÁC đời máy Piston ("&$H$2&" ĐK"&$H$3&") — KIỂM TRA LẠI!",IF($H$31="SAI","⛔ SÉC MĂNG ("&$H$26&" ĐK"&$H$27&") KHÁC đời máy Piston ("&$H$2&" ĐK"&$H$3&") — KIỂM TRA LẠI!",IF(AND($H$5<>"—",$H$5<>"",$H$19<>$H$5),"⚠️ Xy lanh "&$H$6&" nên dùng séc măng "&$H$5&" — đang chọn "&IF($H$19="","(không mạ)",$H$19)&".","✅ Đủ bộ hơi 3 món · cùng đời máy "&$H$2&IF($H$5="—"," (không phân mạ)"," · séc măng "&$H$19&" hợp xy lanh "&$H$6))))) | H18: =IF($H$42=0,"",IFERROR(IF(INDEX('⚙️ SÉC MĂNG'!$G$3:$G$1100,$H$42)=0,"",INDEX('⚙️ SÉC MĂNG'!$G$3:$G$1100,$H$42)),""))
H19: =IF($H$42=0,"",IFERROR(IF(INDEX('⚙️ SÉC MĂNG'!$F$3:$F$1100,$H$42)=0,"",INDEX('⚙️ SÉC MĂNG'!$F$3:$F$1100,$H$42)),""))
H20: =IF($H$41=0,"",IFERROR(IF(INDEX('🔧 XY LANH'!$E$3:$E$1100,$H$41)=0,"",INDEX('🔧 XY LANH'!$E$3:$E$1100,$H$41)),""))
H21: =IF($H$40=0,"",IF($H$10="(A)+(O)","chân ko",IF($H$10="(A)","kiềng gang",$H$10)))
H26: =IF($H$42=0,"",IFERROR(IF(INDEX('⚙️ SÉC MĂNG'!$C$3:$C$1100,$H$42)=0,"",INDEX('⚙️ SÉC MĂNG'!$C$3:$C$1100,$H$42)),""))
H27: =IF($H$42=0,"",IFERROR(IF(INDEX('⚙️ SÉC MĂNG'!$D$3:$D$1100,$H$42)=0,"",INDEX('⚙️ SÉC MĂNG'!$D$3:$D$1100,$H$42)),""))
H29: =IF($H$41=0,"",IFERROR(IF(INDEX('🔧 XY LANH'!$C$3:$C$1100,$H$41)=0,"",INDEX('🔧 XY LANH'!$C$3:$C$1100,$H$41)),""))
H30: =IF($H$41=0,"",IFERROR(IF(INDEX('🔧 XY LANH'!#REF!,$H$41)=0,"",INDEX('🔧 XY LANH'!#REF!,$H$41)),""))
H31: =IF(OR($H$40=0,$H$42=0),"",IF(OR(ISNUMBER(SEARCH($H$2,$H$26)),ISNUMBER(SEARCH($H$26,$H$2))),IF(OR($H$27="",$H$3="",$H$3=$H$27),"OK","SAI"),"SAI"))
H32: =IF(OR($H$40=0,$H$41=0),"",IF(OR(ISNUMBER(SEARCH($H$2,$H$29)),ISNUMBER(SEARCH($H$29,$H$2))),IF(OR($H$30="",$H$3="",$H$3=$H$30),"OK","SAI"),"SAI"))
H33: =IF($H$40=0,"",IFERROR(IF(INDEX('🔩 PISTON'!$K$3:$K$1371,$H$40)=0,"",INDEX('🔩 PISTON'!$K$3:$K$1371,$H$40)),""))
H34: =IF($H$40=0,"",IFERROR(IF(INDEX('🔩 PISTON'!$A$3:$A$1371,$H$40)=0,"",INDEX('🔩 PISTON'!$A$3:$A$1371,$H$40)),""))
H35: =IF($H$41=0,"",IFERROR(IF(INDEX('🔧 XY LANH'!$A$3:$A$1100,$H$41)=0,"",INDEX('🔧 XY LANH'!$A$3:$A$1100,$H$41)),""))
H36: =IF($H$42=0,"",IFERROR(IF(INDEX('⚙️ SÉC MĂNG'!$A$3:$A$1100,$H$42)=0,"",INDEX('⚙️ SÉC MĂNG'!$A$3:$A$1100,$H$42)),""))
H37: =IF($H$41=0,"",IFERROR(IF(INDEX('🔧 XY LANH'!$N$3:$N$1100,$H$41)=0,"",INDEX('🔧 XY LANH'!$N$3:$N$1100,$H$41)),""))
H40: =IFERROR(IF($F$4<>"",MATCH($F$4,'🔩 PISTON'!$A$3:$A$1371,0),IF($C$4<>"",MATCH($C$4,'🔩 PISTON'!$U$3:$U$1371,0),0)),0)
H41: =IFERROR(IF($F$5<>"",MATCH($F$5,'🔧 XY LANH'!$A$3:$A$1100,0),IF($C$5<>"",MATCH($C$5,'🔧 XY LANH'!$N$3:$N$1100,0),$H$43)),0)
H42: =IFERROR(IF($F$6<>"",MATCH($F$6,'⚙️ SÉC MĂNG'!$A$3:$A$1100,0),IF($C$6<>"",MATCH($C$6,'⚙️ SÉC MĂNG'!$R$3:$R$1100,0),$H$44)),0)
H43: =IF('⚙️ BỘ HƠI'!$H$40=0,0,IF(MIN('🔧 XY LANH'!$P$3:$P$1100)=99999,0,MIN('🔧 XY LANH'!$P$3:$P$1100)))
H44: =IF('⚙️ BỘ HƠI'!$H$40=0,0,IF(MIN('⚙️ SÉC MĂNG'!$S$3:$S$1100)=99999,0,MIN('⚙️ SÉC MĂNG'!$S$3:$S$1100)))

Sheet 📦 RON BỘ
A1: STT | B1: 🔖 MÃ VT | C1: 📋 TÊN HÀNG | D1: 📐 ĐK | E1: 🏭 HÃNG | F1: 🏷️ TH SX | G1: 📦 ĐVT | H1: 💰 GIÁ VỐN | I1: 🟢 GIÁ VIP | J1: 🟡 GIÁ Ư.ĐÃI | K1: 🔵 GIÁ ĐẠI LÝ | L1: 🟣 GIÁ GARA | M1: 📦 TỒN | N1: 📝 GHI CHÚ
C2: ◆ HINO (14 sản phẩm)
A3: 1 | B3: HH076479 | C3: Ron bộ Hino DM100 - Amiang - MASAKO | D3: 90 | E3: HINO | F3: MASAKO | G3: Bộ | I3: 630000 | J3: 670000 | K3: 720000
A4: 2 | B4: HH084235 | C4: Ron bộ Hino EC100, ASB Amiang - DF | D4: 97 | E4: HINO | F4: DF | G4: Bộ | I4: 760000 | J4: 810000 | K4: 860000
A5: 3 | B5: HH076278 | C5: Ron bộ Hino EF750, amiang - MASAKO | D5: 137 | E5: HINO | F5: MASAKO | G5: Bộ | I5: 1250000 | J5: 1350000 | K5: 1450000
A6: 4 | B6: HH080139 | C6: Ron bộ Hino EP100, thép - DF | E6: HINO | F6: DF | G6: Bộ | I6: 1670000 | J6: 1770000 | K6: 1900000
A7: 5 | B7: HH072734 | C7: Ron bộ Hino H06C/H07C - Amiang (cổ bô 3 lỗ) - DF | D7: 108 | E7: HINO | F7: DF | G7: Bộ
A8: 6 | B8: HH079303 | C8: Ron bộ Hino H06C/H07C sợi tổng hợp (cổ bô 3 lỗ) - MASAKO | D8: 108 | E8: HINO | F8: MASAKO | G8: Bộ | I8: 750000 | J8: 800000 | K8: 850000
A9: 7 | B9: HH078075 | C9: Ron bộ Hino H07D/ D6DA/ K6700, Non Asb sợi tổng hợp - DF | D9: 109/110 | E9: HINO | F9: DF | G9: Bộ | I9: 810000 | J9: 860000 | K9: 920000
A10: 8 | B10: HH079048 | C10: Ron bộ Hino J05E, Thép - NICE IN | D10: 112 | E10: HINO | F10: NICE IN | G10: Bộ | I10: 1140000 | J10: 1200000 | K10: 1300000
A11: 9 | B11: HH079662 | C11: Ron bộ Hino J07C (sợi tổng hợp) - DF | D11: 114 | E11: HINO | F11: DF | G11: Bộ | I11: 1350000 | J11: 1450000 | K11: 1550000
A12: 10 | B12: HH082104 | C12: Ron bộ Hino J08C-T (J08E) Thép Inox - NICE IN | D12: 112/114 | E12: HINO | F12: NICE IN | G12: Bộ | I12: 1450000 | J12: 1550000 | K12: 1650000
A13: 11 | B13: HH077867 | C13: Ron bộ Hino J08E/ J08C, Thép (S) - NICE IN | D13: 112/114 | E13: HINO | F13: NICE IN | G13: Bộ | I13: 1500000 | J13: 1600000 | K13: 1720000
A14: 12 | B14: HH083903 | C14: Ron bộ Hino N04C thép (S) - NICE IN | E14: HINO | F14: NICE IN | G14: Bộ | I14: 650000 | J14: 680000 | K14: 730000
A15: 13 | B15: HH078290 | C15: Ron bộ Hino W04D, sợi tổng hợp - MASAKO | D15: 104 | E15: HINO | F15: MASAKO | G15: Bộ | I15: 480000 | J15: 510000 | K15: 550000
A16: 14 | B16: HH078291 | C16: Ron bộ Hino W04E, sợi tổng hợp - MASAKO | D16: 104 | E16: HINO | F16: MASAKO | G16: Bộ | I16: 530000 | J16: 560000 | K16: 600000
C17: ◆ ISUZU (47 sản phẩm)
A18: 15 | B18: HH072074 | C18: Ron bộ Isuzu 3KR1 / 3KR2 (Graphite) - DF | D18: 81 | E18: ISUZU | F18: DF | G18: Bộ | I18: 670000 | J18: 720000 | K18: 770000
A19: 16 | B19: HH076547 | C19: Ron bộ Isuzu 3KR1/ 3KR2, Graphite - MASAKO | D19: 81 | E19: ISUZU | F19: MASAKO | G19: Bộ | I19: 675000 | J19: 720000 | K19: 770000
A20: 17 | B20: HH081491 | C20: Ron bộ Isuzu 3LD1, Steel Thép - DF | D20: 83 | E20: ISUZU | F20: DF | G20: Bộ | I20: 690000 | J20: 740000 | K20: 780000
A21: 18 | B21: HH076282 | C21: Ron bộ Isuzu 3LD1, Thép - MASAKO | D21: 83 | E21: ISUZU | F21: MASAKO | G21: Bộ | I21: 605000 | J21: 645000 | K21: 690000
A22: 19 | B22: HH083490 | C22: Ron bộ Isuzu 3LD2, Thép - MASAKO (580.620/60) | D22: 83 | E22: ISUZU | F22: MASAKO (580.620/60) | G22: Bộ | I22: 580000 | J22: 620000 | K22: 660000
A23: 20 | B23: HH078287 | C23: Ron bộ Isuzu 4BC2 Thép (thun cò trơn dẹt) - MASAKO | D23: 102 | E23: ISUZU | F23: MASAKO | G23: Bộ | I23: 460000 | J23: 490000 | K23: 500000
A24: 21 | B24: HH079601 | C24: Ron bộ Isuzu 4BD1/4BB1 Amiang (thun ngạnh, p sau 100-135) - MASAKO | D24: 102 | E24: ISUZU | F24: MASAKO | G24: Bộ | I24: 530000 | J24: 565000 | K24: 610000
A25: 22 | B25: HH075743 | C25: Ron bộ Isuzu 4BD1/4BB1 Thép (thun ngạnh, p sau 100-135) - MASAKO | D25: 102 | E25: ISUZU | F25: MASAKO | G25: Bộ | I25: 540000 | J25: 570000 | K25: 620000
A26: 23 | B26: HH077342 | C26: Ron bộ Isuzu 4BG1 Thép - MASAKO | D26: 105 | E26: ISUZU | F26: MASAKO | G26: Bộ | I26: 540000 | J26: 580000 | K26: 620000
A27: 24 | B27: HH079805 | C27: Ron bộ Isuzu 4BG1 Thép Inox - NICE IN | D27: 105 | E27: ISUZU | F27: NICE IN | G27: Bộ | I27: 740000 | J27: 790000 | K27: 840000
A28: 25 | B28: HH00760 | C28: Ron bộ Isuzu 4BG1, Steel Thép - DF | D28: 105 | E28: ISUZU | F28: DF | G28: Bộ | I28: 690000 | J28: 740000 | K28: 790000
A29: 26 | B29: HH00152 | C29: Ron bộ Isuzu 4BG1-T, phớt trà, Thép - DF | D29: 105 | E29: ISUZU | F29: DF | G29: Bộ
A30: 27 | B30: HH084234 | C30: Ron bộ Isuzu 4FA1, Thép - DF | E30: ISUZU | F30: DF | G30: Bộ | I30: 660000 | J30: 700000 | K30: 750000
A31: 28 | B31: HH078067 | C31: Ron bộ Isuzu 4FB1/ 4FC1, Thép - DF | E31: ISUZU | F31: DF | G31: Bộ | I31: 660000 | J31: 700000 | K31: 750000
A32: 29 | B32: HH078068 | C32: Ron bộ Isuzu 4FE1, Steel Thép - DF | E32: ISUZU | F32: DF | G32: Bộ | I32: 640000 | J32: 680000 | K32: 730000
A33: 30 | B33: HH075973 | C33: Ron bộ Isuzu 4HG1 (new) thép - DF | E33: ISUZU | F33: DF | G33: Bộ | I33: 740000 | J33: 790000 | K33: 840000
A34: 31 | B34: HH075681 | C34: Ron bộ Isuzu 4HG1 (old) thép - DF | E34: ISUZU | F34: DF | G34: Bộ | I34: 740000 | J34: 790000 | K34: 840000
A35: 32 | B35: HH076830 | C35: Ron bộ Isuzu 4HK1-T (đời điện) - thép Inox - NICE IN | E35: ISUZU | F35: NICE IN | G35: Bộ | I35: 1280000 | J35: 1370000 | K35: 1460000
A36: 33 | B36: HH077494 | C36: Ron bộ Isuzu 4JB1 (catte 1 tầng), 4JA1 - Thép - DF | D36: 93 | E36: ISUZU | F36: DF | G36: Bộ | I36: 260000 | J36: 280000 | K36: 300000
A37: 34 | B37: HH075744 | C37: Ron bộ Isuzu 4JB1- T (catte 2 tầng) thép - MASAKO | D37: 93 | E37: ISUZU | F37: MASAKO | G37: Bộ | I37: 400000 | J37: 430000 | K37: 460000
A38: 35 | B38: HH00764 | C38: Ron bộ Isuzu 4JB1-T (catte 2 tầng) thép, 4JA1 - DF | D38: 93 | E38: ISUZU | F38: DF | G38: Bộ | I38: 400000 | J38: 440000 | K38: 470000
A39: 36 | B39: HH076554 | C39: Ron bộ Isuzu 4JC1 (D201) Thép - MASAKO (480.510/50) | D39: 88 | E39: ISUZU | F39: MASAKO (480.510/50) | G39: Bộ | I39: 480000 | J39: 510000 | K39: 550000
A40: 37 | B40: HH084251 | C40: Ron bộ Isuzu 4JE1, Thép - DF | E40: ISUZU | F40: DF | G40: Bộ | I40: 610000 | J40: 650000 | K40: 690000
A41: 38 | B41: HH081249 | C41: Ron bộ Isuzu 4JG1 / 4JG2 - Thép Inox - NICE IN | D41: 95.4 | E41: ISUZU | F41: NICE IN | G41: Bộ | I41: 660000 | J41: 700000 | K41: 750000
A42: 39 | B42: HH077346 | C42: Ron bộ Isuzu 4JG1/ 4JG2, Thép - MASAKO | D42: 95.4 | E42: ISUZU | F42: MASAKO | G42: Bộ | I42: 500000 | J42: 540000 | K42: 580000
A43: 40 | B43: HH072068 | C43: Ron bộ Isuzu 4JH1, thép - DF | D43: 95.4 | E43: ISUZU | F43: DF | G43: Bộ
A44: 41 | B44: HH077053 | C44: Ron bộ Isuzu 4JJ1-T (NF8027-1) thép Inox, phớt béc 57 - NICE IN | D44: 95.4 | E44: ISUZU | F44: NICE IN | G44: Bộ | I44: 950000 | J44: 1030000 | K44: 1100000
A45: 42 | B45: HH081450 | C45: Ron bộ Isuzu 4LC1, Amiang - MASAKO | D45: 77.4 | E45: ISUZU | F45: MASAKO | G45: Bộ | I45: 410000 | J45: 440000 | K45: 470000
A46: 43 | B46: HH074289 | C46: Ron bộ Isuzu 4LE1, Steel thép - DF | D46: 85 | E46: ISUZU | F46: DF | G46: Cái
A47: 44 | B47: HH076827 | C47: Ron bộ Isuzu 4LE1, thép - MASAKO | D47: 85 | E47: ISUZU | F47: MASAKO | G47: Bộ | I47: 590000 | J47: 630000 | K47: 670000
A48: 45 | B48: HH082463 | C48: Ron bộ Isuzu 4LE2, Steel thép - DF | D48: 85 | E48: ISUZU | F48: DF | G48: Bộ | I48: 640000 | J48: 680000 | K48: 730000
A49: 46 | B49: HH079301 | C49: Ron bộ Isuzu 6BD1/ 6BB1 Amiang (thun cò dẹt, p đuôi 105-135) - MASAKO | D49: 102 | E49: ISUZU | F49: MASAKO | G49: Bộ | I49: 600000 | J49: 630000 | K49: 670000
A50: 47 | B50: HH076461 | C50: Ron bộ Isuzu 6BD1/6BB1 Thép (thun cò dẹt, p đuôi 105-135) - NICE IN | D50: 102 | E50: ISUZU | F50: NICE IN | G50: Bộ | I50: 910000 | J50: 960000 | K50: 1030000
A51: 48 | B51: HH075742 | C51: Ron bộ Isuzu 6BD1/6BB1, Thép (t cò dẹt, p sau 105-135)- MASAKO | D51: 102 | E51: ISUZU | G51: Bộ
A52: 49 | B52: HH00761 | C52: Ron bộ Isuzu 6BG1 - Thép - DF | D52: 105 | E52: ISUZU | F52: DF | G52: Bộ
A53: 50 | B53: HH080798 | C53: Ron bộ Isuzu 6HE1, Steel Thép - DF | D53: 110 | E53: ISUZU | F53: DF | G53: Bộ | I53: 1400000 | J53: 1500000 | K53: 1600000
A54: 51 | B54: HH080797 | C54: Ron bộ Isuzu 6HH1, Steel Thép - DF | D54: 115 | E54: ISUZU | F54: DF | G54: Bộ | I54: 1400000 | J54: 1500000 | K54: 1600000
A55: 52 | B55: HH076540 | C55: Ron bộ Isuzu 6HK1 (kim phun cơ) thép - NICE IN | D55: 115 | E55: ISUZU | F55: NICE IN | G55: Bộ | I55: 1400000 | J55: 1500000 | K55: 1600000
A56: 53 | B56: HH076539 | C56: Ron bộ Isuzu 6HK1-T thép (kim phun điện) - NICE IN | D56: 115 | E56: ISUZU | F56: NICE IN | G56: Bộ | I56: 1650000 | J56: 1750000 | K56: 1850000
A57: 54 | B57: HH00762 | C57: Ron bộ Isuzu 6RB1 - Thép - DF | D57: 135 | E57: ISUZU | F57: DF | G57: Bộ
A58: 55 | B58: HH070874 | C58: Ron bộ Isuzu 6SD1 - Thép - DF | D58: 120 | E58: ISUZU | F58: DF | G58: Bộ
A59: 56 | B59: HH084239 | C59: Ron bộ Isuzu 6WA1, Thép - DF | E59: ISUZU | F59: DF | G59: Bộ | I59: 3050000 | J59: 3250000 | K59: 3450000
A60: 57 | B60: HH080447 | C60: Ron bộ Isuzu 6WF1, Thép Inox (phớt 113*148) - NICE IN | D60: 147 | E60: ISUZU | F60: NICE IN | G60: Bộ | I60: 3050000 | J60: 3250000 | K60: 3450000
A61: 58 | B61: HH076462 | C61: Ron bộ Isuzu 6WG1, Thép Inox (phớt 118*148) - NICE IN | D61: 147 | E61: ISUZU | F61: NICE IN | G61: Bộ | I61: 2900000 | J61: 3100000 | K61: 3300000
A62: 59 | B62: HH00763 | C62: Ron bộ Isuzu C240 thép kẹp amiang - DF | D62: 86 | E62: ISUZU | F62: DF | G62: Bộ
A63: 60 | B63: HH082108 | C63: Ron bộ Isuzu DA120/ DA640 (ASB amiang) - MASAKO | D63: 100 | E63: ISUZU | F63: MASAKO | G63: Bộ | I63: 780000 | J63: 835000 | K63: 890000
A64: 61 | B64: HH076067 | C64: Ron bộ Isuzu DA120/DA640, Metal - thép kẹp amiang - MASAKO | D64: 100 | E64: ISUZU | F64: MASAKO | G64: Bộ | I64: 800000 | J64: 860000 | K64: 920000
C65: ◆ MAZDA KIA (10 sản phẩm)
A66: 62 | B66: HH073379 | C66: Ron bộ Kia Bongo/KJ thép (đời điện) - CADA | E66: MAZDA KIA | F66: CADA | G66: Bộ
A67: 63 | B67: HH084237 | C67: Ron bộ Kia J3/ Bongo (Direct injection - đời cơ), Thép - DF | E67: MAZDA KIA | F67: DF | G67: Bộ | I67: 660000 | J67: 700000 | K67: 750000
A68: 64 | B68: HH074788 | C68: Ron bộ Kia JS, Graphite - DF | E68: MAZDA KIA | F68: DF | G68: Bộ
A69: 65 | B69: HH074787 | C69: Ron bộ Kia JT (Graphite) - DF | D69: 98 | E69: MAZDA KIA | F69: DF | G69: Bộ
A70: 66 | B70: HH076285 | C70: Ron bộ Kia JTA/ JT, graphite - MASAKO | D70: 98 | E70: MAZDA KIA | F70: MASAKO | G70: Bộ | I70: 370000 | J70: 395000 | K70: 420000
A71: 67 | B71: HH084250 | C71: Ron bộ Kia K4100/ E4100 ZB, ASB amiang - DF | D71: 92 | E71: MAZDA KIA | F71: DF | G71: Cái | I71: 360000 | J71: 380000 | K71: 400000
A72: 68 | B72: HH084238 | C72: Ron bộ Kia KJ/ J3/ Bongo (Electronic injection - đời điện), Thép - DF | E72: MAZDA KIA | F72: DF | G72: Bộ | I72: 760000 | J72: 810000 | K72: 860000
A73: 69 | B73: HH073885 | C73: Ron bộ Mazda (K2400) - PACIFIC | D73: 92 | E73: MAZDA KIA | F73: PACIFIC | G73: Bộ
A74: 70 | B74: HH00458 | C74: Ron bộ mazda-S5/Kia25 bơm nhớt đầu (XA/T2500) - CGP/ REISSE | D74: 88.9 | E74: MAZDA KIA | F74: CGP/ REISSE | G74: Bộ
A75: 71 | B75: HH081626 | C75: Ron bộ mazda-S5/XA/T2500 - Pacific | D75: 88.9 | E75: MAZDA KIA | F75: Pacific | G75: Bộ
C76: ◆ KOMATSU (24 sản phẩm)
A77: 72 | B77: HH084230 | C77: Ron bộ Dưới (Bottom) Komatsu SA12V140 (140 - 12 máy, S12D140) - DF | E77: KOMATSU | F77: DF | G77: Bộ | I77: 4300000 | J77: 4600000 | K77: 4900000
A78: 73 | B78: HH070302 | C78: Ron bộ KOMATSU-4D105-1 (6130-K1-3012+) - CGP | D78: 104/105 | E78: KOMATSU | F78: CGP | G78: Bộ
A79: 74 | B79: HH00973 | C79: Ron bộ KOMATSU-6D95, giấy CGP (NK) 6206-K1-3012+ | D79: 104 | E79: KOMATSU | G79: Bộ
A80: 75 | B80: HH080753 | C80: Ron bộ Komatsu 3D95, GP - MASAKO | E80: KOMATSU | F80: MASAKO | G80: Bộ | I80: 580000 | J80: 620000 | K80: 660000
A81: 76 | B81: HH076748 | C81: Ron bộ Komatsu 4D105-3 amiang - MASAKO | D81: 105 | E81: KOMATSU | F81: MASAKO | G81: Bộ | I81: 750000 | J81: 800000 | K81: 860000
A82: 77 | B82: HH00750 | C82: Ron bộ Komatsu 4D105-3, amiang - DF | D82: 105 | E82: KOMATSU | F82: DF | G82: Bộ | I82: 720000 | J82: 770000 | K82: 820000
A83: 78 | B83: HH076822 | C83: Ron bộ Komatsu 4D105-5, amiang (S4D105) - MASAKO (650/90.740) | D83: 105 | E83: KOMATSU | F83: MASAKO (650/90.740) | G83: Bộ | I83: 650000 | J83: 690000 | K83: 740000
A84: 79 | B84: HH00758 | C84: Ron bộ Komatsu 4D120, thép, phớt môi nỉ - DF | D84: 120 | E84: KOMATSU | F84: DF | G84: Bộ | I84: 1010000 | J84: 1080000 | K84: 1150000
A85: 80 | B85: HH0623 | C85: Ron bộ Komatsu 4D130, thép, phớt môi nỉ - DF | D85: 130 | E85: KOMATSU | F85: DF | G85: Bộ | I85: 1010000 | J85: 1080000 | K85: 1150000
A86: 81 | B86: HH00977 | C86: Ron bộ Komatsu 4D94 (D20/D21-5) - Amiang - DF | D86: 94 | E86: KOMATSU | F86: DF | G86: Bộ | I86: 600000 | J86: 660000 | K86: 720000
A87: 82 | B87: HH00974 | C87: Ron bộ Komatsu 4D95 (Graphite) - DF | D87: 95 | E87: KOMATSU | F87: DF | G87: Bộ | I87: 500000 | J87: 540000 | K87: 580000
A88: 83 | B88: HH076538 | C88: Ron bộ Komatsu 6D108/S6D108 Thép Inox - NICE IN | D88: 108 | E88: KOMATSU | F88: NICE IN | G88: Bộ | I88: 1350000 | J88: 1420000 | K88: 1500000
A89: 84 | B89: HH071819 | C89: Ron bộ Komatsu 6D110 / S6D110 - Thép - DF | D89: 110 | E89: KOMATSU | F89: DF | G89: Bộ
A90: 85 | B90: HH00756 | C90: Ron bộ Komatsu 6D125-O/ S6D125, thép, 15 lỗ - DF | D90: 125 | E90: KOMATSU | F90: DF | G90: Bộ
A91: 86 | B91: HH083013 | C91: Ron bộ Komatsu S4D102/ 4D102/ 4BT/ PC120-6 (Kim loại) - NICE IN | D91: 102 | E91: KOMATSU | F91: NICE IN | G91: Bộ | I91: 1200000 | J91: 1300000 | K91: 1400000
A92: 87 | B92: HH00125 | C92: Ron bộ Komatsu S4D102/PC120-6 (4D102/4BT) - Kim loại - DF | D92: 102 | E92: KOMATSU | F92: DF | G92: Bộ
A93: 88 | B93: HH00749 | C93: Ron bộ Komatsu S6D102/ PC200-6, Kim loại, 6D102/ 6BT - DF | D93: 102 | E93: KOMATSU | F93: DF | G93: Bộ
A94: 89 | B94: HH00755 | C94: Ron bộ Komatsu S6D105/ 6D105, amiang (có kiềng sơ mi) - DF | D94: 105 | E94: KOMATSU | F94: DF | G94: Bộ
A95: 90 | B95: HH072728 | C95: Ron bộ Komatsu S6D125 E-5/PC400-8/6D125 đời điện - Thép - DF | D95: 125 | E95: KOMATSU | F95: DF | G95: Bộ
A96: 91 | B96: HH072730 | C96: Ron bộ Komatsu S6D140-1/ 6D140-1/ SAA6D140E-2, thép - DF | D96: 140 | E96: KOMATSU | F96: DF | G96: Bộ
A97: 92 | B97: HH072732 | C97: Ron bộ Komatsu S6D140-2 / SAA6D140E-3 - Thép - DF | D97: 140 | E97: KOMATSU | F97: DF | G97: Bộ
A98: 93 | B98: HH072729 | C98: Ron bộ Komatsu S6D140-3/ SAA6D140E-5 - Thép - DF | D98: 140 | E98: KOMATSU | F98: DF | G98: Bộ
A99: 94 | B99: HH073330 | C99: Ron bộ Komatsu SA12V140 (140 - 12 máy, S12D140) Thép - NICE IN | E99: KOMATSU | F99: NICE IN | G99: Bộ
A100: 95 | B100: HH084285 | C100: Ron bộ Trên (Top) Komatsu SA12V140, Thép (140 - 12 máy, S12D140) - DF | E100: KOMATSU | F100: DF | G100: Bộ | I100: 5400000 | J100: 5700000 | K100: 6000000
...

Sheet 📄 RON MIẾNG
A1: STT | B1: 🔖 MÃ VT | C1: 📋 TÊN HÀNG | D1: 📐 ĐK | E1: 🏭 HÃNG | F1: 🏷️ TH SX | G1: 📦 ĐVT | H1: GHI CHÚ | I1: 💰 GIÁ VỐN | J1: 🟢 GIÁ VIP | K1: 🟡 GIÁ Ư.ĐÃI | L1: 🔵 GIÁ ĐẠI LÝ | M1: 🟣 GIÁ GARA | N1: 📦 TỒN | O1: 📝 GHI CHÚ
C2: ◆ HINO (16 sản phẩm)
A3: 1 | B3: HH076259 | C3: Ron miếng Hino DM100 - Amiang - MASAKO | D3: 90 | E3: HINO | F3: MASAKO | G3: Cái
A4: 2 | B4: HH070916 | C4: Ron miếng Hino DM100, Amiang - NICE IN | D4: 90 | E4: HINO | F4: NICE IN | G4: Cái | J4: 140000 | K4: 150000 | L4: 200000
A5: 3 | B5: HH084263 | C5: Ron miếng Hino EC100, ASB amiang - DF | D5: 97 | E5: HINO | F5: DF | G5: Cái | J5: 250000 | K5: 270000 | L5: 290000
A6: 4 | B6: HH076280 | C6: Ron miếng Hino EF750/F17D/EF500, ASB amiang - MASAKO | D6: 137 | E6: HINO | F6: MASAKO | G6: Bộ 2c | J6: 320000 | K6: 350000 | L6: 400000
A7: 5 | B7: HH078098 | C7: Ron miếng Hino EM100, Steel thép - DF | D7: 124 | E7: HINO | F7: DF | G7: Cái | J7: 500000 | K7: 530000 | L7: 560000
A8: 6 | B8: HH076569 | C8: Ron miếng Hino H07C (H06C), Graphite, sợi - NICE IN | D8: 108 | E8: HINO | F8: NICE IN | G8: Cái | J8: 200000 | K8: 215000 | L8: 230000
A9: 7 | B9: HH079592 | C9: Ron miếng Hino J05C-T, thép - NICE IN | E9: HINO | F9: NICE IN | G9: Cái | J9: 280000 | K9: 295000 | L9: 320000
A10: 8 | B10: HH081355 | C10: Ron miếng Hino J05E thép (S) - NICE IN | D10: 112 | E10: HINO | F10: NICE IN | G10: Cái | J10: 290000 | K10: 310000 | L10: 340000
A11: 9 | B11: HH072088 | C11: Ron miếng Hino J05E, sợi tổng hợp, giấy - DF | D11: 112 | E11: HINO | F11: DF | G11: Cái | J11: 300000 | K11: 350000 | L11: 400000
A12: 10 | B12: HH079677 | C12: Ron miếng Hino J07C, sợi tổng hợp - DF | D12: 114 | E12: HINO | F12: DF | G12: Cái | J12: 310000 | K12: 350000 | L12: 400000
A13: 11 | B13: HH072089 | C13: Ron miếng Hino J08C/J08E, sợi tổng hợp, giấy - DF | D13: 112/114 | E13: HINO | F13: DF | G13: Cái | J13: 330000 | K13: 380000 | L13: 430000
A14: 12 | B14: HH077878 | C14: Ron miếng Hino J08E / J08C, Thép (S) - NICE IN | D14: 112/114 | E14: HINO | F14: NICE IN | G14: Cái | J14: 320000 | K14: 340000 | L14: 360000
A15: 13 | B15: HH081356 | C15: Ron miếng Hino J08E/ J08C sợi tổng hợp - NICE IN | D15: 112/114 | E15: HINO | F15: NICE IN | G15: Cái | J15: 300000 | K15: 330000 | L15: 350000
A16: 14 | B16: HH083902 | C16: Ron miếng Hino N04C, thép (S) - NICE IN | E16: HINO | F16: NICE IN | G16: Cái | J16: 180000 | K16: 200000 | L16: 220000
A17: 15 | B17: HH078274 | C17: Ron miếng Hino P11C thép - NICE IN | E17: HINO | F17: NICE IN | G17: Cái | J17: 320000 | K17: 340000 | L17: 370000
A18: 16 | B18: HH073591 | C18: Ron miếng Hino W04D, sợi tổng hợp - NICE IN | D18: 104 | E18: HINO | F18: NICE IN | G18: Cái | J18: 150000 | K18: 170000 | L18: 200000
C19: ◆ ISUZU (42 sản phẩm)
A20: 17 | B20: HH079287 | C20: Ron miếng ISUZU 4LC1/4LB1 amiang - MASAKO | D20: 77.4 | E20: ISUZU | F20: MASAKO | G20: Cái | J20: 85000 | K20: 90000 | L20: 100000
A21: 18 | B21: HH083018 | C21: Ron miếng ISUZU 4LC1/4LB1 amiang - NICE IN (90.100/20) | D21: 77.4 | E21: ISUZU | F21: NICE IN (90.100/20) | G21: Cái | J21: 90000 | K21: 100000 | L21: 120000
A22: 19 | B22: HH076565 | C22: Ron miếng Isuzu 3KC1, GP - MASAKO | D22: 74 | E22: ISUZU | F22: MASAKO | G22: Cái | J22: 140000 | K22: 150000 | L22: 170000
A23: 20 | B23: HH077322 | C23: Ron miếng Isuzu 3KC1, GP - NICE IN | D23: 74 | E23: ISUZU | F23: NICE IN | G23: Cái | J23: 140000 | K23: 150000 | L23: 170000
A24: 21 | B24: HH081351 | C24: Ron miếng Isuzu 3KR1/3KR2, GP - NICE IN | D24: 81 | E24: ISUZU | F24: NICE IN | G24: Cái | J24: 140000 | K24: 150000 | L24: 170000
A25: 22 | B25: HH078270 | C25: Ron miếng Isuzu 3LD1, Thép - NICE IN | D25: 83 | E25: ISUZU | F25: NICE IN | G25: Cái | J25: 170000 | K25: 185000 | L25: 200000
A26: 23 | B26: HH083491 | C26: Ron miếng Isuzu 3LD2, Thép - NICE IN (170/90.210) | D26: 83 | E26: ISUZU | F26: NICE IN (170/90.210) | G26: Cái | J26: 170000 | K26: 190000 | L26: 210000
A27: 24 | B27: HH079698 | C27: Ron miếng Isuzu 4BD1 Amiang (4BB1) - MASAKO | D27: 102 | E27: ISUZU | F27: MASAKO | G27: Cái | J27: 90000 | K27: 100000 | L27: 120000
A28: 25 | B28: HH077324 | C28: Ron miếng Isuzu 4BD1, Thép Inox (4BB1) - NICE IN | D28: 102 | E28: ISUZU | F28: NICE IN | G28: Cái | J28: 160000 | K28: 170000 | L28: 190000
A29: 26 | B29: HH075769 | C29: Ron miếng Isuzu 4BD1, Thép, 4BB1 - MASAKO | D29: 102 | E29: ISUZU | F29: MASAKO | G29: Cái | J29: 110000 | K29: 130000 | L29: 150000
A30: 27 | B30: HH075762 | C30: Ron miếng Isuzu 4BG1/4BE1 thép (S) - MASAKO | D30: 105 | E30: ISUZU | F30: MASAKO | G30: Cái | J30: 110000 | K30: 130000 | L30: 150000
A31: 28 | B31: HH077325 | C31: Ron miếng Isuzu 4BG1/4BE1 thép (S) - NICE IN | D31: 105 | E31: ISUZU | F31: NICE IN | G31: Cái | J31: 160000 | K31: 170000 | L31: 180000
A32: 29 | B32: HH084262 | C32: Ron miếng Isuzu 4FA1, Thép - DF | E32: ISUZU | F32: DF | G32: Cái | J32: 180000 | K32: 190000 | L32: 210000
A33: 30 | B33: HH078099 | C33: Ron miếng Isuzu 4FB1/4FC1, Steel Thép - DF | E33: ISUZU | F33: DF | G33: Cái | J33: 150000 | K33: 160000 | L33: 180000
A34: 31 | B34: HH083885 | C34: Ron miếng Isuzu 4HF1 Old, Thép - NICE IN | D34: 112 | E34: ISUZU | F34: NICE IN | G34: Cái | J34: 200000 | K34: 220000 | L34: 250000
A35: 32 | B35: HH075974 | C35: Ron miếng Isuzu 4HG1-New thép - DF | E35: ISUZU | F35: DF | G35: Cái | J35: 230000 | K35: 250000 | L35: 270000
A36: 33 | B36: HH075975 | C36: Ron miếng Isuzu 4HG1-Old, thép - DF | E36: ISUZU | F36: DF | G36: Cái | J36: 240000 | K36: 260000 | L36: 280000
A37: 34 | B37: HH080622 | C37: Ron miếng Isuzu 4JB1 (4JA1) Thép Inox - NICE IN | D37: 93 | E37: ISUZU | F37: NICE IN | G37: Cái | J37: 100000 | K37: 120000 | L37: 150000
A38: 35 | B38: HH075768 | C38: Ron miếng Isuzu 4JB1 Thép (4JA1) - MASAKO | D38: 93 | E38: ISUZU | F38: MASAKO | G38: Cái | J38: 95000 | K38: 110000 | L38: 120000
A39: 36 | B39: HH079343 | C39: Ron miếng Isuzu 4JB1/4JA1, ASB amiang - MASAKO | D39: 93 | E39: ISUZU | F39: MASAKO | G39: Cái | J39: 80000 | K39: 90000 | L39: 100000
A40: 37 | B40: HH076262 | C40: Ron miếng Isuzu 4JC1 (D201) Thép - MASAKO | D40: 88 | E40: ISUZU | F40: MASAKO | G40: Cái | J40: 140000 | K40: 150000 | L40: 170000
A41: 38 | B41: HH082501 | C41: Ron miếng Isuzu 4JE1 Thép - DF | E41: ISUZU | F41: DF | G41: Cái | J41: 180000 | K41: 190000 | L41: 210000
A42: 39 | B42: HH083887 | C42: Ron miếng Isuzu 4JE1, Thép - NICE IN | E42: ISUZU | F42: NICE IN | G42: Cái | J42: 150000 | K42: 160000 | L42: 180000
A43: 40 | B43: HH077885 | C43: Ron miếng Isuzu 4JG2/ 4JG1, Thép Inox - NICE IN | D43: 95.4 | E43: ISUZU | F43: NICE IN | G43: Cái | J43: 150000 | K43: 160000 | L43: 180000
A44: 41 | B44: HH00785 | C44: Ron miếng Isuzu 4JH1, THÉP - DF | D44: 95.4 | E44: ISUZU | F44: DF | G44: Cái | J44: 150000 | K44: 170000 | L44: 200000
A45: 42 | B45: HH083460 | C45: Ron miếng Isuzu 4JH1, Thép Inox - NICE IN, 120/30/50 | D45: 95.4 | E45: ISUZU | F45: NICE IN, 120/30/50 | G45: Cái | J45: 120000 | K45: 130000 | L45: 150000
A46: 43 | B46: HH077874 | C46: Ron miếng Isuzu 4LE1, Thép Inox - NICE IN | D46: 85 | E46: ISUZU | F46: NICE IN | G46: Cái | J46: 165000 | K46: 175000 | L46: 190000
A47: 44 | B47: HH083007 | C47: Ron miếng Isuzu 4LE2-T - Thép Inox (0.6mm) - NICE IN | D47: 85 | E47: ISUZU | F47: NICE IN | G47: Cái | J47: 160000 | K47: 180000 | L47: 200000
A48: 45 | B48: HH077328 | C48: Ron miếng Isuzu 6BB1/6BD1/DB58, Thép Inox - Stainless - NICE IN | D48: 102 | E48: ISUZU | F48: NICE IN | G48: Cái | J48: 225000 | K48: 240000 | L48: 260000
A49: 46 | B49: HH075770 | C49: Ron miếng Isuzu 6BD1/6BB1/DB58, Steel Thép - MASAKO | D49: 102 | E49: ISUZU | F49: MASAKO | G49: Cái | J49: 140000 | K49: 160000 | L49: 180000
A50: 47 | B50: HH076069 | C50: Ron miếng Isuzu 6BD1/DB58 Amiang (6BB1) - MASAKO | D50: 102 | E50: ISUZU | F50: MASAKO | G50: Cái | J50: 115000 | K50: 125000 | L50: 140000
A51: 48 | B51: HH078548 | C51: Ron miếng Isuzu 6BG1 (6BF1) Thép - MASAKO | D51: 105 | E51: ISUZU | F51: MASAKO | G51: Cái | J51: 140000 | K51: 160000 | L51: 180000
A52: 49 | B52: HH079295 | C52: Ron miếng Isuzu 6BG1, Thép Inox - Stainless - NICE IN | D52: 105 | E52: ISUZU | F52: NICE IN | G52: Cái | J52: 225000 | K52: 240000 | L52: 260000
A53: 50 | B53: HH080799 | C53: Ron miếng Isuzu 6HH1, Steel Thép - DF | D53: 115 | E53: ISUZU | F53: DF | G53: Cái | J53: 350000 | K53: 370000 | L53: 400000
A54: 51 | B54: HH078740 | C54: Ron miếng Isuzu 6HK1 thép (đời cơ) - NICE IN | D54: 115 | E54: ISUZU | F54: NICE IN | G54: Cái | J54: 350000 | K54: 400000 | L54: 450000
... A57: 54 | B57: HH070906 | C57: Ron miếng Isuzu 6SD1, thép - DF | D57: 120 | E57: ISUZU | F57: DF | G57: Cái | J57: 480000 | K57: 550000 | L57: 600000
A58: 55 | B58: HH084267 | C58: Ron miếng Isuzu 6WA1, Thép - DF | E58: ISUZU | F58: DF | G58: Cái | J58: 1050000 | K58: 1100000 | L58: 1200000
A59: 56 | B59: HH076450 | C59: Ron miếng Isuzu 6WG1 (6WF1), Thép Inox - NICE IN | D59: 147 | E59: ISUZU | F59: NICE IN | G59: Cái | J59: 1200000 | K59: 1300000 | L59: 1400000
A60: 57 | B60: HH081932 | C60: Ron miếng Isuzu DA120, Asb amiang - DF | D60: 100 | E60: ISUZU | F60: DF | G60: Cái
A61: 58 | B61: HH00792 | C61: Ron miếng Isuzu DA120, Thép kẹp amiang - DF | D61: 100 | E61: ISUZU | F61: DF | G61: Cái | J61: 210000 | K61: 220000 | L61: 240000
C62: ◆ MAZDA KIA (6 sản phẩm)
A63: 59 | B63: HH078094 | C63: Ron miếng Hino H07D/ Kia D6DA (sợi tổng hợp) - DF | D63: 109/110 | E63: MAZDA KIA | F63: DF | G63: Cái | J63: 220000 | K63: 240000 | L63: 270000
A64: 60 | B64: HH084265 | C64: Ron miếng Kia J3/ BONGO (direct injection, đời cơ), Thép - DF | E64: MAZDA KIA | F64: DF | G64: Cái | J64: 160000 | K64: 180000 | L64: 200000
A65: 61 | B65: HH074791 | C65: Ron miếng Kia JS, Graphite - DF | E65: MAZDA KIA | F65: DF | G65: Cái | J65: 90000 | K65: 100000 | L65: 110000
A66: 62 | B66: HH084278 | C66: Ron miếng Kia K4100/ E4100 ZB, ASB amiang - DF | D66: 92 | E66: MAZDA KIA | F66: DF | G66: Cái | J66: 90000 | K66: 100000 | L66: 120000
A67: 63 | B67: HH084266 | C67: Ron miếng Kia KJ/ J3/ Bongo (Electronic injection, đời điện), Thép - DF | E67: MAZDA KIA | F67: DF | G67: Bộ | J67: 160000 | K67: 180000 | L67: 200000
A68: 64 | B68: HH073063 | C68: Ron miếng mazda-S5/Kia25 (XA/T2500) - CGP | D68: 88.9 | E68: MAZDA KIA | F68: CGP | G68: Cái
C69: ◆ KOMATSU (18 sản phẩm)
A70: 65 | B70: HH00077 | C70: Ron miếng KOMATSU-6D95 thép (S) (6207-K1-3012) | D70: 104 | E70: KOMATSU | G70: Cái
A71: 66 | B71: HH083884 | C71: Ron miếng Komatsu 3D95, Graphite - NICE IN | E71: KOMATSU | F71: NICE IN | G71: Cái | J71: 150000 | K71: 160000 | L71: 170000
A72: 67 | B72: HH077910 | C72: Ron miếng Komatsu 4D102 (S4D102/ 4BT), Metal thép kẹp - NICE IN | D72: 102 | E72: KOMATSU | F72: NICE IN | G72: Cái | J72: 125000 | K72: 135000 | L72: 150000
A73: 68 | B73: HH076451 | C73: Ron miếng Komatsu 4D105-1/ -3, amiang - MASAKO | D73: 105 | E73: KOMATSU | F73: MASAKO | G73: Cái | J73: 95000 | K73: 105000 | L73: 120000
A74: 69 | B74: HH079749 | C74: Ron miếng Komatsu 4D105-5 amiang - MASAKO | D74: 105 | E74: KOMATSU | F74: MASAKO | G74: Cái | J74: 100000 | K74: 110000 | L74: 120000
A75: 70 | B75: HH00783 | C75: Ron miếng Komatsu 4D120, thép - DF | D75: 120 | E75: KOMATSU | F75: DF | G75: Cái | J75: 220000 | K75: 240000 | L75: 260000
A76: 71 | B76: HH00784 | C76: Ron miếng Komatsu 4D130, thép - DF | D76: 130 | E76: KOMATSU | F76: DF | G76: Cái | J76: 220000 | K76: 240000 | L76: 260000
A77: 72 | B77: HH076516 | C77: Ron miếng Komatsu 4D92 (xe ủi) - Amiang - DF | D77: 92 | E77: KOMATSU | F77: DF | G77: Cái | J77: 120000 | K77: 130000 | L77: 150000
A78: 73 | B78: HH077877 | C78: Ron miếng Komatsu 4D95 / S4D95 thép - MASAKO | D78: 95 | E78: KOMATSU | F78: MASAKO | G78: Cái | J78: 150000 | K78: 160000 | L78: 180000
A79: 74 | B79: HH077912 | C79: Ron miếng Komatsu 4D95/ S4D95 GP - NICE | D79: 95 | E79: KOMATSU | F79: NICE | G79: Cái | J79: 100000 | K79: 110000 | L79: 130000
A80: 75 | B80: HH080268 | C80: Ron miếng Komatsu 4D95/ S4D95, Thép Inox - Stainless - NICE IN | D80: 95 | E80: KOMATSU | F80: NICE IN | G80: Cái | J80: 175000 | K80: 190000 | L80: 210000
A81: 76 | B81: HH076562 | C81: Ron miếng Komatsu 6D102 (S6D102/6BT) Metal thép kẹp - NICE IN | D81: 102 | E81: KOMATSU | F81: NICE IN | G81: Cái | J81: 140000 | K81: 160000 | L81: 180000
A82: 77 | B82: HH078254 | C82: Ron miếng Komatsu 6D105/S6D105, Amiang (có kiềng sơ mi) - NICE IN | D82: 105 | E82: KOMATSU | F82: NICE IN | G82: Cái | J82: 215000 | K82: 230000 | L82: 250000
A83: 78 | B83: HH078569 | C83: Ron miếng Komatsu 6D125-N (S6D125) Thép, 16 lỗ - NICE IN | D83: 125 | E83: KOMATSU | F83: NICE IN | G83: Bộ 6c | J83: 500000 | K83: 550000 | L83: 600000
... A87: 82 | B87: HH072750 | C87: Ron miếng Komatsu S6D140 / 6D140, Steel thép - DF | D87: 140 | E87: KOMATSU | F87: DF | G87: Bộ 6c | J87: 900000 | K87: 1000000 | L87: 1100000
C88: ◆ MITSUBISHI (41 sản phẩm)
A89: 83 | B89: HH080428 | C89: Ron miếng 4D56 - 16V (Mitsu L200/ Triton) Thép - MASAKO | D89: 98 | E89: MITSUBISHI | F89: MASAKO | G89: Cái | J89: 110000 | K89: 120000 | L89: 130000
A90: 84 | B90: HH077326 | C90: Ron miếng Mitsu 4D31, Thép Inox (4D30/D4AL) - NICE IN | D90: 100 | E90: MITSUBISHI | F90: NICE IN | G90: Cái | J90: 170000 | K90: 185000 | L90: 200000
A91: 85 | B91: HH076258 | C91: Ron miếng Mitsu 4D32, Thép, D4AF/K1 - MASAKO | D91: 104 | E91: MITSUBISHI | F91: MASAKO | G91: Cái | J91: 110000 | K91: 130000 | L91: 150000
A92: 86 | B92: HH076257 | C92: Ron miếng Mitsu 4D34 Thép - MASAKO | D92: 104 | E92: MITSUBISHI | F92: MASAKO | G92: Cái | J92: 120000 | K92: 130000 | L92: 150000
A93: 87 | B93: HH077911 | C93: Ron miếng Mitsu 4D34, Thép Inox - NICE IN | D93: 104 | E93: MITSUBISHI | F93: NICE IN | G93: Cái | J93: 160000 | K93: 170000 | L93: 180000
A94: 88 | B94: HH084260 | C94: Ron miếng Mitsu 4D35, Thép - DF | D94: 110 | E94: MITSUBISHI | F94: DF | G94: Cái | J94: 160000 | K94: 170000 | L94: 200000
A95: 89 | B95: HH076283 | C95: Ron miếng Mitsu 4D55/4D56, graphite - NICE IN | D95: 91.1 | E95: MITSUBISHI | F95: NICE IN | G95: Cái | J95: 75000 | K95: 90000 | L95: 100000
A96: 90 | B96: HH084261 | C96: Ron miếng Mitsu 4DQ3, Metal thép kẹp - DF | E96: MITSUBISHI | F96: DF | G96: Cái | J96: 150000 | K96: 160000 | L96: 180000
A97: 91 | B97: HH076454 | C97: Ron miếng Mitsu 4M40 Amiang - MASAKO | D97: 95 | E97: MITSUBISHI | F97: MASAKO | G97: Cái | J97: 90000 | K97: 100000 | L97: 120000
A98: 92 | B98: HH083338 | C98: Ron miếng Mitsu 4M40 Amiang - NICE IN | D98: 95 | E98: MITSUBISHI | F98: NICE IN | G98: Cái | J98: 100000 | K98: 110000 | L98: 130000
A99: 93 | B99: HH081776 | C99: Ron miếng Mitsu 4M40-T, Thép - MASAKO | D99: 95 | E99: MITSUBISHI | F99: MASAKO | G99: Cái | J99: 160000 | K99: 170000 | L99: 180000
A100: 94 | B100: HH078261 | C100: Ron miếng Mitsu 6D14, ASB amiang - NICE IN | E100: MITSUBISHI | F100: NICE IN | G100: Cái | J100: 160000 | K100: 175000 | L100: 200000
A101: 95 | B101: HH080609 | C101: Ron miếng Mitsu 6D16-2AT, Amiang (lỗ nước trên vuông)- NICE IN, 170/80.200 | E101: MITSUBISHI | G101: Cái | J101: 170000 | K101: 180000 | L101: 200000
A102: 96 | B102: HH077329 | C102: Ron miếng Mitsu 6D16T amiang - NICE IN | D102: 118 | E102: MITSUBISHI | F102: NICE IN | G102: Cái | J102: 160000 | K102: 180000 | L102: 200000
A103: 97 | B103: HH082736 | C103: Ron miếng Mitsu 6D22-T/6D24 (có 5 seal nước) Thép - MASAKO | E103: MITSUBISHI | F103: MASAKO | G103: Bộ 6c | J103: 580000 | K103: 610000 | L103: 650000
A104: 98 | B104: HH082331 | C104: Ron miếng Mitsu 6D22T/6D24 Thép (Inox, có 5 sin) - NICE IN | E104: MITSUBISHI | F104: NICE IN | G104: Bộ | J104: 700000 | K104: 740000 | L104: 800000
A105: 99 | B105: HH077915 | C105: Ron miếng Mitsu 6D34, Thép Inox - NICE IN | E105: MITSUBISHI | F105: NICE IN | G105: Cái | J105: 270000 | K105: 290000 | L105: 310000
...

Sheet 📋 MIỂNG TNC
A1: 📋 MIỂNG (BẠC) — dữ liệu mới nhất
A2: Mã HH | B2: Hãng | C2: Mã ĐC | D2: ĐK | E2: Cos | F2: Loại | G2: Thương hiệu | H2: ĐVT | I2: Ghi chú | J2: VIP | K2: Ưu đãi | L2: Đại lý | M2: Gara | N2: Tồn | O2: PARNO | P2: Tên đầy đủ
C3: ◆ HINO
A4: HH070779 | B4: HINO | C4: Bạc miểng DM100/DQ100 Cos0 - TAIHO | D4: 90 | E4: Cos0 | F4: Baze+Dên | G4: TAIHO | H4: Bộ | P4: Bạc miểng DM100/DQ100 Cos0 - TAIHO
A5: HH071938 | B5: HINO | C5: Bạc miểng DM100/DQ100 Cos1 - TAIHO | D5: 90 | E5: Cos1 | F5: Baze+Dên | G5: TAIHO | H5: Bộ | P5: Bạc miểng DM100/DQ100 Cos1 - TAIHO
A6: HH071939 | B6: HINO | C6: Bạc miểng DM100/DQ100 Cos2 - TAIHO | D6: 90 | E6: Cos2 | F6: Baze+Dên | G6: TAIHO | H6: Bộ | P6: Bạc miểng DM100/DQ100 Cos2 - TAIHO
A7: HH079058 | B7: HINO | C7: Bạc miểng DM100/DQ100 Cos3 - TAIHO | D7: 90 | E7: Cos3 | F7: Baze+Dên | G7: TAIHO | H7: Bộ | P7: Bạc miểng DM100/DQ100 Cos3 - TAIHO
B8: HINO | C8: Bạc Miểng DM100/DQ100 | D8: 90 | E8: Cos4 | F8: Baze+Dên | H8: Bộ
A9: HH083728 | B9: HINO | C9: Bạc miểng Hino W04D/W04E (M133K, R133K1) STD Cos0 - DAIDO NHẬT | D9: 104 | E9: Cos0 | F9: Baze+Dên | G9: DAIDO NHẬT | H9: Bộ | J9: 590000 | K9: 630000 | L9: 680000 | P9: Bạc miểng Hino W04D/W04E (M133K, R133K1) STD Cos0 - DAIDO NHẬT
A10: HH00276 | B10: HINO | C10: Bạc miểng W04D / W04E Cos0 - TAIHO | D10: 104 | E10: Cos0 | F10: Baze+Dên | G10: TAIHO | H10: Bộ | P10: Bạc miểng W04D / W04E Cos0 - TAIHO
A11: HH00275 | B11: HINO | C11: Bạc miểng W04D / W04E Cos1 - TAIHO | D11: 104 | E11: Cos1 | F11: Baze+Dên | G11: TAIHO | H11: Bộ | P11: Bạc miểng W04D / W04E Cos1 - TAIHO
B12: HINO | C12: Bạc Miểng W04D/W04E | D12: 104 | E12: Cos2 | F12: Baze+Dên | H12: Bộ
B13: HINO | C13: Bạc Miểng W04D/W04E | D13: 104 | E13: Cos3 | F13: Baze+Dên | H13: Bộ
B14: HINO | C14: Bạc Miểng W04D/W04E | D14: 104 | E14: Cos4 | F14: Baze+Dên | H14: Bộ
A15: HH083730 | B15: HINO | C15: Bạc miểng Hino W06D/W06E (M134K, R134K1) STD Cos0 - DAIDO NHẬT | D15: 104 | E15: Cos0 | F15: Baze+Dên | G15: DAIDO NHẬT | H15: Bộ | J15: 1800000 | K15: 1900000 | L15: 2050000 | P15: Bạc miểng Hino W06D/W06E (M134K, R134K1) STD Cos0 - DAIDO NHẬT
B16: HINO | C16: Bạc Miểng W06D/W06E | D16: 104 | E16: Cos1 | F16: Baze+Dên | H16: Bộ
B17: HINO | C17: Bạc Miểng W06D/W06E | D17: 104 | E17: Cos2 | F17: Baze+Dên | H17: Bộ
B18: HINO | C18: Bạc Miểng W06D/W06E | D18: 104 | E18: Cos3 | F18: Baze+Dên | H18: Bộ
A19: HH072136 | B19: HINO | C19: Bạc miểng W06D/ W06E Cos4 - TAIHO | D19: 104 | E19: Cos4 | F19: Baze+Dên | G19: TAIHO | H19: Bộ | P19: Bạc miểng W06D/ W06E Cos4 - TAIHO
A20: HH070806 | B20: HINO | C20: Bạc miểng W06D/ W06E Cos2 - TAIHO | E20: Cos2 | F20: Baze+Dên | G20: TAIHO | H20: Bộ | P20: Bạc miểng W06D/ W06E Cos2 - TAIHO
A21: HH074388 | B21: HINO | C21: Bạc miểng DS30/DS50 cos0 - NDC | D21: 110 | E21: Cos0 | F21: Baze+Dên | G21: NDC | H21: Bộ | P21: Bạc miểng DS30/DS50 cos0 - NDC
B22: HINO | C22: Bạc Miểng DS30/DS50 | D22: 110 | E22: Cos1 | F22: Baze+Dên | H22: Bộ
B23: HINO | C23: Bạc Miểng DS30/DS50 | D23: 110 | E23: Cos2 | F23: Baze+Dên | H23: Bộ
B24: HINO | C24: Bạc Miểng DS30/DS50 | D24: 110 | E24: Cos3 | F24: Baze+Dên | H24: Bộ
B25: HINO | C25: Bạc Miểng DS30/DS50 | D25: 110 | E25: Cos4 | F25: Baze+Dên | H25: Bộ
A26: HH073146 | B26: HINO | C26: Bạc miểng EH700 Cos0 - NDC | D26: 110 | E26: Cos0 | F26: Baze+Dên | G26: NDC | H26: Bộ | P26: Bạc miểng EH700 Cos0 - NDC
B27: HINO | C27: Bạc Miểng EH700 | D27: 110 | E27: Cos1 | F27: Baze+Dên | H27: Bộ
B28: HINO | C28: Bạc Miểng EH700 | D28: 110 | E28: Cos2 | F28: Baze+Dên | H28: Bộ
B29: HINO | C29: Bạc Miểng EH700 | D29: 110 | E29: Cos3 | F29: Baze+Dên | H29: Bộ
B30: HINO | C30: Bạc Miểng EH700 | D30: 110 | E30: Cos4 | F30: Baze+Dên | H30: Bộ
A31: HH068735 | B31: HINO | C31: Bạc miểng H06B-T/H06C/H07C Cos0 - NDC | D31: 110 | E31: Cos0 | F31: Baze+Dên | G31: NDC | H31: Bộ | P31: Bạc miểng H06B-T/H06C/H07C Cos0 - NDC
B32: HINO | C32: Bạc Miểng H06B-T/H06C/H07C | D32: 110 | E32: Cos1 | F32: Baze+Dên | H32: Bộ
B33: HINO | C33: Bạc Miểng H06B-T/H06C/H07C | D33: 110 | E33: Cos2 | F33: Baze+Dên | H33: Bộ
B34: HINO | C34: Bạc Miểng H06B-T/H06C/H07C | D34: 110 | E34: Cos3 | F34: Baze+Dên | H34: Bộ
B35: HINO | C35: Bạc Miểng H06B-T/H06C/H07C | D35: 110 | E35: Cos4 | F35: Baze+Dên | H35: Bộ
A36: HH00587 | B36: HINO | C36: Bạc miểng H06C/H07C Cos0 - TaiHo | D36: 110 | E36: Cos0 | F36: Baze+Dên | G36: TAIHO | H36: Bộ | P36: Bạc miểng H06C/H07C Cos0 - TaiHo
A37: HH071871 | B37: HINO | C37: Bạc miểng H06C/H07C Cos1 - TaiHo | D37: 110 | E37: Cos1 | F37: Baze+Dên | G37: TAIHO | H37: Bộ | P37: Bạc miểng H06C/H07C Cos1 - TaiHo
B38: HINO | C38: Bạc Miểng H06C/H07C | D38: 110 | E38: Cos2 | F38: Baze+Dên | H38: Bộ
A39: HH071381 | B39: HINO | C39: Bạc miểng H06C/H07C Cos3 - TaiHo | D39: 110 | E39: Cos3 | F39: Baze+Dên | G39: TAIHO | H39: Bộ | P39: Bạc miểng H06C/H07C Cos3 - TaiHo
A40: HH081206 | B40: HINO | C40: Bạc miểng H06C/H07C Cos4 - TaiHo | D40: 110 | E40: Cos4 | F40: Baze+Dên | G40: TAIHO | H40: Bộ | P40: Bạc miểng H06C/H07C Cos4 - TaiHo
B41: HINO | C41: Baze H06C/H07C | D41: 110 | E41: Cos0 | F41: Baze | H41: Bộ
A42: HH080514 | B42: HINO | C42: Baze H06C/H07C | D42: 110 | E42: Cos1 | F42: Baze | G42: TDC | H42: Bộ | J42: 550000 | K42: 580000 | L42: 610000 | P42: Miểng baze H06C/H07C cos1 - TDC - M1108K
A43: HH076404 | B43: HINO | C43: Baze H06C/H07C | D43: 110 | E43: Cos2 | F43: Baze | G43: TAIHO | H43: Bộ | P43: Miểng baze H06C/H07C (M218H1) Cos2 - TaiHo
A44: HH080515 | B44: HINO | C44: Baze H06C/H07C | D44: 110 | E44: Cos2 | F44: Baze | G44: TDC | H44: Bộ | J44: 550000 | K44: 580000 | L44: 610000 | P44: Miểng baze H06C/H07C cos2 - TDC - M1108K
B45: HINO | C45: Baze H06C/H07C | D45: 110 | E45: Cos3 | F45: Baze | H45: Bộ
B46: HINO | C46: Baze H06C/H07C | D46: 110 | E46: Cos4 | F46: Baze | H46: Bộ
B47: HINO | C47: Dên H06C/H07C | D47: 110 | E47: Cos0 | F47: Dên | H47: Bộ
A48: HH080534 | B48: HINO | C48: Dên H06C/H07C | D48: 110 | E48: Cos1 | F48: Dên | G48: TDC | H48: Bộ | J48: 490000 | K48: 520000 | L48: 550000 | P48: Miểng dên H06C/H07C cos1 - TDC - R109K
A49: HH076407 | B49: HINO | C49: Dên H06C/H07C | D49: 110 | E49: Cos2 | F49: Dên | G49: TAIHO | H49: Bộ | P49: Miểng dên H06C/H07C (M218H1) Cos2 - TaiHo
A50: HH080535 | B50: HINO | C50: Dên H06C/H07C | D50: 110 | E50: Cos2 | F50: Dên | G50: TDC | H50: Bộ | J50: 500000 | K50: 520000 | L50: 540000 | P50: Miểng dên H06C/H07C cos2 - TDC - R109K
B51: HINO | C51: Dên H06C/H07C | D51: 110 | E51: Cos3 | F51: Dên | H51: Bộ
B52: HINO | C52: Dên H06C/H07C | D52: 110 | E52: Cos4 | F52: Dên | H52: Bộ
A53: HH078906 | B53: HINO | C53: Bạc miểng J05E Cos0 - MAHLE | D53: 112 | E53: Cos0 | F53: Baze+Dên | G53: MAHLE | H53: Bộ | J53: 780000 | K53: 820000 | L53: 860000 | P53: Bạc miểng J05E Cos0 - MAHLE
B54: HINO | C54: Bạc Miểng J05E | D54: 112 | E54: Cos1 | F54: Baze+Dên | H54: Bộ
B55: HINO | C55: Bạc Miểng J05E | D55: 112 | E55: Cos2 | F55: Baze+Dên | H55: Bộ
B56: HINO | C56: Bạc Miểng J05E | D56: 112 | E56: Cos3 | F56: Baze+Dên | H56: Bộ
B57: HINO | C57: Bạc Miểng J05E | D57: 112 | E57: Cos4 | F57: Baze+Dên | H57: Bộ
A58: HH076393 | B58: HINO | C58: Baze J08C/J05C/J08E/J05E | D58: 112 | E58: Cos0 | F58: Baze | G58: TAIHO | H58: Cặp | J58: 100000 | K58: 110000 | L58: 120000 | P58: Miểng baze J08C/J05C/J08E/J05E Cos0 (MP224H) - TAIHO
A59: HH076394 | B59: HINO | C59: Baze J08C/J05C/J08E/J05E | D59: 112 | E59: Cos1 | F59: Baze | G59: TAIHO | H59: Cặp | J59: 100000 | K59: 110000 | L59: 120000 | P59: Miểng baze J08C/J05C/J08E/J05E Cos1 (MP224H) - TAIHO
A60: HH076395 | B60: HINO | C60: Baze J08C/J05C/J08E/J05E | D60: 112 | E60: Cos2 | F60: Baze | G60: TAIHO | H60: Cặp | J60: 100000 | K60: 110000 | L60: 120000 | P60: Miểng baze J08C/J05C/J08E/J05E Cos2 (MP224H) - TAIHO
B61: HINO | C61: Baze J08C/J05C/J08E/J05E | D61: 112 | E61: Cos3 | F61: Baze | H61: Cặp
B62: HINO | C62: Baze J08C/J05C/J08E/J05E | D62: 112 | E62: Cos4 | F62: Baze | H62: Cặp
A63: HH079888 | B63: HINO | C63: Dên J08E | D63: 112 | E63: Cos0 | F63: Dên | G63: CS IVECO | H63: Bộ | J63: 330000 | K63: 350000 | L63: 370000 | P63: Miểng dên J08E (R226H) Cos0 - CS IVECO
A64: HH079889 | B64: HINO | C64: Dên J08E | D64: 112 | E64: Cos1 | F64: Dên | G64: CS IVECO | H64: Bộ | J64: 350000 | K64: 370000 | L64: 390000 | P64: Miểng dên J08E (R226H) Cos1 - CS IVECO
B65: HINO | C65: Dên J08E | D65: 112 | E65: Cos2 | F65: Dên | H65: Bộ
B66: HINO | C66: Dên J08E | D66: 112 | E66: Cos3 | F66: Dên | H66: Bộ
B67: HINO | C67: Dên J08E | D67: 112 | E67: Cos4 | F67: Dên | H67: Bộ
A68: HH080548 | B68: HINO | C68: Dên J08E/J05E | D68: 112 | E68: Cos0 | F68: Dên | G68: TDC | H68: Cặp | J68: 100000 | K68: 110000 | L68: 120000 | P68: Miểng dên (Cặp) J08E/J05E Cos0 - TDC - RP1106K
A69: HH080549 | B69: HINO | C69: Dên J08E/J05E | D69: 112 | E69: Cos1 | F69: Dên | G69: TDC | H69: Cặp | J69: 105000 | K69: 115000 | L69: 125000 | P69: Miểng dên (Cặp) J08E/J05E Cos1 - TDC - RP1106K
A70: HH076401 | B70: HINO | C70: Dên J08E/J05E | D70: 112 | E70: Cos2 | F70: Dên | G70: TAIHO | H70: Cặp | J70: 130000 | K70: 140000 | L70: 150000 | P70: Miểng dên J08E/J05E Cos2 (RP226H) - TAIHO
B71: HINO | C71: Dên J08E/J05E | D71: 112 | E71: Cos3 | F71: Dên | H71: Cặp
B72: HINO | C72: Dên J08E/J05E | D72: 112 | E72: Cos4 | F72: Dên | H72: Cặp
A73: HH079886 | B73: HINO | C73: Baze J08E/J08C | D73: 112 | E73: Cos0 | F73: Baze | G73: CS IVECO | H73: Bộ | J73: 460000 | K73: 480000 | L73: 500000 | P73: Miểng baze J08E/ J08C (M224H) Cos0 - CS IVECO
A74: HH079887 | B74: HINO | C74: Baze J08E/J08C | D74: 112 | E74: Cos1 | F74: Baze | G74: CS IVECO | H74: Bộ | J74: 490000 | K74: 510000 | L74: 530000 | P74: Miểng baze J08E/ J08C (M224H) Cos1 - CS IVECO
B75: HINO | C75: Baze J08E/J08C | D75: 112 | E75: Cos2 | F75: Baze | H75: Bộ
B76: HINO | C76: Baze J08E/J08C | D76: 112 | E76: Cos3 | F76: Baze | H76: Bộ
B77: HINO | C77: Baze J08E/J08C | D77: 112 | E77: Cos4 | F77: Baze | H77: Bộ
B78: HINO | C78: Bạc Miểng J08C | D78: 114 | E78: Cos0 | F78: Baze+Dên | H78: Bộ
A79: HH0355 | B79: HINO | C79: Bạc miểng J08C Cos1 - TAIHO | D79: 114 | E79: Cos1 | F79: Baze+Dên | G79: TAIHO | H79: Bộ | P79: Bạc miểng J08C Cos1 - TAIHO
B80: HINO | C80: Bạc Miểng J08C | D80: 114 | E80: Cos2 | F80: Baze+Dên | H80: Bộ
B81: HINO | C81: Bạc Miểng J08C | D81: 114 | E81: Cos3 | F81: Baze+Dên | H81: Bộ
B82: HINO | C82: Bạc Miểng J08C | D82: 114 | E82: Cos4 | F82: Baze+Dên | H82: Bộ
A83: HH076396 | B83: HINO | C83: Dên J08C/J05C | D83: 114 | E83: Cos0 | F83: Dên | G83: TAIHO | H83: Cặp | J83: 80000 | K83: 90000 | L83: 100000 | O83: RP224H1 | P83: Miểng dên J08C/J05C Cos0 (RP224H1) - TAIHO
A84: HH076397 | B84: HINO | C84: Dên J08C/J05C | D84: 114 | E84: Cos1 | F84: Dên | G84: TAIHO | H84: Cặp | J84: 90000 | K84: 100000 | L84: 110000 | O84: RP224H1 | P84: Miểng dên J08C/J05C Cos1 (RP224H1) - TAIHO
A85: HH076398 | B85: HINO | C85: Dên J08C/J05C | D85: 114 | E85: Cos2 | F85: Dên | G85: TAIHO | H85: Cặp | J85: 90000 | K85: 100000 | L85: 110000 | O85: RP224H1 | P85: Miểng dên J08C/J05C Cos2 (RP224H1) - TAIHO
B86: HINO | C86: Dên J08C/J05C | D86: 114 | E86: Cos3 | F86: Dên | H86: Cặp
B87: HINO | C87: Dên J08C/J05C | D87: 114 | E87: Cos4 | F87: Dên | H87: Cặp
A88: HH078907 | B88: HINO | C88: (kiểm tra lại tồn) Bạc miểng J08CT/J08E Cos0 - MAHLE | D88: 114 | E88: Cos0 | F88: Baze+Dên | G88: MAHLE | H88: Bộ | I88: kiểm tra lại tồn | P88: (kiểm tra lại tồn) Bạc miểng J08CT/J08E Cos0 - MAHLE
A89: HH070653 | B89: HINO | C89: Bạc miểng J08CT/J08E Cos1 - TAIHO | D89: 114 | E89: Cos1 | F89: Baze+Dên | G89: TAIHO | H89: Bộ | P89: Bạc miểng J08CT/J08E Cos1 - TAIHO
A90: HH070659 | B90: HINO | C90: Bạc miểng J08CT/J08E Cos2 - TAIHO | D90: 114 | E90: Cos2 | F90: Baze+Dên | G90: TAIHO | H90: Bộ | P90: Bạc miểng J08CT/J08E Cos2 - TAIHO
A91: HH070660 | B91: HINO | C91: Bạc miểng J08CT/J08E Cos3 - TAIHO | D91: 114 | E91: Cos3 | F91: Baze+Dên | G91: TAIHO | H91: Bộ | P91: Bạc miểng J08CT/J08E Cos3 - TAIHO
B92: HINO | C92: Bạc Miểng J08CT/J08E | D92: 114 | E92: Cos4 | F92: Baze+Dên | H92: Bộ
A93: HH071108 | B93: HINO | C93: Bạc miểng EL100 Cos0 - TaiHo | D93: 116 | E93: Cos0 | F93: Baze+Dên | G93: TAIHO | H93: Bộ | P93: Bạc miểng EL100 Cos0 - TaiHo
A94: HH071142 | B94: HINO | C94: Bạc miểng EL100 Cos1 - TaiHo | D94: 116 | E94: Cos1 | F94: Baze+Dên | G94: TAIHO | H94: Bộ | P94: Bạc miểng EL100 Cos1 - TaiHo
A95: HH072007 | B95: HINO | C95: Bạc miểng EL100 Cos2 - TaiHo | D95: 116 | E95: Cos2 | F95: Baze+Dên | G95: TAIHO | H95: Bộ | P95: Bạc miểng EL100 Cos2 - TaiHo
B96: HINO | C96: Bạc Miểng EL100 | D96: 116 | E96: Cos3 | F96: Baze+Dên | H96: Bộ
B97: HINO | C97: Bạc Miểng EL100 | D97: 116 | E97: Cos4 | F97: Baze+Dên | H97: Bộ
B98: HINO | C98: Bạc Miểng EP100/P09C | D98: 120 | E98: Cos0 | F98: Baze+Dên | H98: Bộ
A99: HH070718 | B99: HINO | C99: Bạc miểng EP100/P09C cos1 - TAIHO | D99: 120 | E99: Cos1 | F99: Baze+Dên | G99: TAIHO | H99: Bộ | P99: Bạc miểng EP100/P09C cos1 - TAIHO
B100: HINO | C100: Bạc Miểng EP100/P09C | D100: 120 | E100: Cos2 | F100: Baze+Dên | H100: Bộ
...

Sheet 🔍 MIỂNG TRA CỨU
A1: 🔍 MIỂNG TRA CỨU — chuyển từ v10 (điền Mã HH + giá để vào Báo giá)
A2: 🏭 Hãng | B2: ⚙️ Mã ĐC | C2: 📐 ĐK | D2: Loại | E2: Tên loại | F2: PARNO | G2: Cung trong | H2: Cung ngoài | I2: Cao | J2: Dày | K2: 📦 ĐVT | L2: 🏷️ Mã HH | M2: 🏷️ TH SX | N2: 💰 Vốn | O2: 🟢 VIP | P2: 🟡 Ưu đãi | Q2: 🔵 Đại lý | R2: 🟣 Gara | S2: 📦 Tồn
A3: CATERPILLAR | B3: 1140/1145/1150/1160/3145/3150/3160 | D3: M | E3: Miểng baze | F3: 4W8091 | H3: 94.195 | I3: 25.4 | J3: 2.604 | K3: Bộ | S3: 🟢 CÓ
A4: CATERPILLAR | B4: 1140/1145/1150/1160/3145/3150/3160 | D4: R | E4: Miểng dên | F4: 9N5923 | H4: 73.74 | I4: 24.3 | J4: 2.407 | K4: Bộ | S4: 🟢 CÓ
A5: CATERPILLAR | B5: 3013C | D5: M | E5: Miểng baze | H5: 72.02 | I5: 19.5 | J5: 2 | K5: Bộ | S5: 🟢 CÓ
A6: CATERPILLAR | B6: 3013C | D6: R | E6: Miểng dên | H6: 55.02 | I6: 19.75 | J6: 1.5 | K6: Bộ | S6: 🟢 CÓ
A7: CATERPILLAR | B7: 3024/3024T | D7: M | E7: Miểng baze | H7: 72.02 | I7: 19.5 | J7: 2 | K7: Bộ | S7: 🟢 CÓ
A8: CATERPILLAR | B8: 3114 | C8: 105 | D8: M | E8: Miểng baze | F8: 101-1530 | H8: 95.015 | I8: 31.8 | J8: 2.44 | K8: Bộ | S8: 🟢 CÓ
A9: CATERPILLAR | B9: 3114 | C9: 105 | D9: R | E9: Miểng dên | F9: 7W9415 | H9: 75.014 | I9: 33.8 | J9: 2.465 | K9: Bộ | S9: 🟢 CÓ
A10: CATERPILLAR | B10: 3114/3116/3126 | C10: 105/110 | D10: M | E10: Miểng baze | F10: 107-7708 | H10: 95.015 | I10: 31.8 | J10: 2.44 | K10: Bộ | S10: 🟢 CÓ
A11: CATERPILLAR | B11: 3114/3116/3126 | C11: 105/110 | D11: R | E11: Miểng dên | F11: 7W9415 | H11: 75.014 | I11: 33.8 | J11: 2.465 | K11: Bộ | S11: 🟢 CÓ
A12: CATERPILLAR | B12: 3116 | C12: 105 | D12: M | E12: Miểng baze | F12: 101-1530 | H12: 95.015 | I12: 31.8 | J12: 2.44 | K12: Bộ | S12: 🟢 CÓ
A13: CATERPILLAR | B13: 3116 | C13: 105 | D13: R | E13: Miểng dên | F13: 7W9415 | H13: 75.014 | I13: 33.8 | J13: 2.465 | K13: Bộ | S13: 🟢 CÓ
A14: CATERPILLAR | B14: 3126 | C14: 110 | D14: M | E14: Miểng baze | F14: 107-7708 | H14: 95.015 | I14: 31.8 | J14: 2.44 | K14: Bộ | S14: 🟢 CÓ
A15: CATERPILLAR | B15: 3126 | C15: 110 | D15: R | E15: Miểng dên | F15: 7W9415 | H15: 75.014 | I15: 33.8 | J15: 2.465 | K15: Bộ | S15: 🟢 CÓ
A16: CATERPILLAR | B16: 3145/3150/3160 | D16: M | E16: Miểng baze | F16: 4W8091 | H16: 94.195 | I16: 25.4 | J16: 2.604 | K16: Bộ | S16: 🟢 CÓ
A17: CATERPILLAR | B17: 3145/3150/3160 | D17: R | E17: Miểng dên | F17: 9N5923 | H17: 73.74 | I17: 24.3 | J17: 2.407 | K17: Bộ | S17: 🟢 CÓ
A18: CATERPILLAR | B18: 3176 | D18: M | E18: Miểng baze | F18: 7W4107 | H18: 108.014 | I18: 35.8 | J18: 3.955 | K18: Bộ | S18: 🟢 CÓ
A19: CATERPILLAR | B19: 3176 | D19: R | E19: Miểng dên | F19: 4P8167 | H19: 86.812 | I19: 43.3 | J19: 2.363 | K19: Bộ | S19: 🟢 CÓ
A20: CATERPILLAR | B20: 3204 | D20: M | E20: Miểng baze | F20: 4W8093 | H20: 94.195 | I20: 25.4 | J20: 2.604 | K20: Bộ | S20: 🟢 CÓ
A21: CATERPILLAR | B21: 3204 | D21: R | E21: Miểng dên | F21: 8N6308 | H21: 96.2 | I21: 49.1 | J21: 3.058 | K21: Bộ | S21: 🟢 CÓ
A22: CATERPILLAR | B22: 3406/3408/3412 | D22: M | E22: Miểng baze | F22: 4W5492 | H22: 129.903 | I22: 41.8 | J22: 4.58 | K22: Bộ | S22: 🟢 CÓ
A23: CATERPILLAR | B23: 3406/3408/3412 | D23: R | E23: Miểng dên | F23: 9Y9497 | H23: 103.512 | I23: 39 | J23: 3.195 | K23: Bộ | S23: 🟢 CÓ
A24: CATERPILLAR | B24: 3508 | D24: M | E24: Miểng baze | F24: 149-6031 | H24: 169.762 | I24: 57.1 | J24: 4.805 | K24: Bộ | S24: 🟢 CÓ
A25: CATERPILLAR | B25: 3508 | D25: R | E25: Miểng dên | F25: 107-7330 | H25: 143.043 | I25: 57.1 | J25: 3.955 | K25: Bộ | S25: 🟢 CÓ
A26: CATERPILLAR | B26: 3512 | D26: M | E26: Miểng baze | F26: 105-0253 | H26: 169.762 | I26: 57.1 | J26: 4.805 | K26: Bộ | S26: 🟢 CÓ
A27: CATERPILLAR | B27: 3512 | D27: R | E27: Miểng dên | F27: 107-7330 | H27: 143.043 | I27: 57.1 | J27: 3.955 | K27: Bộ | S27: 🟢 CÓ
... A29: CATERPILLAR | B29: C6.4 | D29: R | E29: Miểng dên | F29: 297-1748 | H29: 69.02 | I29: 27.6 | J29: 2 | K29: Bộ | S29: 🟢 CÓ
A30: CATERPILLAR | B30: C6.6 | C30: 105 | D30: M | E30: Miểng baze | F30: 211-0588 | H30: 116.013 | I30: 35.7 | J30: 3.952 | K30: Bộ | S30: 🟢 CÓ
A31: CATERPILLAR | B31: C6.6 | C31: 105 | D31: R | E31: Miểng dên | F31: 217-0577 | H31: 86.813 | I31: 45.3 | J31: 2.368 | K31: Bộ | S31: 🟢 CÓ
A32: CATERPILLAR | B32: C7 | D32: R | E32: Miểng dên | F32: M2246638-6 | H32: 75.013 | I32: 33.8 | J32: 2.465 | K32: Bộ | S32: 🟢 CÓ
A33: CATERPILLAR | B33: C9 537 | C33: 112 | D33: M | E33: Miểng baze | F33: 151-2939 | H33: 112.013 | I33: 30.7 | J33: 3.952 | K33: Bộ | S33: 🟢 CÓ
A34: CATERPILLAR | B34: C9 537 | C34: 112 | D34: R | E34: Miểng dên | F34: 213-3190 | H34: 85.013 | I34: 36.6 | J34: 2.469 | K34: Bộ | S34: 🟢 CÓ
A35: CATERPILLAR | B35: D315/D315G/D318/D318G | D35: M | E35: Miểng baze | F35: 4F1726 | H35: 107.963 | I35: 69.5 | J35: 9.45 | K35: Bộ | S35: 🟢 CÓ
A36: CATERPILLAR | B36: D315/D315G/D318/D318G | D36: R | E36: Miểng dên | F36: 9F8580 | H36: 84.557 | I36: 38.1 | J36: 4.13 | K36: Bộ | S36: 🟢 CÓ
A37: CATERPILLAR | B37: D330/D333/G333/D334/3304/3306/C3306 | D37: M | E37: Miểng baze | F37: 4W5738 | H37: 96.926 | I37: 28.7 | J37: 3.988 | K37: Bộ | S37: 🟢 CÓ
A38: CATERPILLAR | B38: D330/D333/G333/D334/3304/3306/C3306 | D38: R | E38: Miểng dên | F38: 9F8580 | H38: 84.55 | I38: 38.1 | J38: 4.13 | K38: Bộ | S38: 🟢 CÓ
A39: CATERPILLAR | B39: D339 | D39: M | E39: Miểng baze | F39: 8N7928 | H39: 117.474 | I39: 82.6 | J39: 4.572 | K39: Bộ | S39: 🟢 CÓ
A40: CATERPILLAR | B40: D339 | D40: R | E40: Miểng dên | F40: 8N7933 | H40: 100.774 | I40: 50.8 | J40: 4.3 | K40: Bộ | S40: 🟢 CÓ
A41: CATERPILLAR | B41: D339/D342/G342/D7/D7C/D7D/D7E | C41: 108 | D41: M | E41: Miểng baze | F41: 9M2430 | H41: 104.515 | I41: 82.7 | J41: 4.572 | K41: Bộ | S41: 🟢 CÓ
A42: CATERPILLAR | B42: D339/D342/G342/D7/D7C/D7D/D7E | C42: 108 | D42: R | E42: Miểng dên | F42: 2M6499 | H42: 100.774 | I42: 65.1 | J42: 4.29 | K42: Bộ | S42: 🟢 CÓ
A43: CATERPILLAR | B43: D343/G343 | D43: M | E43: Miểng baze | F43: 7W2137 | H43: 124.104 | I43: 38.1 | J43: 4.856 | K43: Bộ | S43: 🟢 CÓ
A44: CATERPILLAR | B44: D343/G343 | D44: R | E44: Miểng dên | F44: 7W2136 | H44: 97.942 | I44: 45.08 | J44: 3.96 | K44: Bộ | S44: 🟢 CÓ
A45: CATERPILLAR | B45: D346/D348/D349 | D45: M | E45: Miểng baze | F45: 4W5488 | H45: 143.129 | I45: 47.9 | J45: 4.808 | K45: Bộ | S45: 🟢 CÓ
A46: CATERPILLAR | B46: D346/D348/D349 | D46: R | E46: Miểng dên | F46: 1W8539 | H46: 119.913 | I46: 34.9 | J46: 4.348 | K46: Bộ | S46: 🟢 CÓ
A47: CATERPILLAR | B47: D353/D353C/D353D/D9/D9D/D9E/D9H | D47: M | E47: Miểng baze | F47: 9M3896 | H47: 130.175 | I47: 73.2 | J47: 6.29 | K47: Bộ | S47: 🟢 CÓ
A48: CATERPILLAR | B48: D353/D353C/D353D/D9/D9D/D9E/D9H | D48: R | E48: Miểng dên | F48: 1N4336 | H48: 112.788 | I48: 50.3 | J48: 3.955 | K48: Bộ | S48: 🟢 CÓ
A49: CATERPILLAR | B49: D379/G379/D398/G398/D399/G399 | D49: M | E49: Miểng baze | F49: 8N7764 | H49: 161.874 | I49: 54.1 | J49: 7.854 | K49: Bộ | S49: 🟢 CÓ
A50: CATERPILLAR | B50: D379/G379/D398/G398/D399/G399 | D50: R | E50: Miểng dên | F50: 1N4336 | H50: 112.788 | I50: 50.3 | J50: 3.955 | K50: Bộ | S50: 🟢 CÓ
A51: CATERPILLAR | B51: S4K/S6K | D51: M | E51: Miểng baze | F51: 5I-7588 | H51: 95 | I51: 27.1 | J51: 2.49 | K51: Bộ | S51: 🟢 CÓ
A52: CATERPILLAR | B52: S4K/S6K | D52: R | E52: Miểng dên | F52: 5I-7637 | H52: 64 | I52: 29.6 | J52: 2 | K52: Bộ | S52: 🟢 CÓ
A53: CATERPILLAR | B53: XN1P | D53: M | E53: Miểng baze | F53: H1241/5 | H53: 63.246 | I53: 29.5 | J53: 1.888 | K53: Bộ | S53: 🟢 CÓ
A54: CATERPILLAR | B54: XN1P | D54: R | E54: Miểng dên | F54: 01-4558/4 | H54: 53.674 | I54: 23.4 | J54: 1.818 | K54: Bộ | S54: 🟢 CÓ
A55: ◆ CUMMINS (39 sản phẩm)
A56: CUMMINS | B56: 4BT/4D102/6D102/6BT | C56: 102 | D56: M | E56: Miểng baze | F56: 3802070 | G56: 83 | H56: 88 | I56: 37.3 | J56: 2.46 | K56: Bộ | S56: 🟢 CÓ
A57: CUMMINS | B57: 4BT/4D102/6D102/6BT | C57: 102 | D57: R | E57: Miểng dên | F57: 3901170 | G57: 69 | H57: 73 | I57: 31.1 | J57: 1.97 | K57: Bộ | S57: 🟢 CÓ
A58: CUMMINS | B58: 6CT | C58: 114 | D58: M | E58: Miểng baze | F58: 3802210 | H58: 105 | I58: 42.85 | J58: 3.45 | K58: Bộ
A59: CUMMINS | B59: 6CT | C59: 114 | D59: R | E59: Miểng dên | F59: 3901430 | H59: 81 | I59: 38.1 | J59: 2.47 | K59: Bộ | S59: 🟢 CÓ
A60: CUMMINS | B60: 6D107/QSB6.7/6BT NEW | C60: 102/107 | D60: M | E60: Miểng baze | F60: 6736-21-8110 | H60: 88 | I60: 37.3 | J60: 2.46 | K60: Bộ | S60: 🟢 CÓ
A61: CUMMINS | B61: 6D107/QSB6.7/6BT NEW | C61: 102/107 | D61: R | E61: Miểng dên | F61: 6754-31-3410 | H61: 73 | I61: 31.1 | J61: 1.97 | K61: Bộ | S61: 🟢 CÓ
A62: CUMMINS | B62: A2300 | D62: M | E62: Miểng baze | F62: 4900232 | H62: 58 | I62: 22.05 | J62: 2 | K62: Bộ | S62: 🟢 CÓ
A63: CUMMINS | B63: A2300 | D63: R | E63: Miểng dên | F63: 4900563 | H63: 53 | I63: 22.05 | J63: 1.5 | K63: Bộ | S63: 🟢 CÓ
A64: CUMMINS | B64: ISB | C64: 102 | D64: M | E64: Miểng baze | F64: 3802070 | H64: 88 | I64: F37.300 | J64: 2.46 | K64: Bộ | S64: 🟢 CÓ
A65: CUMMINS | B65: ISB | C65: 102 | D65: R | E65: Miểng dên | F65: 4893693 | H65: 73 | I65: 31.1 | J65: 1.97 | K65: Bộ | S65: 🟢 CÓ
A66: CUMMINS | B66: ISC | D66: M | E66: Miểng baze | F66: 3945917 | H66: 105 | I66: F42.850 | J66: 3.45 | K66: Bộ | S66: 🟢 CÓ
A67: CUMMINS | B67: ISC | D67: R | E67: Miểng dên | F67: 3950661 | H67: 81 | I67: 36 | J67: 2.47 | K67: Bộ | S67: 🟢 CÓ
A68: CUMMINS | B68: ISF | D68: M | E68: Miểng baze | F68: 4996250 | H68: 79.018 | I68: F32.24 | J68: 2.465 | K68: Bộ | S68: 🟢 CÓ
A69: CUMMINS | B69: ISF | D69: R | E69: Miểng dên | H69: 73 | I69: 31.1 | J69: 1.97 | K69: Bộ | S69: 🟢 CÓ
A70: CUMMINS | B70: ISX/QSX | D70: M | E70: Miểng baze | F70: 3800298 | H70: 133 | I70: 39.7 | J70: 3.21 | K70: Bộ | S70: 🟢 CÓ
A71: CUMMINS | B71: ISX/QSX | D71: R | E71: Miểng dên | F71: 4089405 | H71: 99 | I71: 46.7 | J71: 2.375 | K71: Bộ | S71: 🟢 CÓ
A72: CUMMINS | B72: K38，KT38，KTA38/KTAA38/KTA2300，KV12 | D72: M | E72: Miểng baze | F72: AR12250 | H72: 173.88 | I72: 52.7 | J72: 4.335 | K72: Bộ | S72: 🟢 CÓ
A73: CUMMINS | B73: K38，KT38，KTA38/KTAA38/KTA2300，KV12 | D73: R | E73: Miểng dên | F73: 3047390 | H73: 114.36 | I73: 52.7 | J73: 3.157 | K73: Bộ | S73: 🟢 CÓ
A74: CUMMINS | B74: K50，KT50，KTA50/KTAA50/KT3067，KTA3067，KV16 | D74: M | E74: Miểng baze | F74: 3018210 | H74: 173.88 | I74: 52.7 | J74: 4.335 | K74: Bộ | S74: 🟢 CÓ
A75: CUMMINS | B75: K50，KT50，KTA50/KTAA50/KT3067，KTA3067，KV16 | D75: R | E75: Miểng dên | F75: 3047390 | H75: 114.36 | I75: 52.7 | J75: 3.157 | K75: Bộ | S75: 🟢 CÓ
A76: CUMMINS | B76: KT6/KT450/KTA600/KT1150/KT19 | C76: 158.7 | D76: M | E76: Miểng baze | F76: AR12270 | H76: 148.49 | I76: 46 | J76: 4.35 | K76: Bộ | S76: 🟢 CÓ
A77: CUMMINS | B77: KT6/KT450/KTA600/KT1150/KT19 | C77: 158.7 | D77: R | E77: Miểng dên | F77: 205840 | H77: 108.05 | I77: 56.1 | J77: 3.17 | K77: Bộ | S77: 🟢 CÓ
A78: CUMMINS | B78: L-10/LT-10/MT10/M11/ISM | C78: 91.1/125 | D78: M | E78: Miểng baze | F78: 3801150 | H78: 122 | I78: 36.6 | J78: 3.94 | K78: Bộ | S78: 🟢 CÓ
A79: CUMMINS | B79: L-10/LT-10/MT10/M11/ISM | C79: 91.1/125 | D79: R | E79: Miểng dên | F79: 3016760 | H79: 84 | I79: 42.2 | J79: 2.47 | K79: Bộ | S79: 🟢 CÓ
A80: CUMMINS | B80: L/P/N14 | C80: 91.1/139.7 | D80: M | E80: Miểng baze | F80: 3801260 | H80: 120.65 | I80: 55.88 | J80: 3.14 | K80: Bộ | S80: 🟢 CÓ
A81: CUMMINS | B81: L/P/N14 | C81: 91.1/139.7 | D81: R | E81: Miểng dên | F81: 3055145 | H81: 93.76 | I81: 48.54 | J81: 2.405 | K81: Bộ | S81: 🟢 CÓ
A82: CUMMINS | B82: NH6/NH180/195/NH195/200/NH220/250/NH260/280/NH290/320/NT855 CID | C82: 130/139.7 | D82: M | E82: Miểng baze | F82: 3801260 | H82: 120.65 | I82: 55.88 | J82: 3.14 | K82: Bộ | S82: 🟢 CÓ
A83: CUMMINS | B83: NH6/NH180/195/NH195/200/NH220/250/NH260/280/NH290/320/NT855 CID | C83: 130/139.7 | D83: R | E83: Miểng dên | F83: 203670 | H83: 83.13 | I83: 50.3 | J83: 1.85 | K83: Bộ | S83: 🟢 CÓ
A84: CUMMINS | B84: QSB/4B-3.3 | D84: M | E84: Miểng baze | F84: 3800872 | H84: 74 | I84: 25 | J84: 1.971 | K84: Bộ | S84: 🟢 CÓ
A85: CUMMINS | B85: QSB/4B-3.3 | D85: R | E85: Miểng dên | F85: 4993834 | H85: 61 | I85: 25 | J85: 1.978 | K85: Bộ | S85: 🟢 CÓ
A86: CUMMINS | B86: V378 | D86: M | E86: Miểng baze | F86: BM99830 | H86: 95.33 | I86: 29 | J86: 3.18 | K86: Bộ | S86: 🟢 CÓ
A87: CUMMINS | B87: V378 | D87: R | E87: Miểng dên | F87: 553650 | H87: 68.38 | I87: 29.8 | J87: 2.4 | K87: Bộ | S87: 🟢 CÓ
A88: CUMMINS | B88: V504/V505 | D88: M | E88: Miểng baze | F88: BM99820 | H88: 95.33 | I88: 29 | J88: 3.18 | K88: Bộ | S88: 🟢 CÓ
A89: CUMMINS | B89: V504/V505 | D89: R | E89: Miểng dên | F89: 553650 | H89: 68.38 | I89: 29.8 | J89: 2.4 | K89: Bộ | S89: 🟢 CÓ
A90: CUMMINS | B90: V8-155 | D90: M | E90: Miểng baze | F90: BM99830 | H90: 95.33 | I90: 29 | J90: 3.18 | K90: Bộ | S90: 🟢 CÓ
A91: CUMMINS | B91: V8-155 | D91: R | E91: Miểng dên | F91: 3012360 | H91: 68.38 | I91: 29.8 | J91: 2.4 | K91: Bộ | S91: 🟢 CÓ
A92: CUMMINS | B92: V903/VT903 | D92: M | E92: Miểng baze | F92: MS-1265P | H92: 103.2 | I92: 33.3 | J92: 3.94 | K92: Bộ | S92: 🟢 CÓ
A93: CUMMINS | B93: V903/VT903 | D93: R | E93: Miểng dên | F93: CB-1073P | H93: 84.24 | I93: 33.9 | J93: 2.4 | K93: Bộ | S93: 🟢 CÓ
A94: CUMMINS | B94: VT1710/VT700/VT900/VT28 | D94: R | E94: Miểng dên | F94: 200600 | H94: 101.663 | I94: 46.1 | J94: 3.17 | K94: Bộ | S94: 🟢 CÓ
A95: ◆ DEUTZ-KHD (38 sản phẩm)
A96: DEUTZ-KHD | B96: BF 4M 1013 | D96: M | E96: Miểng baze | F96: 02-3808 | H96: 90.52 | I96: 31 | J96: 2.73 | K96: Bộ | S96: 🟢 CÓ
A97: DEUTZ-KHD | B97: BF 4M 1013 | D97: R | E97: Miểng dên | F97: 71-3922 | H97: 72.52 | I97: 30 | J97: 2.232 | K97: Bộ | S97: 🟢 CÓ
A98: DEUTZ-KHD | B98: BF 6 L 913/BF 6 L 913 T/BF 6L 913/BF 6L 913 C/BF 6L 913 T | C98: 91.1/114 | D98: M | E98: Miểng baze | F98: 02-3168 | H98: 79 | I98: 25 | J98: 1.98 | K98: Bộ | S98: 🟢 CÓ
A99: DEUTZ-KHD | B99: BF 6 L 913/BF 6 L 913 T/BF 6L 913/BF 6L 913 C/BF 6L 913 T | C99: 91.1/114 | D99: R | E99: Miểng dên | H99: 70 | I99: 25 | J99: 1.98 | K99: Bộ | S99: 🟢 CÓ
A100: DEUTZ-KHD | B100: BF 6L 413/F 6L 413/F6L 413L | C100: 114 | D100: M | E100: Miểng baze | F100: H925/4 | H100: 96 | I100: 29 | J100: 2.97 | K100: Bộ | S100: 🟢 CÓ
A101: DEUTZ-KHD | B101: BF 6L 413/F 6L 413/F6L 413L | C101: 114 | D101: R | E101: Miểng dên | F101: 71-2834 | H101: 80 | I101: 27.8 | J101: 2.47 | K101: Bộ | S101: 🟢 CÓ
...

Sheet 🔧 BẠC THAU
A1: 🔧 BẠC THAU — nhập 16/06/2026 (điền giá vào Vốn/VIP/Ưu đãi/Đại lý/Gara)
A2: Mã HH | B2: Tên vật tư | C2: 📐 ĐK | D2: ĐVT | E2: Vốn | F2: VIP | G2: Ưu đãi | H2: Đại lý | I2: Gara | J2: Tồn | K2: PARNO | L2: Ghi chú
A3: HH0635 | B3: Bạc thau 4BB1/4BD1/4BG1 - TAIHO | C3: 102/105 | D3: Cái
A4: HH01076 | B4: Bạc thau 4BT - IVECO | C4: 102 | D4: Cái
A5: HH082040 | B5: Bạc thau 4D120/ 4D130 đã xoáy-Taiho (1 bộ xuất 8 cái) | C5: 120/130 | D5: Cái
A6: HH00087 | B6: Bạc thau 4D30/4D31/4D32/6D31 | C6: 100/104 | D6: Cái
A7: HH00510 | B7: Bạc thau 4D30/4D31/4D32/S4KT - NDC | C7: 100/102/104 | D7: Cái
A8: HH0323 | B8: Bạc thau 4D30/4D31/4D32/S4KT - TAIHO | C8: 100/102/104 | D8: Cái | H8: 40000
A9: HH071412 | B9: Bạc thau 4D33/4D31/D4AE/4D34 (ắc 34)- TAIHO | C9: 100/104/108 | D9: Cái | H9: 40000
A10: HH071413 | B10: Bạc thau 4D35/ 4D34 (ắc 36) / 6D34 - TAIHO | C10: 104/110 | D10: Cái | H10: 62500
A11: HH081210 | B11: Bạc thau 4D55/ 4D56 (chưa xoáy) | C11: 91.1 | D11: Cái
A12: HH081209 | B12: Bạc thau 4D55/ 4D56 (xoáy rồi) | C12: 91.1 | D12: Cái
A13: HH00036 | B13: Bạc thau 4D92/4D94 - NDC | C13: 92/94 | D13: Cái
A14: HH071422 | B14: Bạc thau 4D92/4D94 - TAIHO | C14: 92/94 | D14: Cái
A15: HH071427 | B15: Bạc thau 4HG1/4HH1/4HE1/4HF1 - TAIHO | C15: 112 | D15: Cái | G15: 62500 | H15: 70000
A16: HH00057 | B16: Bạc thau 4JA1/4JB1 ắc 31 | C16: 93 | D16: Cái | G16: 30000 | H16: 35000
A17: HH076319 | B17: Bạc thau 4JA1/4JB1 ắc 31 - TDC P450L | C17: 93 | D17: Cái | G17: 30000 | H17: 35000
A18: HH078363 | B18: Bạc thau 4JB1/4JA1 chưa xoáy ắc 31 - CS IVECO | C18: 93 | D18: Cái | G18: 30000 | H18: 35000
A19: HH076604 | B19: Bạc thau 4JB1/4JG1/4JG2 chưa xoáy ắc 34 - CS IVECO | C19: 93/95.4 | D19: Cái | G19: 25000 | H19: 30000
A20: HH01078 | B20: Bạc thau 6BT - IVECO | C20: 102 | D20: Cái
A21: HH01079 | B21: Bạc thau 6CT | C21: 114 | D21: Cái | G21: 45000 | H21: 50000
A22: HH071423 | B22: Bạc thau 6D105/ S6D105/ S4D105-5 ắc 40 - TAIHO | C22: 105 | D22: Cái | H22: 50000
A23: HH00143 | B23: Bạc thau 6D105-1/S6D110 dên xéo - NDC | C23: 105/110 | D23: Cái
A24: HH076609 | B24: Bạc thau 6D107/6D102/4D102/6BT/4BT chưa xoáy - CS IVECO | C24: 102/107 | D24: Cái
A25: HH071426 | B25: Bạc thau 6D107/6D102/4D102/6BT/4BT/S6D107/S6D102/S4D102 - TAIHO | C25: 102/107 | D25: Cái | H25: 100000
A26: HH075680 | B26: Bạc thau 6D107/6D102/4D102/6BT/4BT/S6D107/S6D102/S4D102 loại bán hoàn thiện | C26: 102/107 | D26: Cái | G26: 50000 | H26: 60000
A27: HH00365 | B27: Bạc thau 6D125 | D27: Cái
A28: HH0217 | B28: Bạc thau 6D15T/16T/17T/NE6TA | C28: 110 | D28: Cái
A29: HH071415 | B29: Bạc thau 6D15T/6D16T/6D17T dên xéo, lưng 42 - TAIHO | C29: 118 | D29: Cái | H29: 75000
A30: HH00188 | B30: Bạc thau 6D16/6D105/4D105 size 38 | C30: 105 | D30: Cái
A31: HH00287 | B31: Bạc thau 6D16/6D15/6D14/6D11/6D10/4D105 phi 38 lưng 41 - TAIHO | C31: 105/113 | D31: Cái | G31: 50000 | H31: 60000
A32: HH20486 | B32: Bạc thau 6D16T/ 6M60T lưng 42 dên xéo | C32: 118 | D32: Cái
A33: HH076608 | B33: Bạc thau 6D20/6D21/6D22/6D24 chưa xoáy - CS IVECO | C33: 125 | D33: Cái
A34: HH084105 | B34: Bạc thau 6D20/6D21/6D22/6D24 chưa xoáy - ĐL | C34: 125 | D34: Cái
A35: HH071429 | B35: Bạc thau 6D31 (P903H) ắc 34 - TAIHO | D35: Cái | H35: 60000
A36: HH00046 | B36: Bạc thau 6D34/ 4D34 ắc 36 (lắp lẫn DB58 ắc 36) | C36: 102/104 | D36: Cái
A37: HH00038 | B37: Bạc thau 6D95L/6D95 - NDC | D37: Cái
A38: HH071425 | B38: Bạc thau 6D95L/6D95 - TAIHO | D38: Cái | G38: 40000 | H38: 45000
A39: HH071428 | B39: Bạc thau 6HG1/6HH1/6HE1/6HF1 - TAIHO | C39: 110/115 | D39: Cái | H39: 70000
A40: HH080598 | B40: Bạc thau 6HG1/6HH1/6HE1/6HF1 -ĐL | C40: 110/115 | D40: Cái
A41: HH083940 | B41: Bạc thau 6HK1/6HE1-T , Ắc 40- DAIDO ĐL | C41: 110/115 | D41: Cái
A42: HH00494 | B42: Bạc thau 6M60T/6D16T phi 42 dên xéo - NDC | C42: 118 | D42: Cái
A43: HH083359 | B43: Bạc thau 6RB1 (ắc 52) đã Xoáy - Đài Loan | C43: 135 | D43: Cái
A44: HH00352 | B44: Bạc thau 6SD1 - TAIHO | C44: 120 | D44: Cái | G44: 90000 | H44: 100000
A45: HH071414 | B45: Bạc thau 8DC9 - TAIHO | D45: Cái
A46: HH083761 | B46: Bạc thau C221, chưa xoáy | C46: 83 | D46: Cái
A47: HH071416 | B47: Bạc thau C223/602/C190/BH C240 NEW - TAIHO | C47: 86/88 | D47: Cái
A48: HH078214 | B48: Bạc thau D1146 / DE08 / 65.02405-1011 - DOOSAN | C48: 111 | D48: Cái | G48: 60000 | H48: 70000
A49: HH078215 | B49: Bạc thau D2366 / DE12 / 65.02405-1006 - DOOSAN | C49: 123 | D49: Cái | G49: 70000 | H49: 75000
A50: HH0278 | B50: Bạc thau DA120 - TAIHO | C50: 100 | D50: Cái | G50: 40000 | H50: 50000
A51: HH071417 | B51: Bạc thau DA220 - TAIHO | C51: 100 | D51: Cái | G51: 40000 | H51: 50000
A52: HH078213 | B52: Bạc thau DL08 / 65.02503-8038 - DOOSAN | C52: 108 | D52: Cái | G52: 60000 | H52: 70000
A53: HH0639 | B53: Bạc thau DM100/DQ100 - NDC | C53: 90 | D53: Cái
A54: HH071418 | B54: Bạc thau E120/6RB1T ắc 50 - TAIHO | D54: Cái | H54: 60000
A55: HH081676 | B55: Bạc thau FD33 đã xoáy -Đài Loan | D55: Cái
A56: HH072200 | B56: Bạc thau FE6/ND6/NE6 - NDC | C56: 108 | D56: Cái
A57: HH00118 | B57: Bạc thau H07C/ H06C/ EH700 - TAIHO | C57: 108/110 | D57: Cái | G57: 45000 | H57: 50000
A58: HH075529 | B58: Bạc thau J05E/J08E/J08C- NDC | C58: 112/114 | D58: Cái
A59: HH00581 | B59: Bạc thau J05E/J08E/J08C- TAIHO | C59: 112/114 | D59: Cái
A60: HH074261 | B60: Bạc thau K3600/SL (ắc 34) - NDC | C60: 100 | D60: Cái
A61: HH00128 | B61: Bạc thau Kia HA/T3000/JS/4D94E/S4S/JT (phi 30) - NDC | C61: 94/95/98 | D61: Cái
A62: HH084300 | B62: Bạc thau Kia HA/T3000/JS/4D94E/S4S/JT đã xoáy-TAIHO | C62: 94/95/98 | D62: Cái
A63: HH084011 | B63: Bạc thau NH220 Chưa xoáy-ĐL | C63: 130 | D63: Cái
A64: HH076132 | B64: Bạc thau P11C / EP100 - daido | D64: Cái
A65: HH0320 | B65: Bạc thau S4D95/4D95- TAIHO | C65: 95 | D65: Cái
A66: HH071411 | B66: Bạc thau S4E/4DR5 - TAIHO | C66: 92/94 | D66: Cái
A67: HH071424 | B67: Bạc thau S6D105/S6D110/6D105/6D110 - TAIHO | C67: 105/110 | D67: Cái | H67: 50000
A68: HH00153 | B68: Bạc thau S6D108/ 6D108 - TAIHO | C68: 108 | D68: Cái | H68: 100000
A69: HH076605 | B69: Bạc thau 4BB1/4BD1/6BB1/6BD1/6BE1/6BG1/DB58 chưa xoáy - CS IVECO | C69: 102/105 | D69: Cái | G69: 30000 | H69: 40000
A70: HH076607 | B70: Bạc thau 6D31/4D31 chưa xoáy - CS IVECO | C70: 100 | D70: Cái | G70: 30000 | H70: 40000

Sheet 📏 CĂN DỌC
A1: 📏 CĂN DỌC — nhập 16/06/2026 (điền giá vào Vốn/VIP/Ưu đãi/Đại lý/Gara)
A2: Mã HH | B2: Tên vật tư | C2: 📐 ĐK | D2: ĐVT | E2: Vốn | F2: VIP | G2: Ưu đãi | H2: Đại lý | I2: Gara | J2: Tồn | K2: PARNO | L2: Ghi chú
A3: HH080557 | B3: Căn dọc 1DZ Cos0 - TDC - T9383A | C3: 86 | D3: Bộ | F3: 55000 | G3: 60000 | H3: 70000
A4: HH080558 | B4: Căn dọc 1DZ Cos1 - TDC - T9383A | C4: 86 | D4: Bộ | F4: 55000 | G4: 60000 | H4: 70000
A5: HH074817 | B5: Căn dọc 2J Cos0 | C5: 88 | D5: Bộ
A6: HH073964 | B6: Căn dọc 2J Cos1 | C6: 88 | D6: Bộ
A7: HH078932 | B7: Căn dọc 3306/ 3304 cos0 - TDC TW1110K2 | D7: Bộ | F7: 300000 | G7: 330000 | H7: 360000
A8: HH080513 | B8: Căn dọc 3D84/4D84/3TN84/4TN84/3D88/4D88/3TN88/4TN88 - Cos0 - TDC - T894A | C8: 84/88 | D8: Bộ | F8: 60000 | G8: 70000 | H8: 80000
A9: HH076341 | B9: Căn dọc 3D84/4D84/3TN84/4TN84/3D88/4D88/3TN88/4TN88 - Cos0 - TDC T-TNE84A | C9: 84/88 | D9: Bộ | F9: 50000 | G9: 60000 | H9: 70000
A10: HH078969 | B10: Căn dọc 3D84/4D84/3TN84/4TN84/3D88/4D88/3TN88/4TN88 - Cos1 - TDC T-TNE84A | C10: 84/88 | D10: Bộ | F10: 50000 | G10: 60000 | H10: 70000
A11: HH078970 | B11: Căn dọc 3D84/4D84/3TN84/4TN84/3D88/4D88/3TN88/4TN88 - Cos2 - TDC T-TNE84A | C11: 84/88 | D11: Bộ | F11: 60000 | G11: 70000 | H11: 80000
A12: HH082837 | B12: Căn dọc 3TNE78/ 3TN78/ 3TNE82/ 3D82 (T-TNE78A) - Cos0 - TDC | C12: 78/82 | D12: Cặp | F12: 50000 | G12: 60000 | H12: 70000
A13: HH082838 | B13: Căn dọc 3TNE78/ 3TN78/ 3TNE82/ 3D82 (T-TNE78A) - Cos1 - TDC | C13: 78/82 | D13: Cặp | F13: 50000 | G13: 60000 | H13: 70000
A14: HH076909 | B14: Căn dọc 490QB Cos0 | D14: Bộ
A15: HH079868 | B15: Căn dọc 4D105-3/ 4D105-1 Cos0 - CS IVECO | C15: 105 | D15: Bộ | F15: 50000 | G15: 60000 | H15: 70000
A16: HH079869 | B16: Căn dọc 4D105-3/ 4D105-1 Cos1 - CS IVECO | C16: 105 | D16: Bộ | F16: 50000 | G16: 60000 | H16: 70000
A17: HH00309 | B17: Căn dọc 4D105-3/4D105-1 Cos0 | C17: 105 | D17: Bộ
A18: HH079854 | B18: Căn dọc 4D105-5/ 6D105/ S6D105/ 6D110 Cos0 - CS IVECO | C18: 105 | D18: Bộ | F18: 50000 | G18: 60000 | H18: 70000
A19: HH079855 | B19: Căn dọc 4D105-5/ 6D105/ S6D105/ 6D110 Cos1 - CS IVECO | C19: 105 | D19: Bộ | F19: 50000 | G19: 60000 | H19: 70000
A20: HH00319 | B20: Căn dọc 4D105-5/6D105/S6D105/6D110 Cos0 | C20: 105 | D20: Bộ
A21: HH076331 | B21: Căn dọc 4D120/4D130 cos0 - TDC T852P | C21: 120/130 | D21: Bộ | F21: 460000 | G21: 500000 | H21: 550000
A22: HH079876 | B22: Căn dọc 4D30/ 4D31/ 4D32/ 6D31/ 6DS7 Cos0 - CS IVECO | C22: 98/100/104 | D22: Bộ
A23: HH079877 | B23: Căn dọc 4D30/ 4D31/ 4D32/ 6D31/ 6DS7 Cos1 - CS IVECO | C23: 98/100/104 | D23: Bộ | F23: 50000 | G23: 60000 | H23: 70000
A24: HH00292 | B24: Căn dọc 4D30/4D31/4D32/6D31/6DS7 Cos0 | C24: 98/100/104 | D24: Bộ
A25: HH00291 | B25: Căn dọc 4D30/4D31/4D32/6D31/6DS7 Cos1 | C25: 98/100/104 | D25: Bộ
A26: HH071300 | B26: Căn dọc 4D30/4D31/4D32/6D31/6DS7 Cos2 | C26: 98/100/104 | D26: Bộ
A27: HH00293 | B27: Căn dọc 4D34/6D34 Cos0 | C27: 104 | D27: Bộ
A28: HH080556 | B28: Căn dọc 4D56-Ti cos0 - TDC - T7278A | D28: Bộ | F28: 40000 | G28: 50000 | H28: 60000
A29: HH079862 | B29: Căn dọc 4D92/ 4D94 - Cos0 - CS IVECO | C29: 92/94 | D29: Bộ | F29: 40000 | G29: 50000 | H29: 60000
A30: HH079863 | B30: Căn dọc 4D92/ 4D94 - Cos1 - CS IVECO | C30: 92/94 | D30: Bộ | F30: 40000 | G30: 50000 | H30: 60000
A31: HH00106 | B31: Căn dọc 4D92/4D94 - Cos0 | C31: 92/94 | D31: Bộ
A32: HH00107 | B32: Căn dọc 4D92/4D94 - Cos1 | C32: 92/94 | D32: Bộ
A33: HH00523 | B33: Căn dọc 4D92/4D94 - Cos3 | C33: 92/94 | D33: Bộ
A34: HH074284 | B34: Căn dọc 4D94E/4TN94 - Cos0 | C34: 94 | D34: Bộ
A35: HH074551 | B35: Căn dọc 4D94E/4TN94 - Cos1 | C35: 94 | D35: Bộ
A36: HH074552 | B36: Căn dọc 4D94E/4TN94 - Cos2 | C36: 94 | D36: Bộ
A37: HH078971 | B37: Căn dọc 4D94E/4TNV94/4TNE94 - Cos0 - TDC - T851A | C37: 94 | D37: Bộ | F37: 60000 | G37: 70000 | H37: 80000
A38: HH079870 | B38: Căn dọc 4D95/ 6D95 Cos0 - CS IVECO | C38: 95 | D38: Bộ
A39: HH00104 | B39: Căn dọc 4D95/6D95 Cos0 | C39: 95 | D39: Bộ
A40: HH078958 | B40: Căn dọc 4D95/6D95 Cos0 - TDC - T888L | C40: 95 | D40: Bộ
A41: HH076662 | B41: Căn dọc 4FE1/4FB1/ 4FD1 Cos1 | D41: Bộ
A42: HH071380 | B42: Căn dọc 4HF1/4HG1/6HH1/6HK1 Cos2 | C42: 112/115 | D42: Bộ
A43: HH078936 | B43: Căn dọc 4HG1/4HK1/6HK1/6HE1/6HH1 Cos1 - TDC - T4547A | C43: 110/115 | D43: Bộ | F43: 60000 | G43: 70000 | H43: 80000
A44: HH075796 | B44: Căn dọc 4JB1/C240/4JG2 Cos0 - TDC T4651A | C44: 86/93 | D44: Bộ | F44: 30000 | G44: 40000 | H44: 50000
A45: HH073289 | B45: Căn dọc 4JC1/4JA1/C223 Cos0 | C45: 88 | D45: Bộ
A46: HH072414 | B46: Căn dọc 4JC1/4JA1/C223 Cos1 | C46: 88 | D46: Bộ
A47: HH083688 | B47: Căn dọc 4JC1/4JA1/C223 Cos2 | C47: 88 | D47: Bộ
A48: HH079264 | B48: Căn dọc 4LE1-Cos0 | C48: 85 | D48: Bộ
A49: HH083639 | B49: Căn dọc 4M40 Cos0-NDC | C49: 95 | D49: Bộ
A50: HH00068 | B50: Căn dọc 6BB1/4BA1/4BB1/4BE1/D500 Cos0 | C50: 98/102/105 | D50: Bộ
A51: HH00069 | B51: Căn dọc 6BB1/4BA1/4BB1/4BE1/D500 Cos1 | C51: 98/102/105 | D51: Bộ
A52: HH079873 | B52: Căn dọc 6BD1/ 4BD1/ DB58/ 6BG1/ 4BG1 - Cos1 - CS IVECO | C52: 102/105 | D52: Bộ | F52: 50000 | G52: 60000 | H52: 70000
A53: HH078778 | B53: Căn dọc 6BD1/ 4BD1/DB58/6BG1 Cos4 | C53: 102/105 | D53: 1Máy
A54: HH071019 | B54: Căn dọc 6BD1/4BD1/db58/6BG1 Cos2 | C54: 102/105 | D54: Bộ
A55: HH078933 | B55: Căn dọc 6BD1/4BD1/DB58/6BG1 Cos2 - TDC T427A | C55: 102/105 | D55: Bộ | F55: 60000 | G55: 70000 | H55: 80000
A56: HH076337 | B56: Căn dọc 6BD1/4BD1/DB58/6BG1/4BG1 Cos 0.125 - TDC T427A | C56: 102/105 | D56: Bộ
A57: HH076336 | B57: Căn dọc 6BD1/4BD1/DB58/6BG1/4BG1 Cos0 - TDC T427A | C57: 102/105 | D57: Bộ | F57: 60000 | G57: 70000 | H57: 80000
A58: HH01081 | B58: Căn dọc 6BT Cos0 - IVECO | C58: 102 | D58: Bộ
A59: HH01082 | B59: Căn dọc 6BT Cos1 - IVECO | C59: 102 | D59: Bộ
A60: HH01083 | B60: Căn dọc 6BT Cos2 - IVECO | C60: 102 | D60: Bộ
A61: HH01085 | B61: Căn dọc 6CT Cos1 - IVECO | C61: 114 | D61: Bộ
A62: HH01086 | B62: Căn dọc 6CT Cos2 - IVECO | C62: 114 | D62: Bộ
A63: HH079860 | B63: Căn dọc 6D125/ S6D125 Cos0 - CS IVECO | C63: 125 | D63: Bộ
A64: HH079861 | B64: Căn dọc 6D125/ S6D125 Cos1 - CS IVECO | C64: 125 | D64: Bộ
A65: HH075814 | B65: Căn dọc 6D14/6D15/6D16 - (cos) 0.15 - TDC T626L | C65: 113 | D65: Bộ
A66: HH00202 | B66: Căn dọc 6D14/6D15/6D16 Cos0 | C66: 113 | D66: Bộ
A67: HH071118 | B67: Căn dọc 6D14/6D15/6D16 Cos1 | C67: 113 | D67: Bộ
A68: HH082205 | B68: Căn dọc 6D16T/6M61 Cos0 Daido | C68: 118/130 | D68: Bộ
A69: HH079878 | B69: Căn dọc 6D20/ 6D22/ 6D24 - Cos0 - CS IVECO | C69: 125 | D69: Bộ
A70: HH079879 | B70: Căn dọc 6D20/ 6D22/ 6D24 - Cos1 - CS IVECO | C70: 125 | D70: Bộ
A71: HH071860 | B71: Căn dọc 6D22/6D24 cos0 - TDC T607K | D71: Cái
A72: HH079884 | B72: Căn dọc 8DC9/ 8DC11 Cos0 - CS IVECO | C72: 142/142.2 | D72: Cái | F72: 70000 | G72: 80000 | H72: 90000
A73: HH079885 | B73: Căn dọc 8DC9/ 8DC11 Cos1 - CS IVECO | C73: 142/142.2 | D73: Cái | F73: 70000 | G73: 80000 | H73: 90000
A74: HH00599 | B74: Căn dọc 8DC9/8DC11 Cos2 ĐL | C74: 142/142.2 | D74: Cái
A75: HH075297 | B75: Căn dọc BF6L912 - Cos0 | C75: 100 | D75: Bộ
A76: HH080562 | B76: Căn dọc BF6L912/ BF4L912 Cos0 - TDC - TW3610A4 | C76: 100 | D76: Bộ | F76: 70000 | G76: 80000 | H76: 90000
A77: HH080563 | B77: Căn dọc BF6L913/ BF4L913 Cos0 - TDC - TW3620A4 | C77: 102 | D77: Bộ
A78: HH080251 | B78: Căn dọc C6.4 - cos0 | D78: Bộ
A79: HH076172 | B79: Căn dọc D1146 Cos0 - Doosan | C79: 111 | D79: Bộ
A80: HH076173 | B80: Căn dọc D1146 Cos1 - Doosan | C80: 111 | D80: Bộ
A81: HH076174 | B81: Căn dọc D2366 Cos0 - Doosan | C81: 123 | D81: Bộ
A82: HH076175 | B82: Căn dọc D2366 Cos1 - Doosan | C82: 123 | D82: Bộ
A83: HH081216 | B83: Căn dọc D4CB / D4CC - Cos0 | C83: 91.1/95 | D83: Bộ
A84: HH079491 | B84: Căn dọc D4CB / D4CC - Cos1 | C84: 91.1/95 | D84: Bộ
A85: HH01003 | B85: Căn dọc DA120/DA220/DA640 Cos0 | C85: 100 | D85: Bộ
A86: HH079907 | B86: Căn dọc DE08/ D1146 Cos0 - CS IVECO | C86: 111 | D86: Bộ | F86: 50000 | G86: 60000 | H86: 70000
A87: HH079908 | B87: Căn dọc DE08/ D1146 Cos1 - CS IVECO | C87: 111 | D87: Bộ | F87: 50000 | G87: 60000 | H87: 70000
A88: HH079909 | B88: Căn dọc DE08/ D1146 Cos2 - CS IVECO | C88: 111 | D88: Bộ | F88: 50000 | G88: 60000 | H88: 70000
A89: HH079898 | B89: Căn dọc DE12/ D2366 Cos0 - CS IVECO | C89: 123 | D89: Bộ
A90: HH079899 | B90: Căn dọc DE12/ D2366 Cos1 - CS IVECO | C90: 123 | D90: Bộ
A91: HH079900 | B91: Căn dọc DE12/ D2366 Cos2 - CS IVECO | C91: 123 | D91: Bộ
A92: HH076169 | B92: Căn dọc DL06 Cos0 / 65.01150-6008S - Doosan | C92: 100 | D92: Bộ
A93: HH080340 | B93: Căn dọc DL06 Cos1 / 65.01150-6008S - Doosan | C93: 100 | D93: Bộ
A94: HH080348 | B94: Căn dọc DX12 - Cos0 - DOOSAN | C94: 123 | D94: Bộ
A95: HH073102 | B95: Căn dọc E120 Cos0 ĐL | D95: Bộ
A96: HH080554 | B96: Căn dọc ED33/ED30/FD6/FD35/FD33 Cos0 - TDC - T3023A | C96: 98/100/102.5 | D96: Bộ
A97: HH080555 | B97: Căn dọc ED33/ED30/FD6/FD35/FD33 Cos1 - TDC - T3023A | C97: 98/100/102.5 | D97: Bộ
A98: HH072428 | B98: Căn dọc ED33/ED30/FD6/FD35/FD33 Cos2 | C98: 98/100/102.5 | D98: Bộ
A99: HH071299 | B99: Căn dọc EF750/F17C/F17E Cos2 | C99: 137/139 | D99: Bộ
A100: HH079761 | B100: Căn dọc EM100 cos1 | C100: 124 | D100: Bộ
...

Sheet 📚 CHÚ GIẢI
B1: 📚 CHÚ GIẢI KÝ HIỆU
B2: Ký hiệu | C2: Ý nghĩa
B3: (A) | C3: Có kiềng gang
B4: (A+0) | C4: Lỗ làm mát chân không
B5: F/F | C5: Xy lanh đã xoáy
B6: S/F | C6: Xy lanh chưa xoáy (luôn có thông số)
B7: Kiếng | C7: Xy lanh gốc hãng → séc măng KHÔNG mạ
B8: Gang | C8: Xy lanh thay thế → séc măng CÓ mạ
B9: STD | C9: Cốt 0 (zin)
B10: 0.25 | C10: Cốt 1
B11: 0.50 | C11: Cốt 2
B12: 0.75 | C12: Cốt 3
B13: 1.0 | C13: Cốt 4
B14: Mã HH | C14: Mã hàng hóa trong kho
B16: 🏷️ THƯƠNG HIỆU — XUẤT XỨ
B17: Thương hiệu | C17: Xuất xứ
B18: NPR | C18: Nhật Bản
B19: RIK (Rikken) | C19: Nhật Bản
B20: TP | C20: Nhật Bản
B21: IKAZU | C21: Trung Quốc xuất Châu Âu
B22: IZUMI | C22: Trung Quốc xuất Châu Âu
B23: HENWEIT | C23: Trung Quốc xuất Châu Âu
B24: NSP | C24: Châu Âu
B25: MAHLE | C25: Đức
B26: PROXMANN | C26: (bổ sung)
B28: TIẾNG ANH | C28: TIẾNG VIỆT
B29: ★ Từ điển thuật ngữ kỹ thuật động cơ diesel | A → Z
B30: A — (3 thuật ngữ)
B31: Air Cleaner Assy | C31: Bầu Lọc Gió
B32: Altennator | C32: Máy Phát
B33: Arm Rocker | C33: Nguyên Giàn Cò
B34: B — (3 thuật ngữ)
B35: B | C35: Balance Shaft Bushing Set
B36: Belt | C36: Cây Cu Roa
B37: Bolt | C37: Bulon Nắp Quy Lát
B38: C — (17 thuật ngữ)
B39: C | C39: Camshaft Bearing Set
B40: Camshaft | C40: Trục Cam
B41: Camshaft Drive Belt | C41: Dây Cu Roa Trục Cam
B42: Camshaft Sprocket | C42: Nhông Cam
B43: Clamp Turb End | C43: Đai Sò Turbo
B44: Compressor Wheels | C44: Cánh Gió Turbo
B45: Connecting Rod | C45: Tay Biên
B46: Cooling Fan | C46: Cánh Quạt
B47: Coupling Clutch Plate | C47: Lá Côn
B48: Crankshaft | C48: Trục Cơ
B49: Crankshaft Front Oil Seal | C49: Phớt Đầu Trục Cơ
B50: Crankshaft Position Sensor | C50: Cảm Biến Trục Cơ
... B55: Cylinder Liner | C55: Xy Lanh
B56: D — (1 thuật ngữ)
B57: Damber | C57: Buly Đầu Cốt
B58: E — (4 thuật ngữ)
B59: Engine | C59: Động Cơ
B60: Engine Valve | C60: Su Pap
B61: Excavator Oil Cooler | C61: Két Nhớt
B62: Exhaust Manifold | C62: Cổ Bô Xả
B63: F — (7 thuật ngữ)
B64: Flywheel | C64: Vành Răng Bánh Đà ( Vòng Cô Rôn)
B65: Flywheel Housing | C65: Vỏ Bánh Đà ( Mặt Cọp )
B66: Fuel Injection | C66: Kim Phun, Béc Phun
B67: Fuel Injection Pump | C67: Con Heo
B68: Fuel Pipe | C68: Ông Dẫn Nhiên Liệu
B69: Fuel Pump | C69: Bơm Nhiên Liệu
B70: freeze plug | C70: Đồng Tiền
B71: H — (2 thuật ngữ)
B72: Housing Turbine | C72: Sò Gang Turbo
B73: Hydraulic Pump | C73: Bơm Tổng Thủy Lực
B74: I — (1 thuật ngữ)
B75: Idler Wheel For Tensioning Belt | C75: Con Độn Tăng Dây Cu Roa
B76: K — (1 thuật ngữ)
B77: Ký Hiệu | C77: Loại
B78: L — (1 thuật ngữ)
B79: Liner O-rings | C79: Thun Xy Lanh
B80: M — (6 thuật ngữ)
B81: M | C81: Main Bearing Set
B82: Main Bearing | C82: Miểng Baze
B83: Main Pump | C83: Bơm Tổng Thủy Lực
B84: Manifold Gasket | C84: Ron Cổ Bô Lửa
B85: Mp | C85: Main Bearing Set (pair)
B86: Muffler | C86: Bầu Giảm Thanh
B87: N — (2 thuật ngữ)
B88: Nozzle Holer | C88: Sam Béc
B89: Nozzle Ring | C89: Cánh Ré Turbo
B90: O — (7 thuật ngữ)
B91: Oil Cooler Core | C91: Ruột Sinh Hàn
B92: Oil Cooler Cover | C92: Nắp Sinh Hàn Nhớt
B93: Oil Level Stick | C93: Que Thăm Nhớt
B94: Oil Pan | C94: Đáy Cat Te
B95: Oil Pan Gaskets | C95: Ron Cạt Te
B96: Oil Piston Cooling Nozzle | C96: Cò Phun Nhớt ( Vòi Làm Mát Piston)
B97: Oil Pump | C97: Bơm Nhớt
B98: P — (4 thuật ngữ)
B99: P | C99: Piston Pin Bushing Set
B100: Pc | C100: Pump Drive Shaft Bearing Set
B101: Piston Pin Bushing Set | C101: Bạc Thau
B102: Pushrod | C102: Đũa Su Pap
B103: R — (7 thuật ngữ)
B104: R | C104: Connecting Rod Bearing Set
B105: Rocker Arm | C105: Cò Mổ Su Pap
B106: Rocker Arm Shaft | C106: Dàn Cò Mổ Su Pap
...

Sheet _LOOKUP_VND
A1: Số | B1: Chữ_Giữa | C1: Chữ_Đầu
A2: 0
A3: 1 | B3: không trăm lẻ một | C3: một
A4: 2 | B4: không trăm lẻ hai | C4: hai
A5: 3 | B5: không trăm lẻ ba | C5: ba
A6: 4 | B6: không trăm lẻ bốn | C6: bốn
A7: 5 | B7: không trăm lẻ năm | C7: năm
A8: 6 | B8: không trăm lẻ sáu | C8: sáu
A9: 7 | B9: không trăm lẻ bảy | C9: bảy
A10: 8 | B10: không trăm lẻ tám | C10: tám
A11: 9 | B11: không trăm lẻ chín | C11: chín
A12: 10 | B12: không trăm mười | C12: mười
A13: 11 | B13: không trăm mười một | C13: mười một
A14: 12 | B14: không trăm mười hai | C14: mười hai
... A1001: 999 | B1001: chín trăm chín mươi chín | C1001: chín trăm chín mươi chín

Sheet 🔩 PISTON
A1: 🔩 PISTON —
A2: 🏷️ Mã HH | B2: 🏭 Hãng | C2: ⚙️ Mã ĐC | D2: 📐 ĐK | E2: 🔖 Ký hiệu | F2: Buồng nổ | G2: Ắc | H2: Ắc đỉnh | I2: Tổng dài | J2: Ring 1-5 | K2: 🏷️ Thương hiệu | L2: 📦 ĐVT | M2: 💰 Vốn | N2: 🟢 VIP | O2: 🟡 Ưu đãi | P2: 🔵 Đại lý | Q2: 🟣 Gara | R2: 📦 Tồn | S2: 🔧 PARNO | T2: 📝 Ghi chú | U2: _KEY
B3: ◆ HINO (69 sản phẩm) | U3: =IF($C3="","",B3&" "&C3&" · ĐK"&D3&IF(E3=""," "," "&E3)&IF(K3=""," "," - "&K3))
A4: HH0600 | B4: HINO | C4: DM100 | D4: 90 | E4: (A) | F4: Buồng Nổ hình đầu trâu có 2 dấu supap | G4: 29x77 | H4: 38.5 | I4: 104 | J4: 2.5-2.5-2.5-4-4 | K4: IZUMI | L4: Bộ 6 | R4: 🟢 CÓ | U4: =IF($C4="","",B4&" "&C4&" · ĐK"&D4&IF(E4=""," "," "&E4)&IF(K4=""," "," - "&K4))
A5: HH082015 | B5: HINO | C5: DM100 | D5: 90 | E5: (A) | F5: Buồng Nổ hình đầu trâu có 2 dấu supap | G5: 29x77 | H5: 38.5 | I5: 104 | J5: 2.5-2.5-2.5-4-4 | K5: IKAZU | L5: Bộ 6 | N5: 2100000 | O5: 2250000 | P5: 2400000 | R5: 🟢 CÓ | U5: =IF($C5="","",B5&" "&C5&" · ĐK"&D5&IF(E5=""," "," "&E5)&IF(K5=""," "," - "&K5))
A6: HH083874 | B6: HINO | C6: EC100 | D6: 97 | E6: 0 kiềng gang | F6: Buồng Nổ hình đầu trâu có 2 dấu supap | G6: 31.5x81.5 | H6: 42 | I6: 112 | J6: 2.5-2.5-2.5-4-4 | K6: IKAZU | L6: Bộ 6 | N6: 2250000 | O6: 2400000 | P6: 2550000 | R6: 🟢 CÓ | U6: =IF($C6="","",B6&" "&C6&" · ĐK"&D6&IF(E6=""," "," "&E6)&IF(K6=""," "," - "&K6))
B7: HINO | C7: N04CT | D7: 104 | E7: (A)+(O) | F7: Buồng Nổ tròn dù 59 | G7: 37x85 | I7: 100 | J7: 2.5-2-4 | L7: Bộ 4 | R7: 🟢 CÓ | S7: 13216-E0010 | U7: =IF($C7="","",B7&" "&C7&" · ĐK"&D7&IF(E7=""," "," "&E7)&IF(K7=""," "," - "&K7))
B8: HINO | C8: N04CT-OG | D8: 104 | E8: (A)+(O) | F8: Buồng Nổ 2 tầng ,nhớt 4 | J8: 2.5-2-4
A9: HH070788 | B9: HINO | C9: W04C-T/W06C-T | D9: 104 | E9: (A) | F9: Buồng Nổ tròn 57 nhọn thấp có 2 dấu supap | G9: 37x85 | H9: 44 | I9: 109 | J9: 2.8K-2.5-5 | K9: IZUMI | L9: Bộ 4 | R9: 🟢 CÓ | U9: =IF($C9="","",B9&" "&C9&" · ĐK"&D9&IF(E9=""," "," "&E9)&IF(K9=""," "," - "&K9))
A10: HH00270 | B10: HINO | C10: W04D | D10: 104 | E10: (A) | F10: Buồng Nổ tròn 51 bằng khuyết có 2 dấu supap | G10: 35x85 | H10: 45 | I10: 108.5 | J10: 2.5-2-5 | K10: IZUMI | L10: Bộ 4 | R10: 🟢 CÓ | U10: =IF($C10="","",B10&" "&C10&" · ĐK"&D10&IF(E10=""," "," "&E10)&IF(K10=""," "," - "&K10))
A11: HH082312 | B11: HINO | C11: W04D-T | D11: 104 | E11: (A) | F11: Buồng Nổ tròn 57 nhọn cao có 2 dấu supap | G11: 37x85 | H11: 41.5 | I11: 106 | J11: 2.8K-2-4 | K11: IKAZU | L11: Bộ 4 | N11: 1450000 | O11: 1550000 | P11: 1650000 | R11: 🟢 CÓ | S11: 13216-E0020 | U11: =IF($C11="","",B11&" "&C11&" · ĐK"&D11&IF(E11=""," "," "&E11)&IF(K11=""," "," - "&K11))
B12: HINO | C12: W04DT-NEW | D12: 104 | E12: (A) | F12: Buồng Nổ tròn 51 bằng khuyết có 2 dấu supap | G12: 37x85 | H12: 41.5 | I12: 106 | J12: 2.5-2-4 | L12: Bộ 4 | R12: 🟢 CÓ | U12: =IF($C12="","",B12&" "&C12&" · ĐK"&D12&IF(E12=""," "," "&E12)&IF(K12=""," "," - "&K12))
B13: HINO | C13: W04E | D13: 104 | E13: (A) | F13: Buồng Nổ tròn 51 bằng khuyết có 2 dấu supap | G13: 35x85 | H13: 43 | I13: 106 | J13: 2.5-2-5 | L13: Bộ 4 | R13: 🟢 CÓ | U13: =IF($C13="","",B13&" "&C13&" · ĐK"&D13&IF(E13=""," "," "&E13)&IF(K13=""," "," - "&K13))
A14: HH082313 | B14: HINO | C14: W06D/W04D | D14: 104 | E14: (A) | F14: Buồng Nổ tròn 51 bằng khuyết có 2 dấu supap,ắc đỉnh 45 | G14: 35x85 | H14: 45 | I14: 108.5 | J14: 2.5-2-5 | K14: IKAZU | L14: Bộ 6 | N14: 2100000 | O14: 2200000 | P14: 2350000 | R14: 🟢 CÓ | U14: =IF($C14="","",B14&" "&C14&" · ĐK"&D14&IF(E14=""," "," "&E14)&IF(K14=""," "," - "&K14))
A15: HH082006 | B15: HINO | C15: W06D/W04D | D15: 104 | E15: (A) | F15: Buồng Nổ tròn 51 bằng khuyết có 2 dấu supap,ắc đỉnh 43 | G15: 35x85 | H15: 43 | I15: 106 | J15: 2.5-2-5 | K15: IKAZU | L15: Bộ 6 | N15: 2170000 | O15: 2300000 | P15: 2460000 | R15: 🟢 CÓ | S15: 13216-1460 | U15: =IF($C15="","",B15&" "&C15&" · ĐK"&D15&IF(E15=""," "," "&E15)&IF(K15=""," "," - "&K15))
B16: HINO | C16: EH100 | D16: 105 | E16: 0 kiềng gang | F16: Buồng Nổ hình đầu trâu có 2 dấu supap | G16: 34x89.5 | H16: 42 | I16: 112 | J16: 2.5-2.5-2.5-4-4 | L16: Bộ 6 | R16: 🟢 CÓ | U16: =IF($C16="","",B16&" "&C16&" · ĐK"&D16&IF(E16=""," "," "&E16)&IF(K16=""," "," - "&K16))
B17: HINO | C17: H06B-T | D17: 105.8 | E17: (A)+(O) | F17: Buồng Nổ tròn 65 nhọn có 2 dấu supap | G17: 39x87 | H17: 50 | I17: 121.5 | J17: 2.8K-2.5-2.5-5 | L17: Bộ 6 | R17: 🟢 CÓ | U17: =IF($C17="","",B17&" "&C17&" · ĐK"&D17&IF(E17=""," "," "&E17)&IF(K17=""," "," - "&K17))
B18: HINO | C18: H06B-TI | D18: 105.8 | E18: (A)+(O) | F18: Buồng Nổ tròn 65 nhọn có 2 dấu supap | G18: 39x87 | H18: 50 | I18: 121.5 | J18: 2.8K-2.5-2.5-4 | L18: Bộ 6 | R18: 🟢 CÓ | U18: =IF($C18="","",B18&" "&C18&" · ĐK"&D18&IF(E18=""," "," "&E18)&IF(K18=""," "," - "&K18))
B19: HINO | C19: EH300 | D19: 108 | E19: 0 kiềng gang | F19: Buồng Nổ hình đầu trâu có 2 dấu supap | G19: 35x90 | H19: 42 | I19: 114 | J19: 3-2.5-5-4 | L19: Bộ 6 | R19: 🟢 CÓ | U19: =IF($C19="","",B19&" "&C19&" · ĐK"&D19&IF(E19=""," "," "&E19)&IF(K19=""," "," - "&K19))
A20: HH068738 | B20: HINO | C20: H06C | D20: 108 | E20: (A) | F20: buồng nổ tròn 54 nhọn có 2 dấu supap | G20: 39x90 | H20: 50 | I20: 121.5 | J20: 2.8K-2.5-2.5-5 | K20: IZUMI | L20: Bộ 6 | R20: 🟢 CÓ | S20: 13216-1540 | U20: =IF($C20="","",B20&" "&C20&" · ĐK"&D20&IF(E20=""," "," "&E20)&IF(K20=""," "," - "&K20))
A21: HH076960 | B21: HINO | C21: H06C-T | D21: 108 | E21: (A)+(O) | F21: Buồng Nổ tròn 55 hơi nhọn | G21: 39x90 | H21: 50 | I21: 121.5 | J21: 2.8K-2.5-2.5-5 | K21: IZUMI | L21: Bộ 6 | R21: 🟢 CÓ | U21: =IF($C21="","",B21&" "&C21&" · ĐK"&D21&IF(E21=""," "," "&E21)&IF(K21=""," "," - "&K21))
A22: HH071862 | B22: HINO | C22: H06C-TA | D22: 108 | E22: (A) | F22: buồng nổ tròn 60 nhọn có 2 dấu supap | G22: 39x90 | H22: 50 | I22: 121.5 | J22: 2.8K-2.5-2.5-5 | K22: IZUMI | L22: Bộ 6 | R22: 🟢 CÓ | U22: =IF($C22="","",B22&" "&C22&" · ĐK"&D22&IF(E22=""," "," "&E22)&IF(K22=""," "," - "&K22))
A23: HH0279 | B23: HINO | C23: DS50 | D23: 110 | E23: 0 kiềng gang | F23: Buồng Nổ hình đầu trâu, có 2 dấu supap | G23: 40x92 | H23: 58.5 | I23: 145 | J23: 3-3-3-4.5-4.5 | K23: IZUMI | L23: Cái | R23: 🟢 CÓ | U23: =IF($C23="","",B23&" "&C23&" · ĐK"&D23&IF(E23=""," "," "&E23)&IF(K23=""," "," - "&K23))
A24: HH070478 | B24: HINO | C24: EH700 | D24: 110 | E24: (A) | F24: Buồng Nổ tròn 55 nhọn có 2 dấu supap | G24: 39x90 | H24: 50 | I24: 121.5 | J24: 3-2.5-2.5-5 | K24: IZUMI | L24: Bộ 6 | N24: 2300000 | O24: 2450000 | P24: 2600000 | R24: 🟢 CÓ | S24: 13216-1181 | U24: =IF($C24="","",B24&" "&C24&" · ĐK"&D24&IF(E24=""," "," "&E24)&IF(K24=""," "," - "&K24))
A25: HH070477 | B25: HINO | C25: EH700-T | D25: 110 | E25: (A) | F25: Buồng Nổ tròn 57 nhọn có 2 dấu supap, có cò nhớt | G25: 39x90 | H25: 50 | I25: 121.5 | J25: 3-2.5-2.5-5 | K25: IZUMI | L25: Bộ 6 | R25: 🟢 CÓ | U25: =IF($C25="","",B25&" "&C25&" · ĐK"&D25&IF(E25=""," "," "&E25)&IF(K25=""," "," - "&K25))
A26: HH070475 | B26: HINO | C26: H07C (NEW) | D26: 110 | E26: (A) | F26: Buồng Nổ tròn 53, 5 bằng, có cò nhớt | G26: 39x90 | H26: 50 | I26: 121.5 | J26: 3-2.5-2.5-5 | K26: IZUMI | L26: Bộ 6 | N26: 2100000 | O26: 2250000 | P26: 2400000 | R26: 🟢 CÓ | U26: =IF($C26="","",B26&" "&C26&" · ĐK"&D26&IF(E26=""," "," "&E26)&IF(K26=""," "," - "&K26))
A27: HH081682 | B27: HINO | C27: H07C (OLD) | D27: 110 | E27: (A) | F27: Buồng Nổ tròn 51 nhọn có 2 dấu supap, có cò nhớt | G27: 39x90 | H27: 50 | I27: 121.5 | J27: 3-2.5-2.5-5 | K27: IKAZU | L27: Bộ 6 | N27: 2700000 | O27: 2900000 | P27: 3100000 | R27: 🟢 CÓ | S27: 13211-2580 | U27: =IF($C27="","",B27&" "&C27&" · ĐK"&D27&IF(E27=""," "," "&E27)&IF(K27=""," "," - "&K27))
A28: HH070476 | B28: HINO | C28: H07C (OLD) | D28: 110 | E28: (A) | F28: Buồng Nổ tròn 51 nhọn có 2 dấu supap, có cò nhớt | G28: 39x90 | H28: 50 | I28: 121.5 | J28: 3-2.5-2.5-5 | K28: IZUMI | L28: Bộ 6 | R28: 🟢 CÓ | S28: 13211-2580 | U28: =IF($C28="","",B28&" "&C28&" · ĐK"&D28&IF(E28=""," "," "&E28)&IF(K28=""," "," - "&K28))
A29: HH070808 | B29: HINO | C29: H07C-2 | D29: 110 | E29: (A) | F29: Buồng Nổ tròn 53 dù có 2 dấu supap, có cò nhớt, dù 31 | G29: 39x90 | H29: 50 | I29: 121.5 | J29: 3-2.5-2.5-5 | K29: IZUMI | L29: Bộ 6 | N29: 2530000 | O29: 2670000 | P29: 2800000 | R29: 🟢 CÓ | U29: =IF($C29="","",B29&" "&C29&" · ĐK"&D29&IF(E29=""," "," "&E29)&IF(K29=""," "," - "&K29))
A30: HH082008 | B30: HINO | C30: H07C-T2 | D30: 110 | E30: (A)+(O) | F30: Buồng Nổ tròn 58 nhọn, có lỗ nhớt | G30: 39x90 | H30: 50 | I30: 121.5 | J30: 2.8K-2-2-4 | K30: IKAZU | L30: Bộ 6 | N30: 3050000 | O30: 3250000 | P30: 3450000 | R30: 🟢 CÓ | S30: 13216-2062 | U30: =IF($C30="","",B30&" "&C30&" · ĐK"&D30&IF(E30=""," "," "&E30)&IF(K30=""," "," - "&K30))
A31: HH00115 | B31: HINO | C31: H07C-T2 | D31: 110 | E31: (A)+(O) | F31: Buồng Nổ tròn 58 nhọn, có lỗ nhớt | G31: 39x90 | H31: 50 | I31: 121.5 | J31: 2.8K-2-2-4 | K31: IZUMI | L31: Bộ 6 | R31: 🟢 CÓ | S31: 13216-2740) | U31: =IF($C31="","",B31&" "&C31&" · ĐK"&D31&IF(E31=""," "," "&E31)&IF(K31=""," "," - "&K31))
B32: HINO | C32: H07D | D32: 110 | E32: (A) | F32: Buồng Nổ 58 bằng | G32: 37x85 | H32: 38.5 | I32: 100 | J32: 3-2-4 | L32: Bộ 6 | R32: 🟢 CÓ | S32: 13216-2260 | U32: =IF($C32="","",B32&" "&C32&" · ĐK"&D32&IF(E32=""," "," "&E32)&IF(K32=""," "," - "&K32))
A33: HH070473 | B33: HINO | C33: H07D-NEW | D33: 110 | E33: (A) | F33: Buồng Nổ tròn 57 nhọn | G33: 37x85 | H33: 38.5 | I33: 100 | J33: 3-2-4 | K33: IZUMI | L33: Bộ 6 | N33: 2250000 | O33: 2400000 | P33: 2600000 | R33: 🟢 CÓ | S33: 13216-1980 | U33: =IF($C33="","",B33&" "&C33&" · ĐK"&D33&IF(E33=""," "," "&E33)&IF(K33=""," "," - "&K33))
A34: HH075633 | B34: HINO | C34: J05E/J08E | D34: 112 | E34: (A)+(O) | F34: Buồng Nổ tròn khuyết 63, 5 hơi nhọn | G34: 37x84.5 | H34: 38.5 | I34: 100 | J34: 2.5-2-4 | K34: MAHLE | L34: Bộ 4 | N34: 6000000 | O34: 6500000 | P34: 7000000 | R34: 🟢 CÓ | S34: S130B-E0390 | U34: =IF($C34="","",B34&" "&C34&" · ĐK"&D34&IF(E34=""," "," "&E34)&IF(K34=""," "," - "&K34))
A35: HH071883 | B35: HINO | C35: J05E/J08E | D35: 112 | E35: (A)+(O) | F35: Buồng Nổ tròn khuyết 63, 5 hơi nhọn | G35: 37x84.5 | H35: 38.5 | I35: 100 | J35: 2.5-2-4 | K35: NSP | L35: Bộ 4 | N35: 7500000 | O35: 7900000 | P35: 8200000 | R35: 🟢 CÓ | U35: =IF($C35="","",B35&" "&C35&" · ĐK"&D35&IF(E35=""," "," "&E35)&IF(K35=""," "," - "&K35))
A36: HH081163 | B36: HINO | C36: J05E/J08E | D36: 112 | E36: (A)+(O) | F36: Buồng Nổ tròn khuyết 63, 5 hơi nhọn | G36: 37x84.5 | H36: 38.5 | I36: 100 | J36: 2.5-2-4 | K36: IKAZU | L36: Bộ 4 | N36: 4550000 | O36: 4800000 | P36: 5150000 | R36: 🟢 CÓ | S36: S130A-E0100 | U36: =IF($C36="","",B36&" "&C36&" · ĐK"&D36&IF(E36=""," "," "&E36)&IF(K36=""," "," - "&K36))
A37: HH079464 | B37: HINO | C37: J05ETA (gang) | D37: 112 | F37: Buồng Nổ tròn nhọn, ko có dấu supap | J37: 3K-2-4 | K37: IKAZU | L37: Bộ 4 | N37: 5600000 | O37: 5900000 | P37: 6200000 | R37: 🟢 CÓ | S37: 13201-E0361 | U37: =IF($C37="","",B37&" "&C37&" · ĐK"&D37&IF(E37=""," "," "&E37)&IF(K37=""," "," - "&K37))
A38: HH083527 | B38: HINO | C38: J05ETA (gang) | D38: 112 | F38: Buồng Nổ tròn nhọn 2 tầng, ko có dấu supap | J38: 3K-2-4 | K38: IKAZU | L38: Bộ 4 | N38: 5500000 | O38: 5900000 | P38: 6300000 | R38: 🟢 CÓ | S38: S130A-E0281 | U38: =IF($C38="","",B38&" "&C38&" · ĐK"&D38&IF(E38=""," "," "&E38)&IF(K38=""," "," - "&K38))
B39: HINO | C39: J07E | D39: 112 | E39: (A)+(O) | F39: Buồng Nổ tròn khuyết 63, 5 hơi nhọn | G39: 37x84.5 | H39: 38.5 | I39: 100 | J39: 2.5-2-4 | L39: Cái | R39: 🟢 CÓ | U39: =IF($C39="","",B39&" "&C39&" · ĐK"&D39&IF(E39=""," "," "&E39)&IF(K39=""," "," - "&K39))
B40: HINO | C40: J08E | D40: 112 | E40: (A)+(O) | F40: Buồng Nổ tròn khuyết 63, 5 hơi nhọn | G40: 37x84.5 | H40: 38.5 | I40: 100 | J40: 2.5-2-4 | K40: MAHLE | L40: Bộ 6 | R40: 🟢 CÓ | U40: =IF($C40="","",B40&" "&C40&" · ĐK"&D40&IF(E40=""," "," "&E40)&IF(K40=""," "," - "&K40))
B41: HINO | C41: J07C | D41: 114 | E41: (A) | F41: Buồng Nổ tròn khuyết 56 hơi nhọn | G41: 37x84.5 | H41: 38.5 | I41: 100 | J41: 2.5-2-4 | L41: Cái | R41: 🟢 CÓ | U41: =IF($C41="","",B41&" "&C41&" · ĐK"&D41&IF(E41=""," "," "&E41)&IF(K41=""," "," - "&K41))
A42: HH082318 | B42: HINO | C42: S05D ( J08C / J05C ) | D42: 114 | F42: Buồng Nổ tròn nhọn nổ 56 , cò nhớt, | J42: 2.5-2-4 | K42: IKAZU | N42: 2500000 | O42: 2650000 | P42: 2800000 | S42: 13216-2973
A43: HH070479 | B43: HINO | C43: J08C | D43: 114 | E43: (A) | F43: Buồng Nổ tròn 56 bằng, bạc đầu 3 ly | G43: 37x84.5 | H43: 38.5 | I43: 100 | J43: 3-2-4 | K43: IZUMI | L43: Cái | N43: 2500000 | O43: 2650000 | P43: 2800000 | R43: 🟢 CÓ | S43: 13216-2631 | U43: =IF($C43="","",B43&" "&C43&" · ĐK"&D43&IF(E43=""," "," "&E43)&IF(K43=""," "," - "&K43))
A44: HH073911 | B44: HINO | C44: J08C | D44: 114 | E44: (A) | F44: Buồng Nổ tròn 56 bằng, bạc đầu 2, 5 | G44: 37x84.5 | H44: 38.5 | I44: 100 | J44: 2.5-2-4 | K44: IZUMI | L44: Bộ 6 | R44: 🟢 CÓ | U44: =IF($C44="","",B44&" "&C44&" · ĐK"&D44&IF(E44=""," "," "&E44)&IF(K44=""," "," - "&K44))
A45: HH082716 | B45: HINO | C45: J08C | D45: 114 | E45: (A) | F45: Buồng Nổ tròn 56 bằng, bạc đầu 2, 5 | G45: 37x84.5 | H45: 38.5 | I45: 100 | J45: 2.5-2-4 | K45: IKAZU | L45: Bộ 6 | N45: 2500000 | O45: 2650000 | P45: 2800000 | R45: 🟢 CÓ | U45: =IF($C45="","",B45&" "&C45&" · ĐK"&D45&IF(E45=""," "," "&E45)&IF(K45=""," "," - "&K45))
A46: HH072017 | B46: HINO | C46: J08C-2 | D46: 114 | E46: (A) | F46: Buồng Nổ tròn khuyết 56 hơi nhọn | G46: 37x84.5 | H46: 38.5 | I46: 100 | J46: 2.5-2-4 | K46: IZUMI | L46: Bộ 6 | P46: 480000 | R46: 🟢 CÓ | U46: =IF($C46="","",B46&" "&C46&" · ĐK"&D46&IF(E46=""," "," "&E46)&IF(K46=""," "," - "&K46))
B47: HINO | C47: J08C-NEW | D47: 114 | E47: (A) | F47: Buồng Nổ tròn khuyết 53 hơi nhọn | G47: 37x84.5 | H47: 42 | I47: 103.5 | J47: 2.5-2-4 | L47: Bộ 6 | R47: 🟢 CÓ | U47: =IF($C47="","",B47&" "&C47&" · ĐK"&D47&IF(E47=""," "," "&E47)&IF(K47=""," "," - "&K47))
A48: HH082321 | B48: HINO | C48: J08C-T/J05C-T | D48: 114 | E48: (A)+(O) | F48: Buồng Nổ tròn khuyết 65 hơi nhọn | G48: 37x84.5 | H48: 38.5 | I48: 100 | J48: 2.5-2-4 | K48: IKAZU | L48: Bộ 6 | N48: 4050000 | O48: 4300000 | P48: 4550000 | R48: 🟢 CÓ | S48: S130AE0080 | U48: =IF($C48="","",B48&" "&C48&" · ĐK"&D48&IF(E48=""," "," "&E48)&IF(K48=""," "," - "&K48))
B49: HINO | C49: EB100 | D49: 115 | E49: 0 kiềng gang | F49: Buồng Nổ hình đầu trâu, có 2 dấu supap | G49: 43x89 | H49: 65 | I49: 153 | J49: 3.5-3-3-5-5 | L49: Bộ 6 | R49: 🟢 CÓ | U49: =IF($C49="","",B49&" "&C49&" · ĐK"&D49&IF(E49=""," "," "&E49)&IF(K49=""," "," - "&K49))
A50: HH00267 | B50: HINO | C50: EL100 | D50: 116 | E50: (A) | F50: Buồng Nổ tròn 57 nhọn có 2 dấu supap | G50: 40x93 | H50: 58 | I50: 130.5 | J50: 3-2.5-2.5-5 | K50: IKAZU | L50: Bộ 6 | N50: 3270000 | O50: 3470000 | P50: 3700000 | R50: 🟢 CÓ | S50: 13211-1563 | U50: =IF($C50="","",B50&" "&C50&" · ĐK"&D50&IF(E50=""," "," "&E50)&IF(K50=""," "," - "&K50))
A51: HH070809 | B51: HINO | C51: EL100 | D51: 116 | E51: (A) | F51: Buồng Nổ tròn 57 nhọn có 2 dấu supap | G51: 40x93 | H51: 58 | I51: 130.5 | J51: 3-2.5-2.5-5 | K51: IZUMI | L51: Bộ 6 | N51: 2950000 | O51: 3100000 | P51: 3300000 | R51: 🟢 CÓ | S51: 13211-1563 | U51: =IF($C51="","",B51&" "&C51&" · ĐK"&D51&IF(E51=""," "," "&E51)&IF(K51=""," "," - "&K51))
B52: HINO | C52: P09B-TI | D52: 117.8 | E52: (A)+(O) | F52: Buồng Nổ tròn 67 nhọn, có 4 dấu supap | G52: 47x96.5 | H52: 61 | I52: 145 | J52: 3.3K-2.8K-2.5-5 | L52: Cái | R52: 🟢 CÓ | U52: =IF($C52="","",B52&" "&C52&" · ĐK"&D52&IF(E52=""," "," "&E52)&IF(K52=""," "," - "&K52))
B53: HINO | C53: DK10 | D53: 120 | E53: 0 kiềng gang | F53: Buồng Nổ hình đầu trâu, có 2 dấu supap | G53: 48x100 | H53: 72 | I53: 164 | J53: 3.5-3.5-3.5-5-5 | L53: Bộ 6 | R53: 🟢 CÓ | U53: =IF($C53="","",B53&" "&C53&" · ĐK"&D53&IF(E53=""," "," "&E53)&IF(K53=""," "," - "&K53))
B54: HINO | C54: EB300 | D54: 120 | E54: (A) | F54: Buồng Nổ hình đầu trâu, có 2 dấu supap | G54: 45x100 | H54: 64 | I54: 155.5 | J54: 3.5-3.5-3.5-6 | L54: Bộ 6 | R54: 🟢 CÓ | U54: =IF($C54="","",B54&" "&C54&" · ĐK"&D54&IF(E54=""," "," "&E54)&IF(K54=""," "," - "&K54))
A55: HH083279 | B55: HINO | C55: EP100T | D55: 120 | E55: (A)+(O) | F55: Buồng Nổ tròn 67 nhọn, có 2 dấu supap,cò nhớt | G55: 47x99 | H55: 62 | I55: 145 | J55: 3.3K-2.8K-2.5-5 | K55: IKAZU | L55: Cái | N55: 4550000 | O55: 4800000 | P55: 5250000 | R55: 🟢 CÓ | S55: 13216-1450C | U55: =IF($C55="","",B55&" "&C55&" · ĐK"&D55&IF(E55=""," "," "&E55)&IF(K55=""," "," - "&K55))
A56: HH070480 | B56: HINO | C56: P09C | D56: 120 | E56: (A)+(O) | F56: Buồng Nổ tròn 70 nhọn, có 4 dấu supap | G56: 47x99 | I56: 145 | J56: 3.3K-2.8K-2.5-5 | K56: IZUMI | L56: Cái | R56: 🟢 CÓ | U56: =IF($C56="","",B56&" "&C56&" · ĐK"&D56&IF(E56=""," "," "&E56)&IF(K56=""," "," - "&K56))
A57: HH083163 | B57: HINO | C57: P11C-NEW | D57: 122 | E57: gang | F57: Buồng Nổ tròn 75 nhọn, có 4 dấu supap má ắc lủng | G57: 47x89 | H57: 40 | I57: 96 | J57: 3.3K-2.3K-2-4 | K57: IKAZU | L57: Bộ 6 | N57: 6300000 | O57: 6700000 | P57: 6900000 | R57: 🟢 CÓ | U57: =IF($C57="","",B57&" "&C57&" · ĐK"&D57&IF(E57=""," "," "&E57)&IF(K57=""," "," - "&K57))
A58: HH070481 | B58: HINO | C58: P11C-NEW | D58: 122 | E58: gang | F58: Buồng Nổ tròn 75 nhọn, có 4 dấu supap má ắc lủng | G58: 47x89 | H58: 40 | I58: 96 | J58: 3.3K-2.3K-2-4 | K58: IZUMI | L58: Bộ 6 | R58: 🟢 CÓ | U58: =IF($C58="","",B58&" "&C58&" · ĐK"&D58&IF(E58=""," "," "&E58)&IF(K58=""," "," - "&K58))
A59: HH082549 | B59: HINO | C59: P11C-OLD | D59: 122 | E59: gang | F59: Buồng Nổ tròn 75 nhọn, có 4 dấu supap má ắc ko lủng | G59: 47x89 | H59: 40 | I59: 96 | J59: 3.3K-2.3K-2-4 | K59: IKAZU | L59: Bộ 6 | N59: 6000000 | O59: 6300000 | P59: 6600000 | R59: 🟢 CÓ | U59: =IF($C59="","",B59&" "&C59&" · ĐK"&D59&IF(E59=""," "," "&E59)&IF(K59=""," "," - "&K59))
A60: HH070753 | B60: HINO | C60: P11C-OLD | D60: 122 | E60: gang | F60: Buồng Nổ tròn 75 nhọn, có 4 dấu supap má ắc ko lủng | G60: 47x89 | H60: 40 | I60: 96 | J60: 3.3K-2.3K-2-4 | K60: IZUMI | L60: Bộ 6 | R60: 🟢 CÓ | U60: =IF($C60="","",B60&" "&C60&" · ĐK"&D60&IF(E60=""," "," "&E60)&IF(K60=""," "," - "&K60))
A61: HH070810 | B61: HINO | C61: EM100 | D61: 124 | E61: (A) | F61: Buồng Nổ tròn 63 nhọn, có 2 dấu supap | G61: 42x98 | H61: 59 | I61: 139.5 | J61: 2.8K-2.5-3-5 | K61: IZUMI | L61: Bộ 6 | R61: 🟢 CÓ | U61: =IF($C61="","",B61&" "&C61&" · ĐK"&D61&IF(E61=""," "," "&E61)&IF(K61=""," "," - "&K61))
A62: HH082011 | B62: HINO | C62: EM100 | D62: 124 | E62: (A) | F62: Buồng Nổ tròn 63 nhọn, có 2 dấu supap | G62: 42x98 | H62: 59 | I62: 139.5 | J62: 2.8K-2.5-3-5 | K62: IKAZU | L62: Bộ 6 | N62: 4200000 | O62: 4460000 | P62: 4760000 | R62: 🟢 CÓ | S62: 13216-1370 | U62: =IF($C62="","",B62&" "&C62&" · ĐK"&D62&IF(E62=""," "," "&E62)&IF(K62=""," "," - "&K62))
B63: HINO | C63: M10C | D63: 127 | E63: (A) | F63: Buồng Nổ tròn 65 bằng, có 2 dấu supap | G63: 47x99 | H63: 62 | I63: 144.5 | J63: 3.3K-3-3-5 | L63: Bộ 6 | R63: 🟢 CÓ | S63: 13216-2411 | U63: =IF($C63="","",B63&" "&C63&" · ĐK"&D63&IF(E63=""," "," "&E63)&IF(K63=""," "," - "&K63))
B64: HINO | C64: ED100 | D64: 128 | E64: (A) | F64: Buồng Nổ tròn 48 bằng | G64: 48x107 | H64: 75 | I64: 160 | J64: 3.5-3.5-3.5-6 | L64: Bộ 6 | R64: 🟢 CÓ | U64: =IF($C64="","",B64&" "&C64&" · ĐK"&D64&IF(E64=""," "," "&E64)&IF(K64=""," "," - "&K64))
A65: HH080375 | B65: HINO | C65: K13C-12V | D65: 135 | E65: (A)+(O) | F65: Buồng Nổ 80, 5 nhọn, có 2 dấu supap | G65: 50x110 | H65: 65.3 | I65: 145 | J65: 3.3K-3.5-3.5-5 | K65: IKAZU | L65: Bộ 6 | N65: 5500000 | O65: 5800000 | P65: 6200000 | R65: 🟢 CÓ | S65: 13216-2140 | U65: =IF($C65="","",B65&" "&C65&" · ĐK"&D65&IF(E65=""," "," "&E65)&IF(K65=""," "," - "&K65))
A66: HH070482 | B66: HINO | C66: K13C-12V | D66: 135 | E66: (A)+(O) | F66: Buồng Nổ 80, 5 nhọn, có 2 dấu supap | G66: 50x110 | H66: 65.3 | I66: 145 | J66: 3.3K-3.5-3.5-5 | K66: IZUMI | L66: Bộ 6 | R66: 🟢 CÓ | S66: 13216-2140 | U66: =IF($C66="","",B66&" "&C66&" · ĐK"&D66&IF(E66=""," "," "&E66)&IF(K66=""," "," - "&K66))
B67: HINO | C67: K13C-24V | D67: 135 | E67: (A)+(O) | F67: Buồng Nổ tròn 84 nhọn có 4 dấu supap | G67: 50x110 | H67: 65.3 | I67: 145 | J67: 3.3K-3.5-3.5-5 | L67: Bộ 6 | R67: 🟢 CÓ | S67: 13211-3260 | U67: =IF($C67="","",B67&" "&C67&" · ĐK"&D67&IF(E67=""," "," "&E67)&IF(K67=""," "," - "&K67))
A68: HH073127 | B68: HINO | C68: K13C-TE | D68: 135 | E68: (A)+(O) | F68: Buồng Nổ tròn 82 nhọn có 4 dấu supap | G68: 50x110 | H68: 65.3 | I68: 145 | J68: 3.3K-3.5-3.5-5 | K68: IKAZU | L68: Bộ 6 | N68: 5500000 | O68: 5800000 | P68: 6200000 | R68: 🟢 CÓ | S68: 13216-2330 | U68: =IF($C68="","",B68&" "&C68&" · ĐK"&D68&IF(E68=""," "," "&E68)&IF(K68=""," "," - "&K68))
B69: HINO | C69: E13C | D69: 137 | F69: Nổ tròn nhọn 4 dấu supap | G69: 55x100 | H69: 44 | I69: 110 | J69: 3.3k-2.8k-2.5-4 | L69: Bộ 6 | R69: 🟢 CÓ | U69: =IF($C69="","",B69&" "&C69&" · ĐK"&D69&IF(E69=""," "," "&E69)&IF(K69=""," "," - "&K69))
A70: HH081683 | B70: HINO | C70: EF750 | D70: 137 | E70: (A) | F70: Buồng Nổ tròn 73 nhọn, có 2 dấu supap | G70: 50x110 | H70: 65.3 | I70: 144.3 | J70: 3.3K-3.5-3.5-6 | K70: IKAZU | L70: Bộ 8 | N70: 5800000 | O70: 6100000 | P70: 6400000 | R70: 🟢 CÓ | S70: 13216-1860 | T70: lưu ý xuất kèm ắc | U70: =IF($C70="","",B70&" "&C70&" · ĐK"&D70&IF(E70=""," "," "&E70)&IF(K70=""," "," - "&K70))
A71: HH070483 | B71: HINO | C71: EK100 | D71: 137 | E71: (A) | F71: Buồng Nổ tròn 73 nhọn, có 2 dấu supap,ko cò nhớt | G71: 50x110 | H71: 65.3 | I71: 145.5 | J71: 3.3K-3.5-3.5-6 | K71: IKAZU | L71: Bộ 6 | R71: 🟢 CÓ | T71: lưu ý xuất kèm ắc | U71: =IF($C71="","",B71&" "&C71&" · ĐK"&D71&IF(E71=""," "," "&E71)&IF(K71=""," "," - "&K71))
A72: HH070484 | B72: HINO | C72: EK100 | D72: 137 | E72: (A) | F72: Buồng Nổ tròn 73 nhọn, có 2 dấu supap,ko cò nhớt | G72: 50x110 | H72: 65.3 | I72: 145.5 | J72: 3.3K-3.5-3.5-6 | K72: IZUMI | L72: Bộ 6 | R72: 🟢 CÓ | T72: lưu ý xuất kèm ắc | U72: =IF($C72="","",B72&" "&C72&" · ĐK"&D72&IF(E72=""," "," "&E72)&IF(K72=""," "," - "&K72))
A73: HH070486 | B73: HINO | C73: EK100T | D73: 137 | E73: (A) | F73: Buồng Nổ tròn 74 nhọn, có 2 dấu supap, có cò nhớt | G73: 50x110 | H73: 65.3 | I73: 145.5 | J73: 3.3K-3.5-3.5-6 | K73: IZUMI | L73: Bộ 6 | N73: 3850000 | O73: 4050000 | P73: 4250000 | R73: 🟢 CÓ | T73: lưu ý xuất kèm ắc | U73: =IF($C73="","",B73&" "&C73&" · ĐK"&D73&IF(E73=""," "," "&E73)&IF(K73=""," "," - "&K73))
B74: HINO | C74: EK130T | D74: 137 | E74: (A) | F74: Buồng Nổ tròn 82 nhọn, có 2 dấu supap | G74: 50x110 | H74: 65.3 | I74: 145.5 | J74: 3.3k-3.5-3.5-6 | L74: Cái | R74: 🟢 CÓ | U74: =IF($C74="","",B74&" "&C74&" · ĐK"&D74&IF(E74=""," "," "&E74)&IF(K74=""," "," - "&K74))
A75: HH070485 | B75: HINO | C75: EK200 | D75: 137 | E75: (A) | F75: Buồng Nổ tròn 73 nhọn, có 2 dấu supap,có cò nhớt | G75: 50x110 | H75: 65.3 | I75: 145.5 | J75: 3.3K-3.5-3.5-6 | L75: Bộ 6 | R75: 🟢 CÓ | U75: =IF($C75="","",B75&" "&C75&" · ĐK"&D75&IF(E75=""," "," "&E75)&IF(K75=""," "," - "&K75))
A76: HH081684 | B76: HINO | C76: EK200 | D76: 137 | E76: (A) | F76: Buồng Nổ tròn 73 nhọn, có 2 dấu supap,có cò nhớt | G76: 50x110 | H76: 65.3 | I76: 145.5 | J76: 3.3K-3.5-3.5-6 | L76: Bộ 6 | N76: 4300000 | O76: 4600000 | P76: 4800000 | R76: 🟢 CÓ | U76: =IF($C76="","",B76&" "&C76&" · ĐK"&D76&IF(E76=""," "," "&E76)&IF(K76=""," "," - "&K76))
A77: HH070811 | B77: HINO | C77: F17D L+R | D77: 137 | E77: (A) | F77: Buồng Nổ tròn 73 nhọn, có 2 dấu supap,cò nhớt | G77: 50x110 | H77: 65.3 | I77: 144.3 | J77: 3.3K-3.5-3.5-5 | K77: IZUMI | L77: Bộ 8 | N77: 5650000 | O77: 6000000 | P77: 6400000 | R77: 🟢 CÓ | U77: =IF($C77="","",B77&" "&C77&" · ĐK"&D77&IF(E77=""," "," "&E77)&IF(K77=""," "," - "&K77))
B78: HINO | C78: F17D-NEW | D78: 137 | E78: (A) | F78: Buồng Nổ tròn 69 nhọn, có 2 dấu supap | G78: 50x110 | H78: 62 | I78: 142 | J78: 3.3K-3.5-3.5-4 | L78: Bộ 8 | R78: 🟢 CÓ | U78: =IF($C78="","",B78&" "&C78&" · ĐK"&D78&IF(E78=""," "," "&E78)&IF(K78=""," "," - "&K78))
B79: HINO | C79: F17D-T | D79: 137 | E79: (A) | F79: Buồng Nổ tròn 80 nhọn, có 4 dấu supap | G79: 50x110 | H79: 62 | I79: 142 | J79: 3.3K-3.5-3.5-4 | L79: Bộ 8 | R79: 🟢 CÓ | U79: =IF($C79="","",B79&" "&C79&" · ĐK"&D79&IF(E79=""," "," "&E79)&IF(K79=""," "," - "&K79))
B80: HINO | C80: K13D | D80: 137 | E80: (A) | F80: Buồng Nổ tròn 74 nhọn, có 2 dấu supap | G80: 50x110 | H80: 65.3 | I80: 144.3 | J80: 3.3K-3.5-3.5-5 | L80: Bộ 6 | R80: 🟢 CÓ | U80: =IF($C80="","",B80&" "&C80&" · ĐK"&D80&IF(E80=""," "," "&E80)&IF(K80=""," "," - "&K80))
A81: HH070487 | B81: HINO | C81: F17C-L+R | D81: 139 | E81: (A) | F81: Buồng Nổ tròn 74 nhọn, có 2 dấu supap,có cò nhớt | G81: 50x110 | H81: 65.3 | I81: 144.3 | J81: 3.3K-3.5-3.5-5 | K81: IZUMI | L81: Bộ 8 | N81: 5650000 | O81: 6000000 | P81: 6400000 | R81: 🟢 CÓ | U81: =IF($C81="","",B81&" "&C81&" · ĐK"&D81&IF(E81=""," "," "&E81)&IF(K81=""," "," - "&K81))
B82: HINO | C82: F17C-2 | D82: 139 | E82: (A) | F82: Buồng Nổ tròn 74 nhọn, có 2 dấu supap | G82: 50x110 | H82: 65.3 | I82: 144.3 | J82: 3.3K-3.5-3.5-4 | L82: Bộ 8 | R82: 🟢 CÓ | U82: =IF($C82="","",B82&" "&C82&" · ĐK"&D82&IF(E82=""," "," "&E82)&IF(K82=""," "," - "&K82))
B83: HINO | C83: F17E | D83: 139 | E83: (A) | F83: Buồng Nổ tròn 71 nhọn, có 2 dấu supap | G83: 50x110 | H83: 65.3 | I83: 144.3 | J83: 3.3K-3.5-3.5-5 | L83: Bộ 8 | R83: 🟢 CÓ | U83: =IF($C83="","",B83&" "&C83&" · ĐK"&D83&IF(E83=""," "," "&E83)&IF(K83=""," "," - "&K83))
A84: HH070489 | B84: HINO | C84: V22C-L+R | D84: 139 | E84: (A) | F84: Buồng Nổ tròn 75 nhọn, có 2 dấu supap,cò nhớt | G84: 50x110 | H84: 65.3 | I84: 144.3 | J84: 3.3K-3.5-3.5-6 | K84: IZUMI | L84: Cái | N84: 6550000 | O84: 7000000 | P84: 7450000 | R84: 🟢 CÓ | U84: =IF($C84="","",B84&" "&C84&" · ĐK"&D84&IF(E84=""," "," "&E84)&IF(K84=""," "," - "&K84))
B85: HINO | C85: F20C-A | D85: 146 | E85: (A) | F85: Buồng Nổ tròn 76 nhọn có 4 dấu supap | G85: 50x110 | H85: 59.5 | I85: 138.5 | J85: 3.3K-3.5-3.5-5 | L85: Cái | R85: 🟢 CÓ | U85: =IF($C85="","",B85&" "&C85&" · ĐK"&D85&IF(E85=""," "," "&E85)&IF(K85=""," "," - "&K85))
B86: HINO | C86: F20C-B | D86: 146 | E86: (A) | F86: Buồng Nổ tròn 72 lõm bằng, có 4 dấu supap | G86: 50x110 | H86: 59.5 | I86: 138.5 | J86: 3.3K-3.5-3.5-5 | L86: Cái | R86: 🟢 CÓ | U86: =IF($C86="","",B86&" "&C86&" · ĐK"&D86&IF(E86=""," "," "&E86)&IF(K86=""," "," - "&K86))
B87: HINO | C87: F20C-E | D87: 146 | E87: (A) | F87: Buồng Nổ tròn 70 nhọn, có 4 dấu supap | G87: 50x110 | H87: 59.5 | I87: 138.5 | J87: 3.3K-3-3-4 | L87: Cái | R87: 🟢 CÓ | U87: =IF($C87="","",B87&" "&C87&" · ĐK"&D87&IF(E87=""," "," "&E87)&IF(K87=""," "," - "&K87))
A88: HH080392 | B88: HINO | C88: F21C | D88: 150 | E88: (A) | F88: Buồng Nổ tròn 72 nhọn, có 4 dấu supap | G88: 50x110 | H88: 59.5 | I88: 138.5 | J88: 3.3K-3-3-4 | K88: IKAZU | L88: Cái | N88: 6750000 | O88: 7200000 | P88: 7650000 | R88: 🟢 CÓ | S88: 13216-1331R/13216-2661L | U88: =IF($C88="","",B88&" "&C88&" · ĐK"&D88&IF(E88=""," "," "&E88)&IF(K88=""," "," - "&K88))
B89: HINO | C89: V26C, V26C-T | D89: 150 | E89: (A)+(O) | F89: Buồng Nổ tròn 72 nhọn, có 4 dấu supap | G89: 50x110 | H89: 59.5 | I89: 138.5 | J89: 3.3K-3-3-4 | L89: Cái | R89: 🟢 CÓ | U89: =IF($C89="","",B89&" "&C89&" · ĐK"&D89&IF(E89=""," "," "&E89)&IF(K89=""," "," - "&K89))
A90: HH082919 | B90: INTERNATIONAL MAXXFORCE | C90: DT466E/ 3005634C2/ 3015721C92 | D90: 126 | F90: Piston Thép | G90: 52 | H90: 50 | I90: 110 | J90: 3.5K-2.5-3.5 | K90: HENWEIT | N90: 4200000 | O90: 4400000 | P90: 4600000 | S90: 3005634C2/ 3015721C92
B91: ◆ ISUZU (127 sản phẩm) | U91: =IF($C91="","",B91&" "&C91&" · ĐK"&D91&IF(E91=""," "," "&E91)&IF(K91=""," "," - "&K91))
A92: HH071407 | B92: ISUZU | C92: 3KC1 | D92: 74 | E92: 0 kiềng gang | F92: Buồng Nổ chuồn | G92: 21x66.5 | H92: 27 | I92: 70 | J92: 2-1.5-3.5 | K92: IZUMI | L92: Cái | N92: 980000 | O92: 1050000 | P92: 1100000 | R92: 🟢 CÓ | U92: =IF($C92="","",B92&" "&C92&" · ĐK"&D92&IF(E92=""," "," "&E92)&IF(K92=""," "," - "&K92))
A93: HH083894 | B93: ISUZU | C93: 3KC1 | D93: 74 | E93: 0 kiềng gang | F93: Buồng Nổ chuồn | G93: 21x66.5 | H93: 27 | I93: 70 | J93: 2-1.5-3.5 | K93: NICE IN | L93: Cái | N93: 1100000 | O93: 1200000 | P93: 1300000 | R93: 🟢 CÓ | U93: =IF($C93="","",B93&" "&C93&" · ĐK"&D93&IF(E93=""," "," "&E93)&IF(K93=""," "," - "&K93))
A94: HH076519 | B94: ISUZU | C94: 3KC2 | D94: 74 | E94: 0 kiềng gang | F94: Buồng Nổ vuông 37 có 2 dấu supap | G94: 21x66.5 | H94: 27 | I94: 67 | J94: 2-1.5-3.5 | K94: IZUMI | L94: Cái | N94: 1050000 | O94: 1100000 | P94: 1200000 | R94: 🟢 CÓ | U94: =IF($C94="","",B94&" "&C94&" · ĐK"&D94&IF(E94=""," "," "&E94)&IF(K94=""," "," - "&K94))
B95: ISUZU | C95: 4FE1-PB | D95: 76.3 | E95: 0 kiềng gang | F95: Buồng Nổ chuồn | G95: 25x63 | H95: 33 | I95: 80 | J95: 2-2-4 | L95: Bộ 4 | R95: 🟢 CÓ | U95: =IF($C95="","",B95&" "&C95&" · ĐK"&D95&IF(E95=""," "," "&E95)&IF(K95=""," "," - "&K95))
A96: HH074379 | B96: ISUZU | C96: 3LB1 | D96: 77.4 | E96: 0 kiềng gang | F96: buồng nổ ách chuồn, má đen | G96: 21x60 | H96: 25.5 | I96: 80 | J96: 2-1.5-3.5 | K96: IZUMI | L96: Cái | R96: 🟢 CÓ | U96: =IF($C96="","",B96&" "&C96&" · ĐK"&D96&IF(E96=""," "," "&E96)&IF(K96=""," "," - "&K96))
A97: HH075420 | B97: ISUZU | C97: 4LB1 | D97: 77.4 | E97: 0 kiềng gang | F97: buồng nổ ách chuồn, má đen | G97: 21x60 | H97: 25.5 | I97: 80 | J97: 2-1.5-3.5 | K97: IZUMI | L97: Cái | R97: 🟢 CÓ | U97: =IF($C97="","",B97&" "&C97&" · ĐK"&D97&IF(E97=""," "," "&E97)&IF(K97=""," "," - "&K97))
A98: HH082325 | B98: ISUZU | C98: 4LC1 | D98: 77.4 | E98: 0 kiềng gang | F98: Buồng Nổ chuồn | G98: 25x60 | H98: 31.5 | I98: 80 | J98: 2-1.5-3.5 | K98: NICE IN | L98: Bộ 4 | N98: 1350000 | O98: 1450000 | P98: 1550000 | R98: 🟢 CÓ | U98: =IF($C98="","",B98&" "&C98&" · ĐK"&D98&IF(E98=""," "," "&E98)&IF(K98=""," "," - "&K98))
B99: ISUZU | C99: 4EE1-T | D99: 79 | F99: Buồng Nổ 38, 8 có 4 dấu supap | G99: 27x64 | H99: 26 | I99: 84 | J99: 2-1.5-3 | L99: Bộ 4 | R99: 🟢 CÓ | U99: =IF($C99="","",B99&" "&C99&" · ĐK"&D99&IF(E99=""," "," "&E99)&IF(K99=""," "," - "&K99))
A100: HH068730 | B100: ISUZU | C100: 3KR1 | D100: 81 | E100: 0 kiềng gang | F100: Buồng Nổ chuồn | G100: 25x64 | H100: 37 | I100: 80 | J100: 2-1.75-4 | K100: IZUMI | L100: Cái | N100: 980000 | O100: 1050000 | P100: 1100000 | R100: 🟢 CÓ | U100: =IF($C100="","",B100&" "&C100&" · ĐK"&D100&IF(E100=""," "," "&E100)&IF(K100=""," "," - "&K100))
...

Sheet ⚙️ SÉC MĂNG
A1: ⚙️ SÉC MĂNG — dữ liệu mới nhất (Hãng + ĐK lấy từ Piston)
A2: 🏷️ Mã HH | B2: 🏭 Hãng | C2: ⚙️ Mã ĐC | D2: 📐 ĐK | E2: Xy lanh kiếng? | F2: Loại | G2: Ring | H2: 🏷️ Thương hiệu | I2: 📦 ĐVT | J2: 💰 Vốn | K2: 🟢 VIP | L2: 🟡 Ưu đãi | M2: 🔵 Đại lý | N2: 🟣 Gara | O2: 📦 Tồn | P2: 🔧 PARNO | Q2: 📝 Ghi chú | R2: _KEY | S2: _AUTO
C3: ◆ HINO
A4: HH071911 | B4: HINO | C4: DM100 | D4: 90 | G4: 2.5-2.5-2.5-4-4 | H4: TP | I4: Máy | R4: Séc măng DM100 (2.5-2.5-2.5-4-4) - TP | S4: =IF(OR('⚙️ BỘ HƠI'!$H$40=0,'⚙️ BỘ HƠI'!$H$2="",$C4="",LEFT($C4,1)="◆"),99999,IF(OR(ISNUMBER(SEARCH('⚙️ BỘ HƠI'!$H$2,$C4)),ISNUMBER(SEARCH($C4,'⚙️ BỘ HƠI'!$H$2))),ROW()-2,99999))
A5: HH083979 | B5: HINO | C5: DM100 | D5: 90 | G5: 2.5-2.5-2.5-4-4 | H5: HENWEIT, R-HN23-00 | I5: Máy | K5: 120000 | L5: 130000 | M5: 140000 | P5: SCH20004ZZ | R5: Séc măng Hino DM100 (2.5-2.5-2.5-4-4) SCH20004ZZ - HENWEIT, R-HN23-00 | S5: =IF(OR('⚙️ BỘ HƠI'!$H$40=0,'⚙️ BỘ HƠI'!$H$2="",$C5="",LEFT($C5,1)="◆"),99999,IF(OR(ISNUMBER(SEARCH('⚙️ BỘ HƠI'!$H$2,$C5)),ISNUMBER(SEARCH($C5,'⚙️ BỘ HƠI'!$H$2))),ROW()-2,99999))
A6: HH071287 | B6: HINO | C6: EC100/có/lò/xo | D6: 97 | G6: 2.5-2.5-2.5-4-4 | H6: RIK | I6: 1Máy | R6: Séc măng EC100 có lò xo (2.5-2.5-2.5-4-4) - RIK | S6: =IF(OR('⚙️ BỘ HƠI'!$H$40=0,'⚙️ BỘ HƠI'!$H$2="",$C6="",LEFT($C6,1)="◆"),99999,IF(OR(ISNUMBER(SEARCH('⚙️ BỘ HƠI'!$H$2,$C6)),ISNUMBER(SEARCH($C6,'⚙️ BỘ HƠI'!$H$2))),ROW()-2,99999))
A7: HH083716 | B7: HINO | C7: N04C/W04DT/1+3/thép | D7: 104 | G7: 2.8K-2-4 | H7: NPR | I7: Máy | K7: 1000000 | L7: 1100000 | M7: 1200000 | P7: SDT10221ZZ | R7: Séc măng Hino N04C/W04DT/SDT10221ZZ (2.8K-2-4) 1+3 thép HỘP4- NPR | S7: =IF(OR('⚙️ BỘ HƠI'!$H$40=0,'⚙️ BỘ HƠI'!$H$2="",$C7="",LEFT($C7,1)="◆"),99999,IF(OR(ISNUMBER(SEARCH('⚙️ BỘ HƠI'!$H$2,$C7)),ISNUMBER(SEARCH($C7,'⚙️ BỘ HƠI'!$H$2))),ROW()-2,99999))
A8: HH081985 | B8: HINO | C8: W04C-T/W06C/1/thép | D8: 104 | G8: 2.8K-2.5-5 | H8: NPR | I8: Máy | K8: 250000 | L8: 270000 | M8: 290000 | P8: YDH20047ZX | R8: Séc măng Hino W04C-T/ YDH20047ZX (2.8K-2.5-5) W06C, 1 thép, HỘP1 - NPR | S8: =IF(OR('⚙️ BỘ HƠI'!$H$40=0,'⚙️ BỘ HƠI'!$H$2="",$C8="",LEFT($C8,1)="◆"),99999,IF(OR(ISNUMBER(SEARCH('⚙️ BỘ HƠI'!$H$2,$C8)),ISNUMBER(SEARCH($C8,'⚙️ BỘ HƠI'!$H$2))),ROW()-2,99999))
A9: HH078927 | B9: HINO | C9: W04D/W04E | D9: 104 | G9: 2.5-2-5 | H9: IZUMI | I9: Cái | K9: 110000 | L9: 120000 | M9: 130000 | R9: Séc măng HINO-W04D /W04E (2.5-2-5) - IZUMI | S9: =IF(OR('⚙️ BỘ HƠI'!$H$40=0,'⚙️ BỘ HƠI'!$H$2="",$C9="",LEFT($C9,1)="◆"),99999,IF(OR(ISNUMBER(SEARCH('⚙️ BỘ HƠI'!$H$2,$C9)),ISNUMBER(SEARCH($C9,'⚙️ BỘ HƠI'!$H$2))),ROW()-2,99999))
A10: HH073113 | B10: HINO | C10: W04D/W04E | D10: 104 | G10: 2.5-2-5 | H10: TP | I10: Cái | R10: Séc măng HINO-W04D /W04E (2.5-2-5) - TP | S10: =IF(OR('⚙️ BỘ HƠI'!$H$40=0,'⚙️ BỘ HƠI'!$H$2="",$C10="",LEFT($C10,1)="◆"),99999,IF(OR(ISNUMBER(SEARCH('⚙️ BỘ HƠI'!$H$2,$C10)),ISNUMBER(SEARCH($C10,'⚙️ BỘ HƠI'!$H$2))),ROW()-2,99999))
A11: HH00278 | B11: HINO | C11: W04D/W04E | D11: 104 | G11: 2.5-2-5 | H11: NPR | I11: Máy | P11: SDH20038ZX | R11: Séc măng HINO-W04D/W04E (2.5-2-5) SDH20038ZX - NPR | S11: =IF(OR('⚙️ BỘ HƠI'!$H$40=0,'⚙️ BỘ HƠI'!$H$2="",$C11="",LEFT($C11,1)="◆"),99999,IF(OR(ISNUMBER(SEARCH('⚙️ BỘ HƠI'!$H$2,$C11)),ISNUMBER(SEARCH($C11,'⚙️ BỘ HƠI'!$H$2))),ROW()-2,99999))
A12: HH084322 | B12: HINO | C12: W04D/W04E/nhớt/thép/-/HENWEIT/'R-HN01-00-1 | D12: 104 | G12: 2.5-2-5 | I12: Máy | K12: 140000 | L12: 150000 | M12: 160000 | P12: 13011-1973 | R12: Séc măng Hino W04D/W04E/13011-1973 (2.5-2-5) nhớt thép - HENWEIT 'R-HN01-00-1 | S12: =IF(OR('⚙️ BỘ HƠI'!$H$40=0,'⚙️ BỘ HƠI'!$H$2="",$C12="",LEFT($C12,1)="◆"),99999,IF(OR(ISNUMBER(SEARCH('⚙️ BỘ HƠI'!$H$2,$C12)),ISNUMBER(SEARCH($C12,'⚙️ BỘ HƠI'!$H$2))),ROW()-2,99999))
A13: HH20499 | B13: HINO | C13: W06D/W04D/1+3/thép/1/máy | D13: 104 | G13: 2.5-2-5 | H13: NPR | I13: 1Máy | K13: 150000 | L13: 170000 | M13: 200000 | P13: YDH20041ZX | R13: Séc măng Hino W06D/ YDH20041ZX (2.5-2-5), W04D, 1+3 thép, hộp 1 máy - NPR | S13: =IF(OR('⚙️ BỘ HƠI'!$H$40=0,'⚙️ BỘ HƠI'!$H$2="",$C13="",LEFT($C13,1)="◆"),99999,IF(OR(ISNUMBER(SEARCH('⚙️ BỘ HƠI'!$H$2,$C13)),ISNUMBER(SEARCH($C13,'⚙️ BỘ HƠI'!$H$2))),ROW()-2,99999))
A14: HH00454 | B14: HINO | C14: W06D/W06E | D14: 104 | G14: 2.5-2-5 | H14: TP | I14: Máy | R14: Séc măng W06D/ W06E (2.5-2-5) - TP | S14: =IF(OR('⚙️ BỘ HƠI'!$H$40=0,'⚙️ BỘ HƠI'!$H$2="",$C14="",LEFT($C14,1)="◆"),99999,IF(OR(ISNUMBER(SEARCH('⚙️ BỘ HƠI'!$H$2,$C14)),ISNUMBER(SEARCH($C14,'⚙️ BỘ HƠI'!$H$2))),ROW()-2,99999))
A15: HH076961 | B15: HINO | C15: H06C-TA | D15: 108 | G15: 2.8K-2.5-2.5-5 | H15: TP | I15: 1Máy | R15: Séc măng H06C-TA (2.8K-2.5-2.5-5) - TP | S15: =IF(OR('⚙️ BỘ HƠI'!$H$40=0,'⚙️ BỘ HƠI'!$H$2="",$C15="",LEFT($C15,1)="◆"),99999,IF(OR(ISNUMBER(SEARCH('⚙️ BỘ HƠI'!$H$2,$C15)),ISNUMBER(SEARCH($C15,'⚙️ BỘ HƠI'!$H$2))),ROW()-2,99999))
A16: HH084326 | B16: HINO | C16: H06C-TA | D16: 108 | G16: 2.8K-2.5-2.5-5 | H16: HENWEIT 'R-HN24-00 | I16: Máy | K16: 180000 | L16: 200000 | M16: 220000 | R16: Séc măng Hino H06C-TA (2.8K-2.5-2.5-5) - HENWEIT 'R-HN24-00 | S16: =IF(OR('⚙️ BỘ HƠI'!$H$40=0,'⚙️ BỘ HƠI'!$H$2="",$C16="",LEFT($C16,1)="◆"),99999,IF(OR(ISNUMBER(SEARCH('⚙️ BỘ HƠI'!$H$2,$C16)),ISNUMBER(SEARCH($C16,'⚙️ BỘ HƠI'!$H$2))),ROW()-2,99999))
A17: HH073310 | B17: HINO | C17: H06C/1+4/thép/BỘ6 | D17: 108 | G17: 3-2.5-2.5-5 | H17: NPR | I17: Máy | K17: 1200000 | L17: 1300000 | M17: 1400000 | P17: SDH20042ZX | R17: Séc măng Hino H06C/ SDH20042ZX (3-2.5-2.5-5) 1+4 thép, BỘ6 - NPR | S17: =IF(OR('⚙️ BỘ HƠI'!$H$40=0,'⚙️ BỘ HƠI'!$H$2="",$C17="",LEFT($C17,1)="◆"),99999,IF(OR(ISNUMBER(SEARCH('⚙️ BỘ HƠI'!$H$2,$C17)),ISNUMBER(SEARCH($C17,'⚙️ BỘ HƠI'!$H$2))),ROW()-2,99999))
A18: HH084327 | B18: HINO | C18: EH700/H07C | D18: 110 | G18: 3-2.5-2.5-5 | H18: HENWEIT 'R-HN03-00 | I18: Máy | K18: 150000 | L18: 160000 | M18: 170000 | R18: Séc măng Hino EH700/ H07C (3-2.5-2.5-5) - HENWEIT 'R-HN03-00 | S18: =IF(OR('⚙️ BỘ HƠI'!$H$40=0,'⚙️ BỘ HƠI'!$H$2="",$C18="",LEFT($C18,1)="◆"),99999,IF(OR(ISNUMBER(SEARCH('⚙️ BỘ HƠI'!$H$2,$C18)),ISNUMBER(SEARCH($C18,'⚙️ BỘ HƠI'!$H$2))),ROW()-2,99999))
A19: HH0234 | B19: HINO | C19: EH700/H07C/1+4/thép | D19: 110 | G19: 3-2.5-2.5-5 | H19: NPR | I19: Máy | K19: 930000 | L19: 990000 | M19: 1100000 | P19: SDH20043ZX | R19: Séc măng Hino EH700/H07C/SDH20043ZX (3-2.5-2.5-5) 1+4 thép HỘP6- NPR | S19: =IF(OR('⚙️ BỘ HƠI'!$H$40=0,'⚙️ BỘ HƠI'!$H$2="",$C19="",LEFT($C19,1)="◆"),99999,IF(OR(ISNUMBER(SEARCH('⚙️ BỘ HƠI'!$H$2,$C19)),ISNUMBER(SEARCH($C19,'⚙️ BỘ HƠI'!$H$2))),ROW()-2,99999))
A20: HH071313 | B20: HINO | C20: H07CT/1+4/thép | D20: 110 | G20: 2.8K-2-2.5-4 | H20: NPR | I20: Máy | K20: 1200000 | L20: 1260000 | M20: 1350000 | P20: SDH20057ZX | R20: Séc măng Hino H07CT/ SDH20057ZX (2.8K-2-2.5-4) 1+4 thép HỘP6 - NPR | S20: =IF(OR('⚙️ BỘ HƠI'!$H$40=0,'⚙️ BỘ HƠI'!$H$2="",$C20="",LEFT($C20,1)="◆"),99999,IF(OR(ISNUMBER(SEARCH('⚙️ BỘ HƠI'!$H$2,$C20)),ISNUMBER(SEARCH($C20,'⚙️ BỘ HƠI'!$H$2))),ROW()-2,99999))
A21: HH070558 | B21: HINO | C21: H07D/1+3thép | D21: 110 | G21: 3-2-4 | H21: NPR | I21: Máy | K21: 1000000 | L21: 1100000 | M21: 1200000 | P21: SDH20056ZX | R21: Séc măng Hino H07D/ SDH20056ZX (3-2-4) 1+3thép, HỘP6 - NPR | S21: =IF(OR('⚙️ BỘ HƠI'!$H$40=0,'⚙️ BỘ HƠI'!$H$2="",$C21="",LEFT($C21,1)="◆"),99999,IF(OR(ISNUMBER(SEARCH('⚙️ BỘ HƠI'!$H$2,$C21)),ISNUMBER(SEARCH($C21,'⚙️ BỘ HƠI'!$H$2))),ROW()-2,99999))
A22: HH078417 | B22: HINO | C22: J05E/J08E | D22: 112 | G22: 2.5-2-4 | H22: TP | I22: 1Máy | R22: Séc măng J05E/J08E/ 2.5-2-4 - TP | S22: =IF(OR('⚙️ BỘ HƠI'!$H$40=0,'⚙️ BỘ HƠI'!$H$2="",$C22="",LEFT($C22,1)="◆"),99999,IF(OR(ISNUMBER(SEARCH('⚙️ BỘ HƠI'!$H$2,$C22)),ISNUMBER(SEARCH($C22,'⚙️ BỘ HƠI'!$H$2))),ROW()-2,99999))
A23: HH079583 | B23: HINO | C23: J05E/THÉP | D23: 112 | G23: 2.5-2-4 | H23: NPR | I23: Máy | K23: 750000 | L23: 790000 | M23: 840000 | P23: SDH20108ZY | R23: Séc măng Hino J05E/ SDH20108ZY (2.5-2-4) THÉP HỘP4- NPR | S23: =IF(OR('⚙️ BỘ HƠI'!$H$40=0,'⚙️ BỘ HƠI'!$H$2="",$C23="",LEFT($C23,1)="◆"),99999,IF(OR(ISNUMBER(SEARCH('⚙️ BỘ HƠI'!$H$2,$C23)),ISNUMBER(SEARCH($C23,'⚙️ BỘ HƠI'!$H$2))),ROW()-2,99999))
A24: HH084138 | B24: HINO | C24: J08E/J05E | D24: 112 | G24: 2.5-2-4 | H24: HENWEIT R-HN13-00 | I24: Máy | K24: 150000 | L24: 170000 | M24: 200000 | P24: 13011-4040A | R24: Séc măng Hino J08E/ J05E (2.5-2-4) 13011-4040A - HENWEIT R-HN13-00 | S24: =IF(OR('⚙️ BỘ HƠI'!$H$40=0,'⚙️ BỘ HƠI'!$H$2="",$C24="",LEFT($C24,1)="◆"),99999,IF(OR(ISNUMBER(SEARCH('⚙️ BỘ HƠI'!$H$2,$C24)),ISNUMBER(SEARCH($C24,'⚙️ BỘ HƠI'!$H$2))),ROW()-2,99999))
A25: HH083677 | B25: HINO | C25: YL86/J05E/cho/pt/GANG | D25: 112 | G25: 3K-2-4 | H25: TP | I25: 1Máy | R25: Séc măng YL86/ J05E cho pt GANG, 3K-2-4 - TP | S25: =IF(OR('⚙️ BỘ HƠI'!$H$40=0,'⚙️ BỘ HƠI'!$H$2="",$C25="",LEFT($C25,1)="◆"),99999,IF(OR(ISNUMBER(SEARCH('⚙️ BỘ HƠI'!$H$2,$C25)),ISNUMBER(SEARCH($C25,'⚙️ BỘ HƠI'!$H$2))),ROW()-2,99999))
A26: HH084131 | B26: HINO | C26: J08C | D26: 114 | G26: 2.5-2-4 | H26: HENWEIT R-HN15-00 | I26: 1Máy | K26: 150000 | L26: 170000 | M26: 200000 | P26: 13011-3880 | R26: Séc măng Hino J08C/ 13011-3880/ 2.5-2-4 - HENWEIT R-HN15-00 | S26: =IF(OR('⚙️ BỘ HƠI'!$H$40=0,'⚙️ BỘ HƠI'!$H$2="",$C26="",LEFT($C26,1)="◆"),99999,IF(OR(ISNUMBER(SEARCH('⚙️ BỘ HƠI'!$H$2,$C26)),ISNUMBER(SEARCH($C26,'⚙️ BỘ HƠI'!$H$2))),ROW()-2,99999))
A27: HH073762 | B27: HINO | C27: J08C | D27: 114 | G27: 2.5-2-4 | H27: TP | I27: 1Máy | R27: Séc măng J08C/ 2.5-2-4 - TP | S27: =IF(OR('⚙️ BỘ HƠI'!$H$40=0,'⚙️ BỘ HƠI'!$H$2="",$C27="",LEFT($C27,1)="◆"),99999,IF(OR(ISNUMBER(SEARCH('⚙️ BỘ HƠI'!$H$2,$C27)),ISNUMBER(SEARCH($C27,'⚙️ BỘ HƠI'!$H$2))),ROW()-2,99999))
A28: HH00007 | B28: HINO | C28: J08C | D28: 114 | G28: 2.5-2-4 | H28: NPR | I28: 1Máy | P28: SDH20088ZY | R28: Séc măng J08C/ 2.5-2-4 (SDH20088ZY) - NPR | S28: =IF(OR('⚙️ BỘ HƠI'!$H$40=0,'⚙️ BỘ HƠI'!$H$2="",$C28="",LEFT($C28,1)="◆"),99999,IF(OR(ISNUMBER(SEARCH('⚙️ BỘ HƠI'!$H$2,$C28)),ISNUMBER(SEARCH($C28,'⚙️ BỘ HƠI'!$H$2))),ROW()-2,99999))
A29: HH075424 | B29: HINO | C29: J08C | D29: 114 | G29: 3-2-4 | H29: NPR | I29: 1Máy | K29: 1150000 | L29: 1250000 | M29: 1300000 | P29: SDH20067ZX | R29: Séc măng J08C/ 3-2-4 (SDH20067ZX) - NPR | S29: =IF(OR('⚙️ BỘ HƠI'!$H$40=0,'⚙️ BỘ HƠI'!$H$2="",$C29="",LEFT($C29,1)="◆"),99999,IF(OR(ISNUMBER(SEARCH('⚙️ BỘ HƠI'!$H$2,$C29)),ISNUMBER(SEARCH($C29,'⚙️ BỘ HƠI'!$H$2))),ROW()-2,99999))
A30: HH077096 | B30: HINO | C30: EL100/phi | D30: 116 | G30: 3-2.5-2.5-5 | H30: TP | I30: 1Máy | R30: Séc măng EL100 (phi 116) (3-2.5-2.5-5) - TP | S30: =IF(OR('⚙️ BỘ HƠI'!$H$40=0,'⚙️ BỘ HƠI'!$H$2="",$C30="",LEFT($C30,1)="◆"),99999,IF(OR(ISNUMBER(SEARCH('⚙️ BỘ HƠI'!$H$2,$C30)),ISNUMBER(SEARCH($C30,'⚙️ BỘ HƠI'!$H$2))),ROW()-2,99999))
A31: HH071107 | B31: HINO | C31: EL100/phi | D31: 116 | G31: 3-2.5-2.5-5 | H31: NPR | I31: Máy | K31: 1450000 | L31: 1550000 | M31: 1700000 | P31: SDH20029ZX | R31: Séc măng EL100 (phi 116) (3-2.5-2.5-5) SDH20029ZX - NPR | S31: =IF(OR('⚙️ BỘ HƠI'!$H$40=0,'⚙️ BỘ HƠI'!$H$2="",$C31="",LEFT($C31,1)="◆"),99999,IF(OR(ISNUMBER(SEARCH('⚙️ BỘ HƠI'!$H$2,$C31)),ISNUMBER(SEARCH($C31,'⚙️ BỘ HƠI'!$H$2))),ROW()-2,99999))
A32: HH074451 | B32: HINO | C32: EP100/P09C/1+4/thép/BỘ6 | D32: 120 | G32: 3.3K-2.8K-2.4-5 | H32: NPR | I32: Máy | K32: 1400000 | L32: 1500000 | M32: 1600000 | P32: SDH20034ZX | R32: Séc măng Hino EP100/P09C/SDH20034ZX (3.3K-2.8K-2.4-5) 1+4 thép BỘ6- NPR | S32: =IF(OR('⚙️ BỘ HƠI'!$H$40=0,'⚙️ BỘ HƠI'!$H$2="",$C32="",LEFT($C32,1)="◆"),99999,IF(OR(ISNUMBER(SEARCH('⚙️ BỘ HƠI'!$H$2,$C32)),ISNUMBER(SEARCH($C32,'⚙️ BỘ HƠI'!$H$2))),ROW()-2,99999))
A33: HH070727 | B33: HINO | C33: P11C/P11B | D33: 122 | G33: 3.3K-2.3K-2-4 | H33: NPR | I33: Máy | K33: 1750000 | L33: 1850000 | M33: 1950000 | P33: SDH20073ZZ | R33: Séc măng Hino P11C / P11B (3.3K-2.3K-2-4) SDH20073ZZ - NPR | S33: =IF(OR('⚙️ BỘ HƠI'!$H$40=0,'⚙️ BỘ HƠI'!$H$2="",$C33="",LEFT($C33,1)="◆"),99999,IF(OR(ISNUMBER(SEARCH('⚙️ BỘ HƠI'!$H$2,$C33)),ISNUMBER(SEARCH($C33,'⚙️ BỘ HƠI'!$H$2))),ROW()-2,99999))
A34: HH071927 | B34: HINO | C34: EM100/phi | D34: 124 | G34: 2.8K-2.5-3-5 | H34: NPR | I34: 1Máy | K34: 1700000 | L34: 1800000 | M34: 1950000 | P34: SDH20033ZX | R34: Séc măng EM100 phi 124 (2.8K-2.5-3-5) SDH20033ZX - NPR | S34: =IF(OR('⚙️ BỘ HƠI'!$H$40=0,'⚙️ BỘ HƠI'!$H$2="",$C34="",LEFT($C34,1)="◆"),99999,IF(OR(ISNUMBER(SEARCH('⚙️ BỘ HƠI'!$H$2,$C34)),ISNUMBER(SEARCH($C34,'⚙️ BỘ HƠI'!$H$2))),ROW()-2,99999))
A35: HH082808 | B35: HINO | C35: K13C-TE | D35: 135 | G35: 3.3K-3.5-3.5-5 | H35: NPR | I35: Cái | R35: Séc măng K13C-TE (3.3K-3.5-3.5-5) - NPR | S35: =IF(OR('⚙️ BỘ HƠI'!$H$40=0,'⚙️ BỘ HƠI'!$H$2="",$C35="",LEFT($C35,1)="◆"),99999,IF(OR(ISNUMBER(SEARCH('⚙️ BỘ HƠI'!$H$2,$C35)),ISNUMBER(SEARCH($C35,'⚙️ BỘ HƠI'!$H$2))),ROW()-2,99999))
A36: HH00527 | B36: HINO | C36: EF750 | D36: 137 | G36: 3.3K-3.5-3.5-6 | H36: TP | I36: Cái | R36: Séc măng EF750 (3.3K-3.5-3.5-6) - TP | S36: =IF(OR('⚙️ BỘ HƠI'!$H$40=0,'⚙️ BỘ HƠI'!$H$2="",$C36="",LEFT($C36,1)="◆"),99999,IF(OR(ISNUMBER(SEARCH('⚙️ BỘ HƠI'!$H$2,$C36)),ISNUMBER(SEARCH($C36,'⚙️ BỘ HƠI'!$H$2))),ROW()-2,99999))
A37: HH00526 | B37: HINO | C37: EF750/EF700/1thép | D37: 137 | G37: 3.3K-3.5-3.5-6 | H37: NPR | I37: Máy | K37: 2000000 | L37: 2100000 | M37: 2200000 | P37: SDH20025ZX0 | R37: Séc măng Hino EF750/EF700/SDH20025ZX0 (3.3K-3.5-3.5-6) 1thép, HỘP8 - NPR | S37: =IF(OR('⚙️ BỘ HƠI'!$H$40=0,'⚙️ BỘ HƠI'!$H$2="",$C37="",LEFT($C37,1)="◆"),99999,IF(OR(ISNUMBER(SEARCH('⚙️ BỘ HƠI'!$H$2,$C37)),ISNUMBER(SEARCH($C37,'⚙️ BỘ HƠI'!$H$2))),ROW()-2,99999))
A38: HH074495 | B38: HINO | C38: EK100/EK200 | D38: 137 | H38: TP | I38: Máy | R38: Séc măng EK100/EK200 - TP | S38: =IF(OR('⚙️ BỘ HƠI'!$H$40=0,'⚙️ BỘ HƠI'!$H$2="",$C38="",LEFT($C38,1)="◆"),99999,IF(OR(ISNUMBER(SEARCH('⚙️ BỘ HƠI'!$H$2,$C38)),ISNUMBER(SEARCH($C38,'⚙️ BỘ HƠI'!$H$2))),ROW()-2,99999))
A39: HH077107 | B39: HINO | C39: V22C/10/máy | D39: 139 | G39: 3.3K-3.5-3.5-6 | H39: NPR | I39: Máy | K39: 3250000 | L39: 3450000 | M39: 3660000 | P39: SDH20052ZZ | R39: Séc măng Hino V22C/SDH20052ZZ (3.3K-3.5-3.5-6) hộp 10 máy - NPR | S39: =IF(OR('⚙️ BỘ HƠI'!$H$40=0,'⚙️ BỘ HƠI'!$H$2="",$C39="",LEFT($C39,1)="◆"),99999,IF(OR(ISNUMBER(SEARCH('⚙️ BỘ HƠI'!$H$2,$C39)),ISNUMBER(SEARCH($C39,'⚙️ BỘ HƠI'!$H$2))),ROW()-2,99999))
A40: HH083702 | B40: HINO | C40: F20C/8/máy | D40: 146 | G40: 3.3K-3.5-3.5-5 | H40: NPR | I40: Máy | K40: 3500000 | L40: 3700000 | M40: 3950000 | P40: SDH20062ZX | R40: Séc măng Hino F20C/ SDH20062ZX (3.3K-3.5-3.5-5), hộp 8 máy - NPR | S40: =IF(OR('⚙️ BỘ HƠI'!$H$40=0,'⚙️ BỘ HƠI'!$H$2="",$C40="",LEFT($C40,1)="◆"),99999,IF(OR(ISNUMBER(SEARCH('⚙️ BỘ HƠI'!$H$2,$C40)),ISNUMBER(SEARCH($C40,'⚙️ BỘ HƠI'!$H$2))),ROW()-2,99999))
A41: HH083703 | B41: HINO | C41: F20C/8/máy | D41: 146 | G41: 3.3K-3-3-4 | H41: NPR | I41: Máy | K41: 3260000 | L41: 3450000 | M41: 3700000 | P41: SDH20077ZX | R41: Séc măng Hino F20C/ SDH20077ZX (3.3K-3-3-4) hộp 8 máy - NPR | S41: =IF(OR('⚙️ BỘ HƠI'!$H$40=0,'⚙️ BỘ HƠI'!$H$2="",$C41="",LEFT($C41,1)="◆"),99999,IF(OR(ISNUMBER(SEARCH('⚙️ BỘ HƠI'!$H$2,$C41)),ISNUMBER(SEARCH($C41,'⚙️ BỘ HƠI'!$H$2))),ROW()-2,99999))
C42: ◆ ISUZU
A43: HH071262 | B43: ISUZU | C43: 3KC1/3KC2 | D43: 74 | G43: 2-1.5-3.5 | H43: NPR | I43: 1Máy | K43: 450000 | L43: 500000 | M43: 550000 | P43: SDI10102ZZ | R43: Séc măng 3KC1/3KC2 ( 2-1.5-3.5) SDI10102ZZ - NPR | S43: =IF(OR('⚙️ BỘ HƠI'!$H$40=0,'⚙️ BỘ HƠI'!$H$2="",$C43="",LEFT($C43,1)="◆"),99999,IF(OR(ISNUMBER(SEARCH('⚙️ BỘ HƠI'!$H$2,$C43)),ISNUMBER(SEARCH($C43,'⚙️ BỘ HƠI'!$H$2))),ROW()-2,99999))
A44: HH080955 | B44: ISUZU | C44: 3KC1/3KC2/3c | D44: 74 | G44: 2-1.5-3.5 | H44: IZ IKAZU | I44: 1Máy | K44: 100000 | L44: 110000 | M44: 120000 | R44: Séc măng 3KC1/3KC2 (2-1.5-3.5), hộp 3c - IZ IKAZU | S44: =IF(OR('⚙️ BỘ HƠI'!$H$40=0,'⚙️ BỘ HƠI'!$H$2="",$C44="",LEFT($C44,1)="◆"),99999,IF(OR(ISNUMBER(SEARCH('⚙️ BỘ HƠI'!$H$2,$C44)),ISNUMBER(SEARCH($C44,'⚙️ BỘ HƠI'!$H$2))),ROW()-2,99999))
A45: HH077134 | B45: ISUZU | C45: 4FE1 | D45: 76.3 | G45: 2-2-4 | H45: TP | I45: 1Máy | R45: Séc măng 4FE1 (2-2-4) - TP | S45: =IF(OR('⚙️ BỘ HƠI'!$H$40=0,'⚙️ BỘ HƠI'!$H$2="",$C45="",LEFT($C45,1)="◆"),99999,IF(OR(ISNUMBER(SEARCH('⚙️ BỘ HƠI'!$H$2,$C45)),ISNUMBER(SEARCH($C45,'⚙️ BỘ HƠI'!$H$2))),ROW()-2,99999))
A46: HH0642 | B46: ISUZU | C46: 4FE1 | D46: 76.3 | G46: 2-2-4 | H46: NPR | I46: Máy | K46: 450000 | L46: 500000 | M46: 550000 | P46: SDI10212ZZ | R46: Séc măng 4FE1 (2-2-4) SDI10212ZZ - NPR | S46: =IF(OR('⚙️ BỘ HƠI'!$H$40=0,'⚙️ BỘ HƠI'!$H$2="",$C46="",LEFT($C46,1)="◆"),99999,IF(OR(ISNUMBER(SEARCH('⚙️ BỘ HƠI'!$H$2,$C46)),ISNUMBER(SEARCH($C46,'⚙️ BỘ HƠI'!$H$2))),ROW()-2,99999))
A47: HH071103 | B47: ISUZU | C47: 4LC1 | D47: 77.4 | G47: 2-1.5-3.5 | H47: NPR | I47: Máy | K47: 540000 | L47: 570000 | M47: 600000 | P47: SJI10213ZZ | R47: Séc măng 4LC1 (2-1.5-3.5) SJI10213ZZ - NPR | S47: =IF(OR('⚙️ BỘ HƠI'!$H$40=0,'⚙️ BỘ HƠI'!$H$2="",$C47="",LEFT($C47,1)="◆"),99999,IF(OR(ISNUMBER(SEARCH('⚙️ BỘ HƠI'!$H$2,$C47)),ISNUMBER(SEARCH($C47,'⚙️ BỘ HƠI'!$H$2))),ROW()-2,99999))
A48: HH083986 | B48: ISUZU | C48: 4LC1 | D48: 77.4 | G48: 2-1.5-3.5 | H48: HENWEIT, R-IS45-00 | I48: Máy | K48: 110000 | L48: 120000 | M48: 130000 | P48: 8-97034-609-0 | R48: Séc măng Isuzu 4LC1 (2-1.5-3.5)/ 8-97034-609-0 - HENWEIT, R-IS45-00 | S48: =IF(OR('⚙️ BỘ HƠI'!$H$40=0,'⚙️ BỘ HƠI'!$H$2="",$C48="",LEFT($C48,1)="◆"),99999,IF(OR(ISNUMBER(SEARCH('⚙️ BỘ HƠI'!$H$2,$C48)),ISNUMBER(SEARCH($C48,'⚙️ BỘ HƠI'!$H$2))),ROW()-2,99999))
A49: HH00504 | B49: ISUZU | C49: 3KR1 | D49: 81 | H49: TP | I49: Máy | R49: Séc măng 3KR1 - TP | S49: =IF(OR('⚙️ BỘ HƠI'!$H$40=0,'⚙️ BỘ HƠI'!$H$2="",$C49="",LEFT($C49,1)="◆"),99999,IF(OR(ISNUMBER(SEARCH('⚙️ BỘ HƠI'!$H$2,$C49)),ISNUMBER(SEARCH($C49,'⚙️ BỘ HƠI'!$H$2))),ROW()-2,99999))
A50: HH080944 | B50: ISUZU | C50: 3KR1/3KR2 | D50: 81 | G50: 2-1.75-4 | H50: IZ IKAZU | I50: Máy | K50: 100000 | L50: 110000 | M50: 120000 | R50: Séc măng 3KR1 / 3KR2 (2-1.75-4) - IZ IKAZU | S50: =IF(OR('⚙️ BỘ HƠI'!$H$40=0,'⚙️ BỘ HƠI'!$H$2="",$C50="",LEFT($C50,1)="◆"),99999,IF(OR(ISNUMBER(SEARCH('⚙️ BỘ HƠI'!$H$2,$C50)),ISNUMBER(SEARCH($C50,'⚙️ BỘ HƠI'!$H$2))),ROW()-2,99999))
A51: HH075158 | B51: ISUZU | C51: 3KR1/3KR2 | D51: 81 | G51: 2-1.75-4 | H51: ART | I51: Máy | P51: 15608101 | R51: Séc măng 3KR1 / 3KR2 (2-1.75-4) 15608101 - ART | S51: =IF(OR('⚙️ BỘ HƠI'!$H$40=0,'⚙️ BỘ HƠI'!$H$2="",$C51="",LEFT($C51,1)="◆"),99999,IF(OR(ISNUMBER(SEARCH('⚙️ BỘ HƠI'!$H$2,$C51)),ISNUMBER(SEARCH($C51,'⚙️ BỘ HƠI'!$H$2))),ROW()-2,99999))
A52: HH084332 | B52: ISUZU | C52: 3KR1/3KR2/nhớt/thép | D52: 81 | G52: 2-1.75-4 | H52: HENWEIT 'R-IS48-00 | I52: Máy | K52: 130000 | L52: 140000 | M52: 150000 | R52: Séc măng Isuzu 3KR1/ 3KR2 (2-1.75-4) nhớt thép - HENWEIT 'R-IS48-00 | S52: =IF(OR('⚙️ BỘ HƠI'!$H$40=0,'⚙️ BỘ HƠI'!$H$2="",$C52="",LEFT($C52,1)="◆"),99999,IF(OR(ISNUMBER(SEARCH('⚙️ BỘ HƠI'!$H$2,$C52)),ISNUMBER(SEARCH($C52,'⚙️ BỘ HƠI'!$H$2))),ROW()-2,99999))
A53: HH00229 | B53: ISUZU | C53: Isu/3KR1/3KR2 | D53: 81 | G53: 2-1.75-4 | H53: NPR | I53: Máy | K53: 550000 | L53: 580000 | M53: 620000 | P53: SDI10113ZZ | R53: Séc măng Isu 3KR1/ SDI10113ZZ (2-1.75-4) 3KR2, HỘP3 - NPR | S53: =IF(OR('⚙️ BỘ HƠI'!$H$40=0,'⚙️ BỘ HƠI'!$H$2="",$C53="",LEFT($C53,1)="◆"),99999,IF(OR(ISNUMBER(SEARCH('⚙️ BỘ HƠI'!$H$2,$C53)),ISNUMBER(SEARCH($C53,'⚙️ BỘ HƠI'!$H$2))),ROW()-2,99999))
A54: HH076137 | B54: ISUZU | C54: 3LD1 | D54: 83 | G54: 2-1.75-4 | H54: NPR | I54: Máy | P54: SDI10229ZZ | R54: Séc măng 3LD1 (2-1.75-4) SDI10229ZZ - NPR | S54: =IF(OR('⚙️ BỘ HƠI'!$H$40=0,'⚙️ BỘ HƠI'!$H$2="",$C54="",LEFT($C54,1)="◆"),99999,IF(OR(ISNUMBER(SEARCH('⚙️ BỘ HƠI'!$H$2,$C54)),ISNUMBER(SEARCH($C54,'⚙️ BỘ HƠI'!$H$2))),ROW()-2,99999))
A55: HH079372 | B55: ISUZU | C55: C221/C201/PT | D55: 83 | E55: kiếng | F55: không mạ | G55: 2-2-2-5-5 | H55: TP | I55: Máy | R55: Séc măng C221/C201 PT (2-2-2-5-5) không mạ - TP | S55: =IF(OR('⚙️ BỘ HƠI'!$H$40=0,'⚙️ BỘ HƠI'!$H$2="",$C55="",LEFT($C55,1)="◆"),99999,IF(OR(ISNUMBER(SEARCH('⚙️ BỘ HƠI'!$H$2,$C55)),ISNUMBER(SEARCH($C55,'⚙️ BỘ HƠI'!$H$2))),ROW()-2,99999))
A56: HH074517 | B56: ISUZU | C56: C221/C201/PT/mạ | D56: 83 | G56: 2-2-2-5-5 | H56: TP | I56: 1Máy | R56: Séc măng C221/C201 PT (2-2-2-5-5) mạ - TP | S56: =IF(OR('⚙️ BỘ HƠI'!$H$40=0,'⚙️ BỘ HƠI'!$H$2="",$C56="",LEFT($C56,1)="◆"),99999,IF(OR(ISNUMBER(SEARCH('⚙️ BỘ HƠI'!$H$2,$C56)),ISNUMBER(SEARCH($C56,'⚙️ BỘ HƠI'!$H$2))),ROW()-2,99999))
A57: HH070443 | B57: ISUZU | C57: 4LE1/4LE2 | D57: 85 | G57: 2-1.75-4 | H57: NPR | I57: 1Máy | K57: 620000 | L57: 660000 | M57: 710000 | P57: SJI10216ZZ | R57: Séc măng 4LE1/4LE2 (2-1.75-4) SJI10216ZZ - NPR | S57: =IF(OR('⚙️ BỘ HƠI'!$H$40=0,'⚙️ BỘ HƠI'!$H$2="",$C57="",LEFT($C57,1)="◆"),99999,IF(OR(ISNUMBER(SEARCH('⚙️ BỘ HƠI'!$H$2,$C57)),ISNUMBER(SEARCH($C57,'⚙️ BỘ HƠI'!$H$2))),ROW()-2,99999))
A58: HH081058 | B58: ISUZU | C58: 4LE1/4LE2 | D58: 85 | G58: 2HK-2-3 | H58: TP | I58: 1Máy | R58: Séc măng 4LE1/4LE2 (2HK-2-3) - TP | S58: =IF(OR('⚙️ BỘ HƠI'!$H$40=0,'⚙️ BỘ HƠI'!$H$2="",$C58="",LEFT($C58,1)="◆"),99999,IF(OR(ISNUMBER(SEARCH('⚙️ BỘ HƠI'!$H$2,$C58)),ISNUMBER(SEARCH($C58,'⚙️ BỘ HƠI'!$H$2))),ROW()-2,99999))
A59: HH084329 | B59: ISUZU | C59: 4LE1/4LE2/nhớt/Thép | D59: 85 | G59: 2-1.75-4 | H59: HENWEIT 'R-IS39-00 | I59: 1Máy | K59: 125000 | L59: 130000 | M59: 140000 | P59: 8-97141-208-0 | R59: Séc măng Isuzu 4LE1/ 4LE2/ 8-97141-208-0 (2-1.75-4) nhớt Thép - HENWEIT 'R-IS39-00 | S59: =IF(OR('⚙️ BỘ HƠI'!$H$40=0,'⚙️ BỘ HƠI'!$H$2="",$C59="",LEFT($C59,1)="◆"),99999,IF(OR(ISNUMBER(SEARCH('⚙️ BỘ HƠI'!$H$2,$C59)),ISNUMBER(SEARCH($C59,'⚙️ BỘ HƠI'!$H$2))),ROW()-2,99999))
A60: HH00021 | B60: ISUZU | C60: C190/C240 | D60: 86 | E60: kiếng | F60: không mạ | G60: 2-2-2-5 | H60: NPR | I60: 1Máy | P60: SDI10051ZZ | R60: Séc măng C190 C240/ 2-2-2-5 (SDI10051ZZ) không mạ - NPR | S60: =IF(OR('⚙️ BỘ HƠI'!$H$40=0,'⚙️ BỘ HƠI'!$H$2="",$C60="",LEFT($C60,1)="◆"),99999,IF(OR(ISNUMBER(SEARCH('⚙️ BỘ HƠI'!$H$2,$C60)),ISNUMBER(SEARCH($C60,'⚙️ BỘ HƠI'!$H$2))),ROW()-2,99999))
A61: HH084147 | B61: ISUZU | C61: C190/C240 | D61: 86 | E61: gang | F61: có mạ | G61: 2-2-2-5 | H61: HENWEIT, R-IS07-00 | I61: Máy | K61: 115000 | L61: 125000 | M61: 140000 | R61: Séc măng Isuzu C190/ C240 (2-2-2-5) có mạ - HENWEIT, R-IS07-00 | S61: =IF(OR('⚙️ BỘ HƠI'!$H$40=0,'⚙️ BỘ HƠI'!$H$2="",$C61="",LEFT($C61,1)="◆"),99999,IF(OR(ISNUMBER(SEARCH('⚙️ BỘ HƠI'!$H$2,$C61)),ISNUMBER(SEARCH($C61,'⚙️ BỘ HƠI'!$H$2))),ROW()-2,99999))
A62: HH083707 | B62: ISUZU | C62: C190/C240 | D62: 86 | E62: kiếng | F62: không mạ | G62: 2-2-2-5 | H62: NPR | I62: Máy | K62: 470000 | L62: 500000 | M62: 550000 | P62: SDI10051ZX | R62: Séc măng C190 C240/ SDI10051ZX (2-2-2-5) 1thép+KO mạ, XL KIẾNG, HỘP4 - NPR | S62: =IF(OR('⚙️ BỘ HƠI'!$H$40=0,'⚙️ BỘ HƠI'!$H$2="",$C62="",LEFT($C62,1)="◆"),99999,IF(OR(ISNUMBER(SEARCH('⚙️ BỘ HƠI'!$H$2,$C62)),ISNUMBER(SEARCH($C62,'⚙️ BỘ HƠI'!$H$2))),ROW()-2,99999))
A63: HH075161 | B63: ISUZU | C63: C190/C240 | D63: 86 | E63: gang | F63: có mạ | G63: 2-2-2-5 | H63: ART | I63: Máy | K63: 150000 | L63: 160000 | M63: 200000 | P63: 15768402 | R63: Séc măng C190/ C240 (2-2-2-5) dùng cho xl gang 15768402 - ART | S63: =IF(OR('⚙️ BỘ HƠI'!$H$40=0,'⚙️ BỘ HƠI'!$H$2="",$C63="",LEFT($C63,1)="◆"),99999,IF(OR(ISNUMBER(SEARCH('⚙️ BỘ HƠI'!$H$2,$C63)),ISNUMBER(SEARCH($C63,'⚙️ BỘ HƠI'!$H$2))),ROW()-2,99999))
A64: HH071331 | B64: ISUZU | C64: C190G/C240 | D64: 86 | E64: gang | F64: có mạ | G64: 2-2-2-5 | H64: NPR | I64: 1Máy | K64: 800000 | L64: 850000 | M64: 900000 | P64: SDI10083ZX | R64: Séc măng C190G/ C240 (2-2-2-5) có mạ/ SDI10083ZX - NPR | S64: =IF(OR('⚙️ BỘ HƠI'!$H$40=0,'⚙️ BỘ HƠI'!$H$2="",$C64="",LEFT($C64,1)="◆"),99999,IF(OR(ISNUMBER(SEARCH('⚙️ BỘ HƠI'!$H$2,$C64)),ISNUMBER(SEARCH($C64,'⚙️ BỘ HƠI'!$H$2))),ROW()-2,99999))
A65: HH074894 | B65: ISUZU | C65: C190G/C240/New | D65: 86 | E65: gang | F65: có mạ | G65: 2.5-2-5 | H65: TP | I65: 1Máy | R65: Séc măng C190G/C240 New (2.5 -2- 5) có mạ - TP | S65: =IF(OR('⚙️ BỘ HƠI'!$H$40=0,'⚙️ BỘ HƠI'!$H$2="",$C65="",LEFT($C65,1)="◆"),99999,IF(OR(ISNUMBER(SEARCH('⚙️ BỘ HƠI'!$H$2,$C65)),ISNUMBER(SEARCH($C65,'⚙️ BỘ HƠI'!$H$2))),ROW()-2,99999))
A66: HH074330 | B66: ISUZU | C66: C190G/C240 | D66: 86 | E66: gang | F66: có mạ | G66: 2-2-2-5 | H66: TP | I66: 1Máy | R66: Séc măng C190G/ C240 (2-2-2-5) có mạ cho sơ mi gang - TP | S66: =IF(OR('⚙️ BỘ HƠI'!$H$40=0,'⚙️ BỘ HƠI'!$H$2="",$C66="",LEFT($C66,1)="◆"),99999,IF(OR(ISNUMBER(SEARCH('⚙️ BỘ HƠI'!$H$2,$C66)),ISNUMBER(SEARCH($C66,'⚙️ BỘ HƠI'!$H$2))),ROW()-2,99999))
A67: HH081983 | B67: ISUZU | C67: C190G/C240/cos4 | D67: 86 | E67: gang | F67: có mạ | G67: 2-2-2-5 | H67: NPR | I67: 1Máy | R67: Séc măng C190G/ C240 (2-2-2-5) có mạ cos4 - NPR | S67: =IF(OR('⚙️ BỘ HƠI'!$H$40=0,'⚙️ BỘ HƠI'!$H$2="",$C67="",LEFT($C67,1)="◆"),99999,IF(OR(ISNUMBER(SEARCH('⚙️ BỘ HƠI'!$H$2,$C67)),ISNUMBER(SEARCH($C67,'⚙️ BỘ HƠI'!$H$2))),ROW()-2,99999))
A68: HH071204 | B68: ISUZU | C68: C190G/COS/2 | D68: 86 | E68: gang | F68: có mạ | G68: 2-2-2-5 | H68: RIK | I68: 1Máy | R68: Séc măng C190G (2-2-2-5) có mạ COS 2 - RIK | S68: =IF(OR('⚙️ BỘ HƠI'!$H$40=0,'⚙️ BỘ HƠI'!$H$2="",$C68="",LEFT($C68,1)="◆"),99999,IF(OR(ISNUMBER(SEARCH('⚙️ BỘ HƠI'!$H$2,$C68)),ISNUMBER(SEARCH($C68,'⚙️ BỘ HƠI'!$H$2))),ROW()-2,99999))
A69: HH080140 | B69: ISUZU | C69: C240- | D69: 86 | E69: kiếng | F69: không mạ | G69: 2-2-2-5 | H69: -TP | I69: 1Máy | R69: Séc măng C240-(2-2-2-5)-không mạ -TP | S69: =IF(OR('⚙️ BỘ HƠI'!$H$40=0,'⚙️ BỘ HƠI'!$H$2="",$C69="",LEFT($C69,1)="◆"),99999,IF(OR(ISNUMBER(SEARCH('⚙️ BỘ HƠI'!$H$2,$C69)),ISNUMBER(SEARCH($C69,'⚙️ BỘ HƠI'!$H$2))),ROW()-2,99999))
A70: HH075160 | B70: ISUZU | C70: C240/C190 | D70: 86 | E70: gang | F70: có mạ | G70: 2.5-2-5 | H70: ART | I70: Máy | P70: 15768401 | R70: Séc măng C240/C190 (2.5-2-5) dùng cho xl gang 15768401 - ART | S70: =IF(OR('⚙️ BỘ HƠI'!$H$40=0,'⚙️ BỘ HƠI'!$H$2="",$C70="",LEFT($C70,1)="◆"),99999,IF(OR(ISNUMBER(SEARCH('⚙️ BỘ HƠI'!$H$2,$C70)),ISNUMBER(SEARCH($C70,'⚙️ BỘ HƠI'!$H$2))),ROW()-2,99999))
A71: HH078675 | B71: ISUZU | C71: C240/New | D71: 86 | E71: kiếng | F71: không mạ | G71: 2.5-2-5 | H71: IZUMI | I71: 1Máy | K71: 70000 | L71: 80000 | M71: 90000 | R71: Séc măng C240 New (2.5 -2- 5) không mạ - IZUMI | S71: =IF(OR('⚙️ BỘ HƠI'!$H$40=0,'⚙️ BỘ HƠI'!$H$2="",$C71="",LEFT($C71,1)="◆"),99999,IF(OR(ISNUMBER(SEARCH('⚙️ BỘ HƠI'!$H$2,$C71)),ISNUMBER(SEARCH($C71,'⚙️ BỘ HƠI'!$H$2))),ROW()-2,99999))
A72: HH074561 | B72: ISUZU | C72: C240/New/C190 | D72: 86 | E72: kiếng | F72: không mạ | G72: 2.5-2-5 | H72: TP | I72: 1Máy | R72: Séc măng C240 New / C190 (2.5 -2- 5) không mạ - TP | S72: =IF(OR('⚙️ BỘ HƠI'!$H$40=0,'⚙️ BỘ HƠI'!$H$2="",$C72="",LEFT($C72,1)="◆"),99999,IF(OR(ISNUMBER(SEARCH('⚙️ BỘ HƠI'!$H$2,$C72)),ISNUMBER(SEARCH($C72,'⚙️ BỘ HƠI'!$H$2))),ROW()-2,99999))
A73: HH071117 | B73: ISUZU | C73: Isu/C240/C190 | D73: 86 | E73: gang | F73: có mạ | G73: 2.5-2-5 | H73: NPR | I73: Máy | K73: 700000 | L73: 750000 | M73: 800000 | P73: SDI10093ZZ | R73: Séc măng Isu C240/C190/SDI10093ZZ (2.5-2-5) CÓ mạ, BỘ4- NPR | S73: =IF(OR('⚙️ BỘ HƠI'!$H$40=0,'⚙️ BỘ HƠI'!$H$2="",$C73="",LEFT($C73,1)="◆"),99999,IF(OR(ISNUMBER(SEARCH('⚙️ BỘ HƠI'!$H$2,$C73)),ISNUMBER(SEARCH($C73,'⚙️ BỘ HƠI'!$H$2))),ROW()-2,99999))
A74: HH071116 | B74: ISUZU | C74: Isu/C240/C190 | D74: 86 | E74: kiếng | F74: không mạ | G74: 2.5-2-5 | H74: NPR | I74: Máy | K74: 400000 | L74: 420000 | M74: 450000 | P74: SDI10095ZZ | R74: Séc măng Isu C240/C190/SDI10095ZZ (2.5-2-5) KO mạ, BỘ4- NPR | S74: =IF(OR('⚙️ BỘ HƠI'!$H$40=0,'⚙️ BỘ HƠI'!$H$2="",$C74="",LEFT($C74,1)="◆"),99999,IF(OR(ISNUMBER(SEARCH('⚙️ BỘ HƠI'!$H$2,$C74)),ISNUMBER(SEARCH($C74,'⚙️ BỘ HƠI'!$H$2))),ROW()-2,99999))
A75: HH080617 | B75: ISUZU | C75: Isu/C223/4JC1 | D75: 88 | E75: kiếng | F75: không mạ | G75: 2-2-4 | H75: NPR | I75: Máy | K75: 350000 | L75: 400000 | M75: 450000 | P75: SDI10103ZZ | R75: Séc măng Isu C223/ SDI10103ZZ (2-2-4) 4JC1 KO mạ, HỘP4 - NPR | S75: =IF(OR('⚙️ BỘ HƠI'!$H$40=0,'⚙️ BỘ HƠI'!$H$2="",$C75="",LEFT($C75,1)="◆"),99999,IF(OR(ISNUMBER(SEARCH('⚙️ BỘ HƠI'!$H$2,$C75)),ISNUMBER(SEARCH($C75,'⚙️ BỘ HƠI'!$H$2))),ROW()-2,99999))
A76: HH070829 | B76: ISUZU | C76: Isu/D201/4JC1/1+4/thép/BỘ4 | D76: 88 | G76: 2-2-2-4 | H76: NPR | I76: Máy | K76: 730000 | L76: 780000 | M76: 830000 | P76: SDI10124ZX | R76: Séc măng Isu D201/ SDI10124ZX (2-2-2-4) 4JC1, 1+4 thép, BỘ4 - NPR | S76: =IF(OR('⚙️ BỘ HƠI'!$H$40=0,'⚙️ BỘ HƠI'!$H$2="",$C76="",LEFT($C76,1)="◆"),99999,IF(OR(ISNUMBER(SEARCH('⚙️ BỘ HƠI'!$H$2,$C76)),ISNUMBER(SEARCH($C76,'⚙️ BỘ HƠI'!$H$2))),ROW()-2,99999))
A77: HH073214 | B77: ISUZU | C77: 4JA1/4JB1 | D77: 93 | H77: TP | I77: Cái | R77: Séc măng 4JA1/4JB1 - TP | S77: =IF(OR('⚙️ BỘ HƠI'!$H$40=0,'⚙️ BỘ HƠI'!$H$2="",$C77="",LEFT($C77,1)="◆"),99999,IF(OR(ISNUMBER(SEARCH('⚙️ BỘ HƠI'!$H$2,$C77)),ISNUMBER(SEARCH($C77,'⚙️ BỘ HƠI'!$H$2))),ROW()-2,99999))
A78: HH074319 | B78: ISUZU | C78: 4JA1/4JB1-V | D78: 93 | E78: gang | F78: có mạ | H78: TP | I78: Máy | R78: Séc măng 4JA1/4JB1-V có mạ - TP | S78: =IF(OR('⚙️ BỘ HƠI'!$H$40=0,'⚙️ BỘ HƠI'!$H$2="",$C78="",LEFT($C78,1)="◆"),99999,IF(OR(ISNUMBER(SEARCH('⚙️ BỘ HƠI'!$H$2,$C78)),ISNUMBER(SEARCH($C78,'⚙️ BỘ HƠI'!$H$2))),ROW()-2,99999))
A79: HH083927 | B79: ISUZU | C79: 4JB1/493 | D79: 93 | E79: gang | F79: có mạ | G79: 3K-2-3.5 | H79: HENWEIT, R-IS43-00 | I79: Máy | K79: 100000 | L79: 110000 | M79: 120000 | R79: Séc măng Isuzu 4JB1/ 493 (có mạ) / 3K-2-3.5 - HENWEIT, R-IS43-00 | S79: =IF(OR('⚙️ BỘ HƠI'!$H$40=0,'⚙️ BỘ HƠI'!$H$2="",$C79="",LEFT($C79,1)="◆"),99999,IF(OR(ISNUMBER(SEARCH('⚙️ BỘ HƠI'!$H$2,$C79)),ISNUMBER(SEARCH($C79,'⚙️ BỘ HƠI'!$H$2))),ROW()-2,99999))
A80: HH079791 | B80: ISUZU | C80: 4JB1/4JA1 | D80: 93 | E80: kiếng | F80: không mạ | G80: 2-2-4 | H80: IZ IKAZU | I80: Máy | R80: Séc măng 4JB1 / 4JA1 / 2-2-4 không mạ - IZ IKAZU | S80: =IF(OR('⚙️ BỘ HƠI'!$H$40=0,'⚙️ BỘ HƠI'!$H$2="",$C80="",LEFT($C80,1)="◆"),99999,IF(OR(ISNUMBER(SEARCH('⚙️ BỘ HƠI'!$H$2,$C80)),ISNUMBER(SEARCH($C80,'⚙️ BỘ HƠI'!$H$2))),ROW()-2,99999))
A81: HH077618 | B81: ISUZU | C81: 4JB1/4JA1 | D81: 93 | E81: kiếng | F81: không mạ | G81: 2-2-4 | H81: IZUMI | I81: Máy | K81: 70000 | L81: 80000 | M81: 90000 | R81: Séc măng 4JB1 / 4JA1 / 2-2-4 không mạ - IZUMI | S81: =IF(OR('⚙️ BỘ HƠI'!$H$40=0,'⚙️ BỘ HƠI'!$H$2="",$C81="",LEFT($C81,1)="◆"),99999,IF(OR(ISNUMBER(SEARCH('⚙️ BỘ HƠI'!$H$2,$C81)),ISNUMBER(SEARCH($C81,'⚙️ BỘ HƠI'!$H$2))),ROW()-2,99999))
A82: HH075171 | B82: ISUZU | C82: 4JB1/4JA1 | D82: 93 | E82: kiếng | F82: không mạ | G82: 2-2-4 | H82: ART | I82: Máy | P82: 15609302 | R82: Séc măng 4JB1/4JA1/ 2-2-4 (15609302) không mạ - ART | S82: =IF(OR('⚙️ BỘ HƠI'!$H$40=0,'⚙️ BỘ HƠI'!$H$2="",$C82="",LEFT($C82,1)="◆"),99999,IF(OR(ISNUMBER(SEARCH('⚙️ BỘ HƠI'!$H$2,$C82)),ISNUMBER(SEARCH($C82,'⚙️ BỘ HƠI'!$H$2))),ROW()-2,99999))
A83: HH080881 | B83: ISUZU | C83: 4JB1/4JA1 | D83: 93 | E83: kiếng | F83: không mạ | G83: 2-2-4 | H83: NPR | I83: 1Máy | R83: Séc măng 4JB1/4JA1/ 2-2-4 không mạ - NPR | S83: =IF(OR('⚙️ BỘ HƠI'!$H$40=0,'⚙️ BỘ HƠI'!$H$2="",$C83="",LEFT($C83,1)="◆"),99999,IF(OR(ISNUMBER(SEARCH('⚙️ BỘ HƠI'!$H$2,$C83)),ISNUMBER(SEARCH($C83,'⚙️ BỘ HƠI'!$H$2))),ROW()-2,99999))
A84: HH077206 | B84: ISUZU | C84: 4JB1/4JA1/-/MAHLE | D84: 93 | E84: kiếng | F84: không mạ | G84: 2-2-4 | I84: Máy | K84: 80000 | L84: 90000 | M84: 100000 | P84: 8-94247867-0 | R84: Séc măng 4JB1/4JA1/ 2-2-4 không mạ - MAHLE 8-94247867-0 | S84: =IF(OR('⚙️ BỘ HƠI'!$H$40=0,'⚙️ BỘ HƠI'!$H$2="",$C84="",LEFT($C84,1)="◆"),99999,IF(OR(ISNUMBER(SEARCH('⚙️ BỘ HƠI'!$H$2,$C84)),ISNUMBER(SEARCH($C84,'⚙️ BỘ HƠI'!$H$2))),ROW()-2,99999))
A85: HH075162 | B85: ISUZU | C85: 4JB1/4JA1 | D85: 93 | E85: gang | F85: có mạ | G85: 2-2-4 | H85: ART | I85: Máy | P85: 15609301 | R85: Séc măng 4JB1/4JA1/ 2-2-4 (dùng cho xl gang) 15609301 - ART | S85: =IF(OR('⚙️ BỘ HƠI'!$H$40=0,'⚙️ BỘ HƠI'!$H$2="",$C85="",LEFT($C85,1)="◆"),99999,IF(OR(ISNUMBER(SEARCH('⚙️ BỘ HƠI'!$H$2,$C85)),ISNUMBER(SEARCH($C85,'⚙️ BỘ HƠI'!$H$2))),ROW()-2,99999))
A86: HH083104 | B86: ISUZU | C86: 4JB1/ZYNP | D86: 93 | E86: kiếng | F86: không mạ | G86: 2-2-4 | H86: NSP | I86: 1Máy | K86: 90000 | L86: 95000 | M86: 100000 | R86: Séc măng ISUZU 93/ 4JB1/ 2-2-4 (không mạ) ZYNP - NSP | S86: =IF(OR('⚙️ BỘ HƠI'!$H$40=0,'⚙️ BỘ HƠI'!$H$2="",$C86="",LEFT($C86,1)="◆"),99999,IF(OR(ISNUMBER(SEARCH('⚙️ BỘ HƠI'!$H$2,$C86)),ISNUMBER(SEARCH($C86,'⚙️ BỘ HƠI'!$H$2))),ROW()-2,99999))
A87: HH00023 | B87: ISUZU | C87: Isu/4JB1/4JA1 | D87: 93 | E87: gang+kiếng | G87: 2-2-4 | H87: NPR | I87: Máy | K87: 400000 | L87: 420000 | M87: 450000 | P87: SDI10110ZX | R87: Séc măng Isu 4JB1/4JA1/SDI10110ZX (2-2-4)Thép XL gang/kiếng HỘP4- NPR | S87: =IF(OR('⚙️ BỘ HƠI'!$H$40=0,'⚙️ BỘ HƠI'!$H$2="",$C87="",LEFT($C87,1)="◆"),99999,IF(OR(ISNUMBER(SEARCH('⚙️ BỘ HƠI'!$H$2,$C87)),ISNUMBER(SEARCH($C87,'⚙️ BỘ HƠI'!$H$2))),ROW()-2,99999))
A88: HH083105 | B88: ISUZU | C88: JMC493/4JB1 | D88: 93 | E88: kiếng | F88: không mạ | G88: 3K-2-4 | H88: NSP | I88: 1Máy | K88: 90000 | L88: 95000 | M88: 100000 | R88: Séc măng ISUZU 93/ JMC493/ 4JB1/ 3K-2-4 (không mạ) ZYNP - NSP | S88: =IF(OR('⚙️ BỘ HƠI'!$H$40=0,'⚙️ BỘ HƠI'!$H$2="",$C88="",LEFT($C88,1)="◆"),99999,IF(OR(ISNUMBER(SEARCH('⚙️ BỘ HƠI'!$H$2,$C88)),ISNUMBER(SEARCH($C88,'⚙️ BỘ HƠI'!$H$2))),ROW()-2,99999))
A89: HH083106 | B89: ISUZU | C89: JMC493/4JB1 | D89: 93 | E89: gang+kiếng | G89: 2.5K-2-2 | H89: NSP | I89: 1Máy | K89: 90000 | L89: 95000 | M89: 100000 | R89: Séc măng ISUZU 93/ JMC493/ 4JB1/ 2.5K-2-2 (thép xài sm kiếng và gang) ZYNP - NSP | S89: =IF(OR('⚙️ BỘ HƠI'!$H$40=0,'⚙️ BỘ HƠI'!$H$2="",$C89="",LEFT($C89,1)="◆"),99999,IF(OR(ISNUMBER(SEARCH('⚙️ BỘ HƠI'!$H$2,$C89)),ISNUMBER(SEARCH($C89,'⚙️ BỘ HƠI'!$H$2))),ROW()-2,99999))
A90: HH083282 | B90: ISUZU | C90: JX493/4JB1 | D90: 93 | E90: gang | F90: có mạ | G90: 2.8K-2-3 | H90: IZ IKAZU | I90: Máy | K90: 80000 | L90: 90000 | M90: 100000 | R90: Séc măng Isuzu JX493/ 4JB1/ 2.8K-2-3, CÓ mạ, xl gang - IZ IKAZU | S90: =IF(OR('⚙️ BỘ HƠI'!$H$40=0,'⚙️ BỘ HƠI'!$H$2="",$C90="",LEFT($C90,1)="◆"),99999,IF(OR(ISNUMBER(SEARCH('⚙️ BỘ HƠI'!$H$2,$C90)),ISNUMBER(SEARCH($C90,'⚙️ BỘ HƠI'!$H$2))),ROW()-2,99999))
A91: HH080378 | B91: ISUZU | C91: 4JG2/4JG1 | D91: 95.4 | E91: kiếng | F91: không mạ | G91: 2.5-2-4 | H91: IZ IKAZU | I91: 1Máy | K91: 85000 | L91: 90000 | M91: 95000 | R91: Séc măng 4JG2/4JG1 (2.5-2-4) không mạ - IZ IKAZU | S91: =IF(OR('⚙️ BỘ HƠI'!$H$40=0,'⚙️ BỘ HƠI'!$H$2="",$C91="",LEFT($C91,1)="◆"),99999,IF(OR(ISNUMBER(SEARCH('⚙️ BỘ HƠI'!$H$2,$C91)),ISNUMBER(SEARCH($C91,'⚙️ BỘ HƠI'!$H$2))),ROW()-2,99999))
A92: HH073194 | B92: ISUZU | C92: 4JG2/4JG1 | D92: 95.4 | E92: kiếng | F92: không mạ | G92: 2.5-2-4 | H92: TP | I92: 1Máy | R92: Séc măng 4JG2/4JG1 (2.5-2-4) không mạ - TP | S92: =IF(OR('⚙️ BỘ HƠI'!$H$40=0,'⚙️ BỘ HƠI'!$H$2="",$C92="",LEFT($C92,1)="◆"),99999,IF(OR(ISNUMBER(SEARCH('⚙️ BỘ HƠI'!$H$2,$C92)),ISNUMBER(SEARCH($C92,'⚙️ BỘ HƠI'!$H$2))),ROW()-2,99999))
A93: HH074055 | B93: ISUZU | C93: 4JG2/4JG1/mạ | D93: 95.4 | G93: 2.5-2-4 | H93: TP | I93: 1Máy | R93: Séc măng 4JG2/4JG1 (2.5-2-4) mạ - TP | S93: =IF(OR('⚙️ BỘ HƠI'!$H$40=0,'⚙️ BỘ HƠI'!$H$2="",$C93="",LEFT($C93,1)="◆"),99999,IF(OR(ISNUMBER(SEARCH('⚙️ BỘ HƠI'!$H$2,$C93)),ISNUMBER(SEARCH($C93,'⚙️ BỘ HƠI'!$H$2))),ROW()-2,99999))
A94: HH077658 | B94: ISUZU | C94: 4JJ1 | D94: 95.4 | E94: gang | F94: có mạ | G94: 2HK-2-3 | H94: TP | I94: Cái | R94: Séc măng 4JJ1 (2HK-2-3) có mạ - TP | S94: =IF(OR('⚙️ BỘ HƠI'!$H$40=0,'⚙️ BỘ HƠI'!$H$2="",$C94="",LEFT($C94,1)="◆"),99999,IF(OR(ISNUMBER(SEARCH('⚙️ BỘ HƠI'!$H$2,$C94)),ISNUMBER(SEARCH($C94,'⚙️ BỘ HƠI'!$H$2))),ROW()-2,99999))
A95: HH077657 | B95: ISUZU | C95: 4JJ1-TC | D95: 95.4 | E95: gang | F95: có mạ | G95: 2HK-1.5-3 | H95: TP | I95: Máy | R95: Séc măng 4JJ1-TC (2HK-1.5-3) có mạ - TP | S95: =IF(OR('⚙️ BỘ HƠI'!$H$40=0,'⚙️ BỘ HƠI'!$H$2="",$C95="",LEFT($C95,1)="◆"),99999,IF(OR(ISNUMBER(SEARCH('⚙️ BỘ HƠI'!$H$2,$C95)),ISNUMBER(SEARCH($C95,'⚙️ BỘ HƠI'!$H$2))),ROW()-2,99999))
A96: HH071510 | B96: ISUZU | C96: Isu/4JG2/4JG1/KO/mạ | D96: 95.4 | G96: 2.5-2-4 | H96: NPR | I96: Máy | K96: 450000 | L96: 500000 | M96: 550000 | P96: SDI10141ZZ | R96: Séc măng Isu 4JG2/ SDI10141ZZ (2.5-2-4) 4JG1, KO mạ, HỘP4 - NPR | S96: =IF(OR('⚙️ BỘ HƠI'!$H$40=0,'⚙️ BỘ HƠI'!$H$2="",$C96="",LEFT($C96,1)="◆"),99999,IF(OR(ISNUMBER(SEARCH('⚙️ BỘ HƠI'!$H$2,$C96)),ISNUMBER(SEARCH($C96,'⚙️ BỘ HƠI'!$H$2))),ROW()-2,99999))
A97: HH072180 | B97: ISUZU | C97: Isu/4JH1/95.4/KO/mạ/nhớt/thép/xl/kiếng | D97: 95.4 | G97: 2.5-2-3 | H97: NPR | I97: Máy | K97: 420000 | L97: 450000 | M97: 500000 | P97: SDI10193ZZ | R97: Séc măng Isu 4JH1/ SDI10193ZZ/ 95.4(2.5-2-3) KO mạ, nhớt thép, xl kiếng, HỘP4- NPR | S97: =IF(OR('⚙️ BỘ HƠI'!$H$40=0,'⚙️ BỘ HƠI'!$H$2="",$C97="",LEFT($C97,1)="◆"),99999,IF(OR(ISNUMBER(SEARCH('⚙️ BỘ HƠI'!$H$2,$C97)),ISNUMBER(SEARCH($C97,'⚙️ BỘ HƠI'!$H$2))),ROW()-2,99999))
A98: HH00009 | B98: ISUZU | C98: Isu/4JJ1-TC/1+3thép | D98: 95.4 | G98: 2HK-2-3 | H98: NPR | I98: Máy | K98: 650000 | L98: 700000 | M98: 750000 | P98: SDI10215ZZ | R98: Séc măng Isu 4JJ1-TC/SDI10215ZZ (2HK-2-3) 1+3thép, HỘP4 - NPR | S98: =IF(OR('⚙️ BỘ HƠI'!$H$40=0,'⚙️ BỘ HƠI'!$H$2="",$C98="",LEFT($C98,1)="◆"),99999,IF(OR(ISNUMBER(SEARCH('⚙️ BỘ HƠI'!$H$2,$C98)),ISNUMBER(SEARCH($C98,'⚙️ BỘ HƠI'!$H$2))),ROW()-2,99999))
A99: HH00010 | B99: ISUZU | C99: Isu/4JJ1-TC/THÉP | D99: 95.4 | G99: 2HK-1.5-3 | H99: NPR | I99: Máy | K99: 530000 | L99: 550000 | M99: 600000 | P99: SDI10209ZZ | R99: Séc măng Isu 4JJ1-TC/SDI10209ZZ (2HK-1.5-3) THÉP, HỘP4 - NPR | S99: =IF(OR('⚙️ BỘ HƠI'!$H$40=0,'⚙️ BỘ HƠI'!$H$2="",$C99="",LEFT($C99,1)="◆"),99999,IF(OR(ISNUMBER(SEARCH('⚙️ BỘ HƠI'!$H$2,$C99)),ISNUMBER(SEARCH($C99,'⚙️ BỘ HƠI'!$H$2))),ROW()-2,99999))
A100: HH081455 | B100: ISUZU | C100: Isu/4KH1/95.4/4JH1/THÉP/XL/gang/kiếng | D100: 95.4 | G100: 2.5-2-3 | H100: NPR | I100: Máy | K100: 450000 | L100: 500000 | M100: 550000 | P100: SDI10224ZZ0 | R100: Séc măng Isu 4KH1/ SDI10224ZZ0/95.4 (2.5-2-3) 4JH1, THÉP, XL gang/kiếng, HỘP4- NPR | S100: =IF(OR('⚙️ BỘ HƠI'!$H$40=0,'⚙️ BỘ HƠI'!$H$2="",$C100="",LEFT($C100,1)="◆"),99999,IF(OR(ISNUMBER(SEARCH('⚙️ BỘ HƠI'!$H$2,$C100)),ISNUMBER(SEARCH($C100,'⚙️ BỘ HƠI'!$H$2))),ROW()-2,99999))
...

Sheet 🔧 XY LANH
A1: 🔧 XY LANH — dữ liệu thật từ v10 (Mã HH/giá/kiếng-gang để trống điền sau)
A2: 🏷️ Mã HH | B2: 🏭 Hãng | C2: ⚙️ Mã ĐC | D2: đường kính | E2: Số máy | F2: LOẠI | G2: PARNO | H2: 🏷️ Thương hiệu | I2: ghi chú | J2: 🟢 VIP | K2: 🟡 Ưu đãi | L2: 🔵 Đại lý | M2: 🟣 Gara | N2: _TÊN | O2: _KEY | P2: _AUTO | Q2: 💡 Gợi ý Mã HH
B3: ◆ HINO (53 sản phẩm) | O3: =IF($N3="","",$N3) | P3: =IF(OR('⚙️ BỘ HƠI'!$H$40=0,'⚙️ BỘ HƠI'!$H$2="",$C3="",LEFT($C3,1)="◆"),99999,IF(OR(ISNUMBER(SEARCH('⚙️ BỘ HƠI'!$H$2,$C3)),ISNUMBER(SEARCH($C3,'⚙️ BỘ HƠI'!$H$2))),ROW()-2,99999))
A4: HH080200 | B4: HINO | C4: DM100 | D4: 90 | E4: 6 | F4: xy lanh gang F/F | G4: 11467-1601 | H4: IZ IKAZU | I4: Cái | J4: 1480000 | K4: 1580000 | L4: 1680000 | N4: Xy lanh Hino DM100 (11467-1601) - IZ IKAZU | O4: =IF($N4="","",$N4) | P4: =IF(OR('⚙️ BỘ HƠI'!$H$40=0,'⚙️ BỘ HƠI'!$H$2="",$C4="",LEFT($C4,1)="◆"),99999,IF(OR(ISNUMBER(SEARCH('⚙️ BỘ HƠI'!$H$2,$C4)),ISNUMBER(SEARCH($C4,'⚙️ BỘ HƠI'!$H$2))),ROW()-2,99999)) | Q4: ⚠️ HH070448, HH073131
A5: HH0638 | B5: HINO | C5: DM100 | D5: 90 | G5: 11467-1601 | H5: IZUMI | I5: Cái | N5: Xy lanh DM100 (11467-1601) - IZUMI | O5: =IF($N5="","",$N5) | P5: =IF(OR('⚙️ BỘ HƠI'!$H$40=0,'⚙️ BỘ HƠI'!$H$2="",$C5="",LEFT($C5,1)="◆"),99999,IF(OR(ISNUMBER(SEARCH('⚙️ BỘ HƠI'!$H$2,$C5)),ISNUMBER(SEARCH($C5,'⚙️ BỘ HƠI'!$H$2))),ROW()-2,99999)) | Q5: ⚠️ HH070449, HH080195
A6: HH081232 | B6: HINO | C6: EC100 | D6: 97 | G6: 11467-1130 | H6: IZ IKAZU | I6: Cái | J6: 1500000 | K6: 1600000 | L6: 1700000 | N6: Xy lanh EC100 (11467-1130) - IZ IKAZU | O6: =IF($N6="","",$N6) | P6: =IF(OR('⚙️ BỘ HƠI'!$H$40=0,'⚙️ BỘ HƠI'!$H$2="",$C6="",LEFT($C6,1)="◆"),99999,IF(OR(ISNUMBER(SEARCH('⚙️ BỘ HƠI'!$H$2,$C6)),ISNUMBER(SEARCH($C6,'⚙️ BỘ HƠI'!$H$2))),ROW()-2,99999))
A7: HH080199 | B7: HINO | C7: W04D-T/W06D-T có lợi ron | D7: 104 | G7: W04C, W06E | H7: IZ IKAZU | I7: Cái | J7: 200000 | K7: 215000 | L7: 230000 | N7: Xy lanh HINO W04D-T/ W06D-T có lợi ron (W04C, W06E) - IZ IKAZU | O7: =IF($N7="","",$N7) | P7: =IF(OR('⚙️ BỘ HƠI'!$H$40=0,'⚙️ BỘ HƠI'!$H$2="",$C7="",LEFT($C7,1)="◆"),99999,IF(OR(ISNUMBER(SEARCH('⚙️ BỘ HƠI'!$H$2,$C7)),ISNUMBER(SEARCH($C7,'⚙️ BỘ HƠI'!$H$2))),ROW()-2,99999)) | Q7: ⚠️ HH00896, HH079040, HH084160
A8: HH073131 | B8: HINO | C8: W04D/W04C/W06D/W06E có lợi ron | D8: 104 | H8: IZUMI | I8: Cái | N8: Xy lanh HINO W04D/W04C/W06D/W06E F/F có lợi ron - IZUMI | O8: =IF($N8="","",$N8) | P8: =IF(OR('⚙️ BỘ HƠI'!$H$40=0,'⚙️ BỘ HƠI'!$H$2="",$C8="",LEFT($C8,1)="◆"),99999,IF(OR(ISNUMBER(SEARCH('⚙️ BỘ HƠI'!$H$2,$C8)),ISNUMBER(SEARCH($C8,'⚙️ BỘ HƠI'!$H$2))),ROW()-2,99999)) | Q8: ⚠️ HH00733, HH00734, HH00891, HH071311, HH075733
A9: HH070448 | B9: HINO | C9: W04D/W04C/W06D/W06E không lợi ron | D9: 104 | H9: IZUMI | I9: Cái | N9: Xy lanh HINO W04D/W04C/W06D/W06E F/F không lợi ron - IZUMI | O9: =IF($N9="","",$N9) | P9: =IF(OR('⚙️ BỘ HƠI'!$H$40=0,'⚙️ BỘ HƠI'!$H$2="",$C9="",LEFT($C9,1)="◆"),99999,IF(OR(ISNUMBER(SEARCH('⚙️ BỘ HƠI'!$H$2,$C9)),ISNUMBER(SEARCH($C9,'⚙️ BỘ HƠI'!$H$2))),ROW()-2,99999)) | Q9: ⚠️ HH072695, HH079243, HH079774
A10: HH080195 | B10: HINO | C10: EH100 | D10: 105 | G10: 11467-1040 | H10: IZ IKAZU | I10: Cái | J10: 1100000 | K10: 1200000 | L10: 1300000 | N10: Xy lanh HINO EH100 F/F (11467-1040) - IZ IKAZU | O10: =IF($N10="","",$N10) | P10: =IF(OR('⚙️ BỘ HƠI'!$H$40=0,'⚙️ BỘ HƠI'!$H$2="",$C10="",LEFT($C10,1)="◆"),99999,IF(OR(ISNUMBER(SEARCH('⚙️ BỘ HƠI'!$H$2,$C10)),ISNUMBER(SEARCH($C10,'⚙️ BỘ HƠI'!$H$2))),ROW()-2,99999))
A11: HH070449 | B11: HINO | C11: EH100 | D11: 105 | H11: IZUMI | I11: Cái | J11: 1100000 | K11: 1200000 | L11: 1300000 | N11: Xy lanh HINO EH100 F/F đời hoàn thiện - IZUMI | O11: =IF($N11="","",$N11) | P11: =IF(OR('⚙️ BỘ HƠI'!$H$40=0,'⚙️ BỘ HƠI'!$H$2="",$C11="",LEFT($C11,1)="◆"),99999,IF(OR(ISNUMBER(SEARCH('⚙️ BỘ HƠI'!$H$2,$C11)),ISNUMBER(SEARCH($C11,'⚙️ BỘ HƠI'!$H$2))),ROW()-2,99999)) | Q11: ⚠️ HH070782, HH082195
A12: HH079241 | B12: HINO | C12: H06C | D12: 108 | G12: 114671601 | H12: NSP | I12: Cái | J12: 2750000 | K12: 2900000 | L12: 3100000 | N12: Xy lanh H06C / 114671601 F/F - NSP | O12: =IF($N12="","",$N12) | P12: =IF(OR('⚙️ BỘ HƠI'!$H$40=0,'⚙️ BỘ HƠI'!$H$2="",$C12="",LEFT($C12,1)="◆"),99999,IF(OR(ISNUMBER(SEARCH('⚙️ BỘ HƠI'!$H$2,$C12)),ISNUMBER(SEARCH($C12,'⚙️ BỘ HƠI'!$H$2))),ROW()-2,99999))
A13: HH082001 | B13: HINO | C13: H06C-TA/H06C | D13: 108 | G13: 11467-1591 | H13: IZ IKAZU | I13: Cái | J13: 1360000 | K13: 1450000 | L13: 1550000 | N13: Xy lanh Hino H06C-TA/H06C/ 11467-1591 - IZ IKAZU | O13: =IF($N13="","",$N13) | P13: =IF(OR('⚙️ BỘ HƠI'!$H$40=0,'⚙️ BỘ HƠI'!$H$2="",$C13="",LEFT($C13,1)="◆"),99999,IF(OR(ISNUMBER(SEARCH('⚙️ BỘ HƠI'!$H$2,$C13)),ISNUMBER(SEARCH($C13,'⚙️ BỘ HƠI'!$H$2))),ROW()-2,99999))
A14: HH072679 | B14: HINO | C14: H06C-TA/H06C | D14: 108 | H14: NSP | I14: Cái | L14: 250000 | N14: Xy lanh H06C-TA/H06C S/F bán hoàn thiện - NSP | O14: =IF($N14="","",$N14) | P14: =IF(OR('⚙️ BỘ HƠI'!$H$40=0,'⚙️ BỘ HƠI'!$H$2="",$C14="",LEFT($C14,1)="◆"),99999,IF(OR(ISNUMBER(SEARCH('⚙️ BỘ HƠI'!$H$2,$C14)),ISNUMBER(SEARCH($C14,'⚙️ BỘ HƠI'!$H$2))),ROW()-2,99999))
A15: HH068739 | B15: HINO | C15: H06C-TA/H06C | D15: 108 | G15: 11467-1591 | H15: IZUMI | I15: Cái | J15: 1200000 | K15: 1300000 | L15: 1400000 | N15: Xy lanh H06C-TA/H06C/ 11467-1591 - IZUMI | O15: =IF($N15="","",$N15) | P15: =IF(OR('⚙️ BỘ HƠI'!$H$40=0,'⚙️ BỘ HƠI'!$H$2="",$C15="",LEFT($C15,1)="◆"),99999,IF(OR(ISNUMBER(SEARCH('⚙️ BỘ HƠI'!$H$2,$C15)),ISNUMBER(SEARCH($C15,'⚙️ BỘ HƠI'!$H$2))),ROW()-2,99999))
A16: HH080197 | B16: HINO | C16: DS50 | D16: 110 | G16: 11467-1550 | H16: IZ IKAZU | I16: Cái | J16: 1900000 | K16: 2000000 | L16: 2100000 | N16: Xy lanh DS50 / 11467-1550 - IZ IKAZU | O16: =IF($N16="","",$N16) | P16: =IF(OR('⚙️ BỘ HƠI'!$H$40=0,'⚙️ BỘ HƠI'!$H$2="",$C16="",LEFT($C16,1)="◆"),99999,IF(OR(ISNUMBER(SEARCH('⚙️ BỘ HƠI'!$H$2,$C16)),ISNUMBER(SEARCH($C16,'⚙️ BỘ HƠI'!$H$2))),ROW()-2,99999))
A17: HH073238 | B17: HINO | C17: H07C | H17: NSP | I17: Cái | L17: 250000 | N17: Xy lanh H07C bán hoàn thiện S/F - NSP | O17: =IF($N17="","",$N17) | P17: =IF(OR('⚙️ BỘ HƠI'!$H$40=0,'⚙️ BỘ HƠI'!$H$2="",$C17="",LEFT($C17,1)="◆"),99999,IF(OR(ISNUMBER(SEARCH('⚙️ BỘ HƠI'!$H$2,$C17)),ISNUMBER(SEARCH($C17,'⚙️ BỘ HƠI'!$H$2))),ROW()-2,99999))
A18: HH079240 | B18: HINO | C18: H07C | G18: 114671210 | H18: NSP | I18: Cái | K18: 1700000 | L18: 1800000 | N18: Xy lanh H07C/ 114671210 F/F - NSP | O18: =IF($N18="","",$N18) | P18: =IF(OR('⚙️ BỘ HƠI'!$H$40=0,'⚙️ BỘ HƠI'!$H$2="",$C18="",LEFT($C18,1)="◆"),99999,IF(OR(ISNUMBER(SEARCH('⚙️ BỘ HƠI'!$H$2,$C18)),ISNUMBER(SEARCH($C18,'⚙️ BỘ HƠI'!$H$2))),ROW()-2,99999))
A19: HH079772 | B19: HINO | C19: H07C | G19: EH700/H07D | H19: IZ IKAZU | I19: Cái | J19: 1360000 | K19: 1450000 | L19: 1550000 | N19: Xy lanh Hino H07C/11467-1200 (EH700/H07D) - IZ IKAZU | O19: =IF($N19="","",$N19) | P19: =IF(OR('⚙️ BỘ HƠI'!$H$40=0,'⚙️ BỘ HƠI'!$H$2="",$C19="",LEFT($C19,1)="◆"),99999,IF(OR(ISNUMBER(SEARCH('⚙️ BỘ HƠI'!$H$2,$C19)),ISNUMBER(SEARCH($C19,'⚙️ BỘ HƠI'!$H$2))),ROW()-2,99999))
A20: HH00896 | B20: HINO | C20: H07C/EH700/H07D | D20: 110 | G20: 11467-1200 | H20: IZUMI | I20: Cái | N20: Xy lanh H07C/EH700/H07D (11467-1200) - IZUMI | O20: =IF($N20="","",$N20) | P20: =IF(OR('⚙️ BỘ HƠI'!$H$40=0,'⚙️ BỘ HƠI'!$H$2="",$C20="",LEFT($C20,1)="◆"),99999,IF(OR(ISNUMBER(SEARCH('⚙️ BỘ HƠI'!$H$2,$C20)),ISNUMBER(SEARCH($C20,'⚙️ BỘ HƠI'!$H$2))),ROW()-2,99999)) | Q20: ⚠️ HH070509, HH081456
A21: HH079040 | B21: HINO | C21: H07C/EH700/H07D | D21: 110 | H21: IZUMI | I21: Cái | J21: 1200000 | K21: 1300000 | L21: 1400000 | N21: Xy lanh H07C/EH700/H07D S/F bán hoàn thiện - IZUMI | O21: =IF($N21="","",$N21) | P21: =IF(OR('⚙️ BỘ HƠI'!$H$40=0,'⚙️ BỘ HƠI'!$H$2="",$C21="",LEFT($C21,1)="◆"),99999,IF(OR(ISNUMBER(SEARCH('⚙️ BỘ HƠI'!$H$2,$C21)),ISNUMBER(SEARCH($C21,'⚙️ BỘ HƠI'!$H$2))),ROW()-2,99999))
A22: HH084160 | B22: HINO | C22: H07C/EH700/H07D | D22: 110 | G22: 11467-1200 | H22: HENWEIT, L-HN004-00 | I22: Cái | J22: 1780000 | K22: 1900000 | L22: 2050000 | N22: Xy lanh Hino H07C/ EH700/ H07D/ 11467-1200 - HENWEIT, L-HN004-00 | O22: =IF($N22="","",$N22) | P22: =IF(OR('⚙️ BỘ HƠI'!$H$40=0,'⚙️ BỘ HƠI'!$H$2="",$C22="",LEFT($C22,1)="◆"),99999,IF(OR(ISNUMBER(SEARCH('⚙️ BỘ HƠI'!$H$2,$C22)),ISNUMBER(SEARCH($C22,'⚙️ BỘ HƠI'!$H$2))),ROW()-2,99999)) | Q22: ⚠️ HH070830, HH080577
A23: HH071311 | B23: HINO | C23: J05E/J08E | D23: 112 | H23: NPR | I23: Cái | N23: Xy lanh J05E/J08E - NPR | O23: =IF($N23="","",$N23) | P23: =IF(OR('⚙️ BỘ HƠI'!$H$40=0,'⚙️ BỘ HƠI'!$H$2="",$C23="",LEFT($C23,1)="◆"),99999,IF(OR(ISNUMBER(SEARCH('⚙️ BỘ HƠI'!$H$2,$C23)),ISNUMBER(SEARCH($C23,'⚙️ BỘ HƠI'!$H$2))),ROW()-2,99999)) | Q23: ⚠️ HH070830, HH080577
A24: HH00891 | B24: HINO | C24: J05E/J08E | D24: 112 | G24: 1173210 | H24: NSP | I24: Cái | N24: Xy lanh J05E/J08E (1173210) - NSP | O24: =IF($N24="","",$N24) | P24: =IF(OR('⚙️ BỘ HƠI'!$H$40=0,'⚙️ BỘ HƠI'!$H$2="",$C24="",LEFT($C24,1)="◆"),99999,IF(OR(ISNUMBER(SEARCH('⚙️ BỘ HƠI'!$H$2,$C24)),ISNUMBER(SEARCH($C24,'⚙️ BỘ HƠI'!$H$2))),ROW()-2,99999))
A25: HH073239 | B25: HINO | C25: J05E/J08E | D25: 112 | H25: NSP | I25: Cái | L25: 250000 | N25: Xy lanh J05E/J08E bán hoàn thiện S/F - NSP | O25: =IF($N25="","",$N25) | P25: =IF(OR('⚙️ BỘ HƠI'!$H$40=0,'⚙️ BỘ HƠI'!$H$2="",$C25="",LEFT($C25,1)="◆"),99999,IF(OR(ISNUMBER(SEARCH('⚙️ BỘ HƠI'!$H$2,$C25)),ISNUMBER(SEARCH($C25,'⚙️ BỘ HƠI'!$H$2))),ROW()-2,99999))
A26: HH075734 | B26: HINO | C26: J05E/J08E/E0060 | D26: 112 | G26: lợi cổ 3 ly | H26: MAHLE | I26: Cái | J26: 3200000 | K26: 3500000 | L26: 3700000 | N26: Xy lanh J05E/J08E/ 11462-E0060 (lợi cổ 3 ly) - MAHLE | O26: =IF($N26="","",$N26) | P26: =IF(OR('⚙️ BỘ HƠI'!$H$40=0,'⚙️ BỘ HƠI'!$H$2="",$C26="",LEFT($C26,1)="◆"),99999,IF(OR(ISNUMBER(SEARCH('⚙️ BỘ HƠI'!$H$2,$C26)),ISNUMBER(SEARCH($C26,'⚙️ BỘ HƠI'!$H$2))),ROW()-2,99999))
A27: HH075733 | B27: HINO | C27: J05E/J08E/S1146-73210 | D27: 112 | G27: lợi cổ 8 ly | H27: MAHLE | I27: Cái | J27: 3200000 | K27: 3500000 | L27: 3700000 | N27: Xy lanh J05E/J08E/ S1146-73210 (lợi cổ 8 ly) - MAHLE | O27: =IF($N27="","",$N27) | P27: =IF(OR('⚙️ BỘ HƠI'!$H$40=0,'⚙️ BỘ HƠI'!$H$2="",$C27="",LEFT($C27,1)="◆"),99999,IF(OR(ISNUMBER(SEARCH('⚙️ BỘ HƠI'!$H$2,$C27)),ISNUMBER(SEARCH($C27,'⚙️ BỘ HƠI'!$H$2))),ROW()-2,99999))
A28: HH079773 | B28: HINO | C28: J08E/J05E | D28: 112 | G28: 11467-3210A | H28: IZ IKAZU | I28: Cái | J28: 240000 | K28: 255000 | L28: 270000 | N28: Xy lanh HINO J08E/J05E (11467-3210A) lợi cổ 8mm - IZ IKAZU | O28: =IF($N28="","",$N28) | P28: =IF(OR('⚙️ BỘ HƠI'!$H$40=0,'⚙️ BỘ HƠI'!$H$2="",$C28="",LEFT($C28,1)="◆"),99999,IF(OR(ISNUMBER(SEARCH('⚙️ BỘ HƠI'!$H$2,$C28)),ISNUMBER(SEARCH($C28,'⚙️ BỘ HƠI'!$H$2))),ROW()-2,99999))
A29: HH00733 | B29: HINO | C29: J08E/J05E | D29: 112 | G29: 11467-3210A | H29: IZUMI | I29: Cái | N29: Xy lanh HINO J08E/J05E (11467-3210A) lợi cổ 8mm - IZUMI | O29: =IF($N29="","",$N29) | P29: =IF(OR('⚙️ BỘ HƠI'!$H$40=0,'⚙️ BỘ HƠI'!$H$2="",$C29="",LEFT($C29,1)="◆"),99999,IF(OR(ISNUMBER(SEARCH('⚙️ BỘ HƠI'!$H$2,$C29)),ISNUMBER(SEARCH($C29,'⚙️ BỘ HƠI'!$H$2))),ROW()-2,99999))
A30: HH00734 | B30: HINO | C30: J08E/J05E | D30: 112 | G30: 11467-3210B | H30: IZUMI | I30: Cái | N30: Xy lanh HINO J08E/J05E (11467-3210B) lợi cổ 3mm - IZUMI | O30: =IF($N30="","",$N30) | P30: =IF(OR('⚙️ BỘ HƠI'!$H$40=0,'⚙️ BỘ HƠI'!$H$2="",$C30="",LEFT($C30,1)="◆"),99999,IF(OR(ISNUMBER(SEARCH('⚙️ BỘ HƠI'!$H$2,$C30)),ISNUMBER(SEARCH($C30,'⚙️ BỘ HƠI'!$H$2))),ROW()-2,99999))
A31: HH072695 | B31: HINO | C31: J08C/J05C | D31: 114 | G31: 11467-2601 | H31: IZUMI | I31: Cái | J31: 1400000 | K31: 1500000 | L31: 1600000 | N31: Xy lanh HINO J08C/J05C (11467-2601) lợi cổ 3mm - IZUMI | O31: =IF($N31="","",$N31) | P31: =IF(OR('⚙️ BỘ HƠI'!$H$40=0,'⚙️ BỘ HƠI'!$H$2="",$C31="",LEFT($C31,1)="◆"),99999,IF(OR(ISNUMBER(SEARCH('⚙️ BỘ HƠI'!$H$2,$C31)),ISNUMBER(SEARCH($C31,'⚙️ BỘ HƠI'!$H$2))),ROW()-2,99999)) | Q31: ⚠️ HH070448, HH073131
A32: HH079243 | B32: HINO | C32: J08C/J05C | D32: 114 | G32: lợi cổ 8mm | H32: NSP | I32: Cái | J32: 450000 | K32: 475000 | L32: 500000 | N32: Xy lanh J08C /J05C/ 114672790 (lợi cổ 8mm) F/F - NSP | O32: =IF($N32="","",$N32) | P32: =IF(OR('⚙️ BỘ HƠI'!$H$40=0,'⚙️ BỘ HƠI'!$H$2="",$C32="",LEFT($C32,1)="◆"),99999,IF(OR(ISNUMBER(SEARCH('⚙️ BỘ HƠI'!$H$2,$C32)),ISNUMBER(SEARCH($C32,'⚙️ BỘ HƠI'!$H$2))),ROW()-2,99999))
A33: HH079041 | B33: HINO | C33: J08C/J05C | D33: 114 | H33: IZUMI | I33: Bộ 6 | J33: 1150000 | K33: 1200000 | L33: 1250000 | N33: Xy lanh HINO J08C/J05C lợi cổ 8mm S/F bán hoàn thiện - IZUMI | O33: =IF($N33="","",$N33) | P33: =IF(OR('⚙️ BỘ HƠI'!$H$40=0,'⚙️ BỘ HƠI'!$H$2="",$C33="",LEFT($C33,1)="◆"),99999,IF(OR(ISNUMBER(SEARCH('⚙️ BỘ HƠI'!$H$2,$C33)),ISNUMBER(SEARCH($C33,'⚙️ BỘ HƠI'!$H$2))),ROW()-2,99999))
A34: HH079774 | B34: HINO | C34: J08C/J05C lợi cổ 8mm | D34: 114 | G34: 11467-2611 | H34: IZ IKAZU | I34: Cái | J34: 1500000 | K34: 1600000 | L34: 1700000 | N34: Xy lanh HINO J08C/J05C lợi cổ 8mm (11467-2611) - IZ IKAZU | O34: =IF($N34="","",$N34) | P34: =IF(OR('⚙️ BỘ HƠI'!$H$40=0,'⚙️ BỘ HƠI'!$H$2="",$C34="",LEFT($C34,1)="◆"),99999,IF(OR(ISNUMBER(SEARCH('⚙️ BỘ HƠI'!$H$2,$C34)),ISNUMBER(SEARCH($C34,'⚙️ BỘ HƠI'!$H$2))),ROW()-2,99999))
A35: HH072178 | B35: HINO | C35: EB100/EB200 | D35: 115 | G35: đối chiếu lại lỗ khuyết sam trên xy lanh | H35: IZUMI | I35: Cái | J35: 2400000 | K35: 2500000 | L35: 2700000 | N35: Xy lanh EB100/EB200 (đối chiếu lại lỗ khuyết sam trên xy lanh) - IZUMI | O35: =IF($N35="","",$N35) | P35: =IF(OR('⚙️ BỘ HƠI'!$H$40=0,'⚙️ BỘ HƠI'!$H$2="",$C35="",LEFT($C35,1)="◆"),99999,IF(OR(ISNUMBER(SEARCH('⚙️ BỘ HƠI'!$H$2,$C35)),ISNUMBER(SEARCH($C35,'⚙️ BỘ HƠI'!$H$2))),ROW()-2,99999)) | Q35: ⚠️ HH072695, HH079243, HH079774
A36: HH082195 | B36: HINO | C36: EL100 | D36: 116 | G36: 11467-1240 | H36: IZ IKAZU | I36: Cái | J36: 1750000 | K36: 1850000 | L36: 1950000 | N36: Xy lanh Hino EL100 /11467-1240 - IZ IKAZU | O36: =IF($N36="","",$N36) | P36: =IF(OR('⚙️ BỘ HƠI'!$H$40=0,'⚙️ BỘ HƠI'!$H$2="",$C36="",LEFT($C36,1)="◆"),99999,IF(OR(ISNUMBER(SEARCH('⚙️ BỘ HƠI'!$H$2,$C36)),ISNUMBER(SEARCH($C36,'⚙️ BỘ HƠI'!$H$2))),ROW()-2,99999)) | Q36: ⚠️ HH00733, HH00734, HH00891, HH071311, HH075733
A37: HH070782 | B37: HINO | C37: EL100 | D37: 116 | H37: IZUMI | I37: Cái | N37: Xy lanh EL100 - IZUMI | O37: =IF($N37="","",$N37) | P37: =IF(OR('⚙️ BỘ HƠI'!$H$40=0,'⚙️ BỘ HƠI'!$H$2="",$C37="",LEFT($C37,1)="◆"),99999,IF(OR(ISNUMBER(SEARCH('⚙️ BỘ HƠI'!$H$2,$C37)),ISNUMBER(SEARCH($C37,'⚙️ BỘ HƠI'!$H$2))),ROW()-2,99999))
A38: HH072026 | B38: HINO | C38: DK10 | D38: 120 | G38: 11467-1380 | H38: IZUMI | I38: Cái | J38: 2600000 | K38: 2750000 | L38: 2900000 | N38: Xy lanh DK10 / 11467-1380 - IZUMI | O38: =IF($N38="","",$N38) | P38: =IF(OR('⚙️ BỘ HƠI'!$H$40=0,'⚙️ BỘ HƠI'!$H$2="",$C38="",LEFT($C38,1)="◆"),99999,IF(OR(ISNUMBER(SEARCH('⚙️ BỘ HƠI'!$H$2,$C38)),ISNUMBER(SEARCH($C38,'⚙️ BỘ HƠI'!$H$2))),ROW()-2,99999))
A39: HH081568 | B39: HINO | C39: EP100/P09C | D39: 120 | G39: 11467-1730 | H39: IZ IKAZU | I39: Cái | J39: 1600000 | K39: 1700000 | L39: 1850000 | N39: Xy lanh EP100/P09C/ 11467-1730 - IZ IKAZU | O39: =IF($N39="","",$N39) | P39: =IF(OR('⚙️ BỘ HƠI'!$H$40=0,'⚙️ BỘ HƠI'!$H$2="",$C39="",LEFT($C39,1)="◆"),99999,IF(OR(ISNUMBER(SEARCH('⚙️ BỘ HƠI'!$H$2,$C39)),ISNUMBER(SEARCH($C39,'⚙️ BỘ HƠI'!$H$2))),ROW()-2,99999)) | Q39: ⚠️ HH070450, HH081567
A40: HH070726 | B40: HINO | C40: P11C | G40: không gờ ron | H40: IZ IKAZU | I40: Cái | J40: 1500000 | K40: 1600000 | L40: 1700000 | N40: Xy lanh Hino P11C / 11467-2710 (không gờ ron) - IZ IKAZU | O40: =IF($N40="","",$N40) | P40: =IF(OR('⚙️ BỘ HƠI'!$H$40=0,'⚙️ BỘ HƠI'!$H$2="",$C40="",LEFT($C40,1)="◆"),99999,IF(OR(ISNUMBER(SEARCH('⚙️ BỘ HƠI'!$H$2,$C40)),ISNUMBER(SEARCH($C40,'⚙️ BỘ HƠI'!$H$2))),ROW()-2,99999)) | Q40: ⚠️ HH00733, HH00734, HH00891, HH071311, HH075733
A41: HH084369 | B41: HINO | C41: P11CT | G41: 11467-2710, Có gờ ron | H41: IZ IKAZU | I41: Cái | N41: Xy lanh Hino P11CT (11467-2710, Có gờ ron) - IZ IKAZU | O41: =IF($N41="","",$N41) | P41: =IF(OR('⚙️ BỘ HƠI'!$H$40=0,'⚙️ BỘ HƠI'!$H$2="",$C41="",LEFT($C41,1)="◆"),99999,IF(OR(ISNUMBER(SEARCH('⚙️ BỘ HƠI'!$H$2,$C41)),ISNUMBER(SEARCH($C41,'⚙️ BỘ HƠI'!$H$2))),ROW()-2,99999))
A42: HH082197 | B42: HINO | C42: EM100 | D42: 124 | G42: 11467-1661 | H42: IZ IKAZU | I42: Cái | J42: 1650000 | K42: 1750000 | L42: 1850000 | N42: Xy lanh EM100/ 11467-1661 - IZ IKAZU | O42: =IF($N42="","",$N42) | P42: =IF(OR('⚙️ BỘ HƠI'!$H$40=0,'⚙️ BỘ HƠI'!$H$2="",$C42="",LEFT($C42,1)="◆"),99999,IF(OR(ISNUMBER(SEARCH('⚙️ BỘ HƠI'!$H$2,$C42)),ISNUMBER(SEARCH($C42,'⚙️ BỘ HƠI'!$H$2))),ROW()-2,99999))
A43: HH081456 | B43: HINO | C43: K13C | G43: 11467-2090 | H43: IZ IKAZU | I43: Cái | J43: 2670000 | K43: 2840000 | L43: 3030000 | N43: Xy lanh Hino K13C / 11467-2090 - IZ IKAZU | O43: =IF($N43="","",$N43) | P43: =IF(OR('⚙️ BỘ HƠI'!$H$40=0,'⚙️ BỘ HƠI'!$H$2="",$C43="",LEFT($C43,1)="◆"),99999,IF(OR(ISNUMBER(SEARCH('⚙️ BỘ HƠI'!$H$2,$C43)),ISNUMBER(SEARCH($C43,'⚙️ BỘ HƠI'!$H$2))),ROW()-2,99999))
A44: HH070509 | B44: HINO | C44: K13C | G44: 11467-2090 | H44: IZUMI | I44: Cái | J44: 2450000 | K44: 2600000 | L44: 2750000 | N44: Xy lanh HINO K13C / 11467-2090 - IZUMI | O44: =IF($N44="","",$N44) | P44: =IF(OR('⚙️ BỘ HƠI'!$H$40=0,'⚙️ BỘ HƠI'!$H$2="",$C44="",LEFT($C44,1)="◆"),99999,IF(OR(ISNUMBER(SEARCH('⚙️ BỘ HƠI'!$H$2,$C44)),ISNUMBER(SEARCH($C44,'⚙️ BỘ HƠI'!$H$2))),ROW()-2,99999)) | Q44: ⚠️ HH079776, HH20443
A45: HH070452 | B45: HINO | C45: E13C | D45: 137 | H45: IZUMI | I45: Cái | J45: 1800000 | K45: 1900000 | L45: 2000000 | N45: Xy lanh HINO E13C F/F đời hoàn thiện - IZUMI | O45: =IF($N45="","",$N45) | P45: =IF(OR('⚙️ BỘ HƠI'!$H$40=0,'⚙️ BỘ HƠI'!$H$2="",$C45="",LEFT($C45,1)="◆"),99999,IF(OR(ISNUMBER(SEARCH('⚙️ BỘ HƠI'!$H$2,$C45)),ISNUMBER(SEARCH($C45,'⚙️ BỘ HƠI'!$H$2))),ROW()-2,99999)) | Q45: ⚠️ HH072682, HH074812, HH079776, HH081781, HH20443
A46: HH080577 | B46: HINO | C46: EF750/F17D | D46: 137 | G46: 11467-1900 | H46: IZ IKAZU | I46: Cái | J46: 3500000 | K46: 3700000 | L46: 3950000 | N46: Xy lanh Hino EF750/F17D/ 11467-1900 - IZ IKAZU | O46: =IF($N46="","",$N46) | P46: =IF(OR('⚙️ BỘ HƠI'!$H$40=0,'⚙️ BỘ HƠI'!$H$2="",$C46="",LEFT($C46,1)="◆"),99999,IF(OR(ISNUMBER(SEARCH('⚙️ BỘ HƠI'!$H$2,$C46)),ISNUMBER(SEARCH($C46,'⚙️ BỘ HƠI'!$H$2))),ROW()-2,99999)) | Q46: ⚠️ HH079776, HH20443
A47: HH070830 | B47: HINO | C47: EF750/F17D | D47: 137 | G47: 11467-1900 | H47: IZUMI | I47: Cái | N47: Xy lanh EF750/F17D/ 11467-1900 - IZUMI | O47: =IF($N47="","",$N47) | P47: =IF(OR('⚙️ BỘ HƠI'!$H$40=0,'⚙️ BỘ HƠI'!$H$2="",$C47="",LEFT($C47,1)="◆"),99999,IF(OR(ISNUMBER(SEARCH('⚙️ BỘ HƠI'!$H$2,$C47)),ISNUMBER(SEARCH($C47,'⚙️ BỘ HƠI'!$H$2))),ROW()-2,99999))
A48: HH070972 | B48: HINO | C48: EK100/EK200/K13D/EK130 | D48: 137 | H48: IZUMI | I48: Cái | J48: 2300000 | K48: 2400000 | L48: 2500000 | N48: Xy lanh EK100/ EK200/ K13D/ EK130 - IZUMI | O48: =IF($N48="","",$N48) | P48: =IF(OR('⚙️ BỘ HƠI'!$H$40=0,'⚙️ BỘ HƠI'!$H$2="",$C48="",LEFT($C48,1)="◆"),99999,IF(OR(ISNUMBER(SEARCH('⚙️ BỘ HƠI'!$H$2,$C48)),ISNUMBER(SEARCH($C48,'⚙️ BỘ HƠI'!$H$2))),ROW()-2,99999))
A49: HH081569 | B49: HINO | C49: F17C/F17E | D49: 139 | G49: 11467-1702 | H49: IZ IKAZU | I49: Cái | J49: 3560000 | K49: 3780000 | L49: 4040000 | N49: Xy lanh Hino F17C/ F17E (11467-1702) - IZ IKAZU | O49: =IF($N49="","",$N49) | P49: =IF(OR('⚙️ BỘ HƠI'!$H$40=0,'⚙️ BỘ HƠI'!$H$2="",$C49="",LEFT($C49,1)="◆"),99999,IF(OR(ISNUMBER(SEARCH('⚙️ BỘ HƠI'!$H$2,$C49)),ISNUMBER(SEARCH($C49,'⚙️ BỘ HƠI'!$H$2))),ROW()-2,99999)) | Q49: ⚠️ HH073803, HH083025
A50: HH080703 | B50: HINO | C50: F21C/3030A | D50: 150 | G50: 11467- | H50: IZ IKAZU | I50: Cái | J50: 3240000 | K50: 3400000 | L50: 3600000 | N50: Xy lanh Hino F21C / 11467-3030A - IZ IKAZU | O50: =IF($N50="","",$N50) | P50: =IF(OR('⚙️ BỘ HƠI'!$H$40=0,'⚙️ BỘ HƠI'!$H$2="",$C50="",LEFT($C50,1)="◆"),99999,IF(OR(ISNUMBER(SEARCH('⚙️ BỘ HƠI'!$H$2,$C50)),ISNUMBER(SEARCH($C50,'⚙️ BỘ HƠI'!$H$2))),ROW()-2,99999)) | Q50: ⚠️ HH00080, HH076235, HH079950, HH080362, HH081393
A51: HH082000 | B51: HINO | C51: J08E/J05E | D51: 112 | G51: 11467-3210B | H51: IZ IKAZU | I51: Bộ 6 | J51: 1500000 | K51: 1600000 | L51: 1700000 | N51: Xy lanh HINO J08E/J05E (11467-3210B) lợi cổ 3mm - IZ IKAZU | O51: =IF($N51="","",$N51) | P51: =IF(OR('⚙️ BỘ HƠI'!$H$40=0,'⚙️ BỘ HƠI'!$H$2="",$C51="",LEFT($C51,1)="◆"),99999,IF(OR(ISNUMBER(SEARCH('⚙️ BỘ HƠI'!$H$2,$C51)),ISNUMBER(SEARCH($C51,'⚙️ BỘ HƠI'!$H$2))),ROW()-2,99999)) | Q51: ⚠️ HH075729, HH081287, HH083369
A52: HH081567 | B52: HINO | C52: F20C-152 | H52: IZ IKAZU | I52: Cái | J52: 3100000 | K52: 3200000 | L52: 3400000 | N52: Xy lanh HINO F20C-152 F/F đời hoàn thiện - IZ IKAZU | O52: =IF($N52="","",$N52) | P52: =IF(OR('⚙️ BỘ HƠI'!$H$40=0,'⚙️ BỘ HƠI'!$H$2="",$C52="",LEFT($C52,1)="◆"),99999,IF(OR(ISNUMBER(SEARCH('⚙️ BỘ HƠI'!$H$2,$C52)),ISNUMBER(SEARCH($C52,'⚙️ BỘ HƠI'!$H$2))),ROW()-2,99999)) | Q52: ⚠️ HH075729, HH081287
A53: HH070450 | B53: HINO | C53: F20C-152 | H53: IZUMI | I53: Cái | J53: 3100000 | K53: 3200000 | L53: 3400000 | N53: Xy lanh HINO F20C-152 F/F đời hoàn thiện - IZUMI | O53: =IF($N53="","",$N53) | P53: =IF(OR('⚙️ BỘ HƠI'!$H$40=0,'⚙️ BỘ HƠI'!$H$2="",$C53="",LEFT($C53,1)="◆"),99999,IF(OR(ISNUMBER(SEARCH('⚙️ BỘ HƠI'!$H$2,$C53)),ISNUMBER(SEARCH($C53,'⚙️ BỘ HƠI'!$H$2))),ROW()-2,99999)) | Q53: ⚠️ HH075729, HH081287, HH084085
A54: HH083029 | B54: HINO | C54: F20C-154 | H54: IZ IKAZU | I54: Cái | J54: 3100000 | K54: 3200000 | L54: 3400000 | N54: Xy lanh HINO F20C-154 F/F đời hoàn thiện - IZ IKAZU | O54: =IF($N54="","",$N54) | P54: =IF(OR('⚙️ BỘ HƠI'!$H$40=0,'⚙️ BỘ HƠI'!$H$2="",$C54="",LEFT($C54,1)="◆"),99999,IF(OR(ISNUMBER(SEARCH('⚙️ BỘ HƠI'!$H$2,$C54)),ISNUMBER(SEARCH($C54,'⚙️ BỘ HƠI'!$H$2))),ROW()-2,99999)) | Q54: ⚠️ HH083026, HH20513
A55: HH081253 | B55: HINO | C55: P11C-T | G55: 114673140 | H55: NSP | I55: Cái | J55: 3700000 | K55: 4000000 | L55: 4200000 | N55: Xy lanh Hino P11C-T (114673140) - NSP | O55: =IF($N55="","",$N55) | P55: =IF(OR('⚙️ BỘ HƠI'!$H$40=0,'⚙️ BỘ HƠI'!$H$2="",$C55="",LEFT($C55,1)="◆"),99999,IF(OR(ISNUMBER(SEARCH('⚙️ BỘ HƠI'!$H$2,$C55)),ISNUMBER(SEARCH($C55,'⚙️ BỘ HƠI'!$H$2))),ROW()-2,99999))
A56: HH071022 | B56: HINO | C56: P11CT | G56: 11467-3140A, Có gờ ron | H56: IZUMI | I56: Cái | J56: 1500000 | K56: 1600000 | L56: 1700000 | N56: Xy lanh Hino P11CT (11467-3140A, Có gờ ron) - IZUMI | O56: =IF($N56="","",$N56) | P56: =IF(OR('⚙️ BỘ HƠI'!$H$40=0,'⚙️ BỘ HƠI'!$H$2="",$C56="",LEFT($C56,1)="◆"),99999,IF(OR(ISNUMBER(SEARCH('⚙️ BỘ HƠI'!$H$2,$C56)),ISNUMBER(SEARCH($C56,'⚙️ BỘ HƠI'!$H$2))),ROW()-2,99999))
B57: ◆ ISUZU (77 sản phẩm) | O57: =IF($N57="","",$N57) | P57: =IF(OR('⚙️ BỘ HƠI'!$H$40=0,'⚙️ BỘ HƠI'!$H$2="",$C57="",LEFT($C57,1)="◆"),99999,IF(OR(ISNUMBER(SEARCH('⚙️ BỘ HƠI'!$H$2,$C57)),ISNUMBER(SEARCH($C57,'⚙️ BỘ HƠI'!$H$2))),ROW()-2,99999)) | Q57: ⚠️ HH00088, HH073456, HH075859, HH079951, HH080363
A58: HH081566 | B58: ISUZU | C58: C221 | D58: 83 | F58: Kiếng | G58: 9-11261-253-0 | H58: IZ IKAZU | I58: Cái | J58: 1180000 | K58: 1250000 | L58: 1350000 | N58: Xy lanh C221/ 9-11261-253-0/ kiếng - IZ IKAZU | O58: =IF($N58="","",$N58) | P58: =IF(OR('⚙️ BỘ HƠI'!$H$40=0,'⚙️ BỘ HƠI'!$H$2="",$C58="",LEFT($C58,1)="◆"),99999,IF(OR(ISNUMBER(SEARCH('⚙️ BỘ HƠI'!$H$2,$C58)),ISNUMBER(SEARCH($C58,'⚙️ BỘ HƠI'!$H$2))),ROW()-2,99999)) | Q58: ⚠️ HH00088, HH073456, HH075859, HH079951, HH20446
A59: HH074812 | B59: ISUZU | C59: C240 | D59: 86 | F59: Gang | G59: 85*90*178*94*4 | H59: IZUMI | I59: Cái | J59: 500000 | K59: 530000 | L59: 570000 | N59: Xy lanh C240 S/F gang (85*90*178*94*4) bán hoàn thiện - IZUMI | O59: =IF($N59="","",$N59) | P59: =IF(OR('⚙️ BỘ HƠI'!$H$40=0,'⚙️ BỘ HƠI'!$H$2="",$C59="",LEFT($C59,1)="◆"),99999,IF(OR(ISNUMBER(SEARCH('⚙️ BỘ HƠI'!$H$2,$C59)),ISNUMBER(SEARCH($C59,'⚙️ BỘ HƠI'!$H$2))),ROW()-2,99999)) | Q59: ⚠️ HH00212, HH081705
A60: HH081781 | B60: ISUZU | C60: C240 | D60: 86 | F60: Gang | G60: 85*90*178*94*4.5 | H60: IZ IKAZU | I60: Cái | J60: 500000 | K60: 530000 | L60: 570000 | N60: Xy lanh ISUZU C240 S/F gang (85*90*178*94*4.5) bán hoàn thiện - IZ IKAZU | O60: =IF($N60="","",$N60) | P60: =IF(OR('⚙️ BỘ HƠI'!$H$40=0,'⚙️ BỘ HƠI'!$H$2="",$C60="",LEFT($C60,1)="◆"),99999,IF(OR(ISNUMBER(SEARCH('⚙️ BỘ HƠI'!$H$2,$C60)),ISNUMBER(SEARCH($C60,'⚙️ BỘ HƠI'!$H$2))),ROW()-2,99999)) | Q60: ⚠️ HH00212, HH081705
A61: HH072682 | B61: ISUZU | C61: C240 | D61: 86 | F61: Gang | G61: lưng 90, đường kính lợi 93.8, lợi 4 ly | H61: NSP | I61: Cái | L61: 200000 | N61: Xy lanh C240 S/F gang (lưng 90, đường kính lợi 93.8, lợi 4 ly) bán hoàn thiện - NSP | O61: =IF($N61="","",$N61) | P61: =IF(OR('⚙️ BỘ HƠI'!$H$40=0,'⚙️ BỘ HƠI'!$H$2="",$C61="",LEFT($C61,1)="◆"),99999,IF(OR(ISNUMBER(SEARCH('⚙️ BỘ HƠI'!$H$2,$C61)),ISNUMBER(SEARCH($C61,'⚙️ BỘ HƠI'!$H$2))),ROW()-2,99999)) | Q61: ⚠️ HH00384, HH080364
A62: HH20443 | B62: ISUZU | C62: C240/C190 | D62: 86 | F62: Kiếng | G62: 9-11261-230-1 | H62: IZUMI | I62: Cái | J62: 750000 | K62: 800000 | L62: 900000 | N62: Xy lanh C240/C190/ 9-11261-230-1 kiếng - IZUMI | O62: =IF($N62="","",$N62) | P62: =IF(OR('⚙️ BỘ HƠI'!$H$40=0,'⚙️ BỘ HƠI'!$H$2="",$C62="",LEFT($C62,1)="◆"),99999,IF(OR(ISNUMBER(SEARCH('⚙️ BỘ HƠI'!$H$2,$C62)),ISNUMBER(SEARCH($C62,'⚙️ BỘ HƠI'!$H$2))),ROW()-2,99999)) | Q62: ⚠️ HH00091, HH079315, HH079762, HH079952, HH081395
A63: HH079776 | B63: ISUZU | C63: C240/C190 | D63: 86 | F63: Kiếng | G63: 9-11261-230-1 | H63: IZ IKAZU | I63: Cái | J63: 800000 | K63: 900000 | L63: 1000000 | N63: Xy lanh Isuzu C240/C190/ 9-11261-230-1, chromed kiếng - IZ IKAZU | O63: =IF($N63="","",$N63) | P63: =IF(OR('⚙️ BỘ HƠI'!$H$40=0,'⚙️ BỘ HƠI'!$H$2="",$C63="",LEFT($C63,1)="◆"),99999,IF(OR(ISNUMBER(SEARCH('⚙️ BỘ HƠI'!$H$2,$C63)),ISNUMBER(SEARCH($C63,'⚙️ BỘ HƠI'!$H$2))),ROW()-2,99999))
A64: HH072359 | B64: ISUZU | C64: C223/4JC1 | D64: 88 | G64: 88*90*163*95*0.9 | H64: IZUMI | I64: Cái | K64: 760000 | L64: 800000 | N64: Xy lanh C223 / 4JC1 (88*90*163*95*0.9) - IZUMI | O64: =IF($N64="","",$N64) | P64: =IF(OR('⚙️ BỘ HƠI'!$H$40=0,'⚙️ BỘ HƠI'!$H$2="",$C64="",LEFT($C64,1)="◆"),99999,IF(OR(ISNUMBER(SEARCH('⚙️ BỘ HƠI'!$H$2,$C64)),ISNUMBER(SEARCH($C64,'⚙️ BỘ HƠI'!$H$2))),ROW()-2,99999)) | Q64: ⚠️ HH00091, HH079315, HH079762, HH079952, HH081395
A65: HH081393 | B65: ISUZU | C65: 4JB1 | D65: 93 | E65: 4 | G65: 92*97*180*F101*5 | H65: IZ IKAZU | I65: Cái | J65: 140000 | K65: 150000 | L65: 160000 | N65: Xy lanh 4JB1 S/F (92*97*180*F101*5)bán hoàn thiện - IZ IKAZU | O65: =IF($N65="","",$N65) | P65: =IF(OR('⚙️ BỘ HƠI'!$H$40=0,'⚙️ BỘ HƠI'!$H$2="",$C65="",LEFT($C65,1)="◆"),99999,IF(OR(ISNUMBER(SEARCH('⚙️ BỘ HƠI'!$H$2,$C65)),ISNUMBER(SEARCH($C65,'⚙️ BỘ HƠI'!$H$2))),ROW()-2,99999))
A66: HH081704 | B66: ISUZU | C66: 4JB1 | D66: 93 | G66: 92*97*181*F101*4, bán hoàn thiện | H66: IZUMI IKAZU | I66: Cái | N66: Xy lanh 4JB1 S/F (92*97*181*F101*4)bán hoàn thiện - IZUMI IKAZU | O66: =IF($N66="","",$N66) | P66: =IF(OR('⚙️ BỘ HƠI'!$H$40=0,'⚙️ BỘ HƠI'!$H$2="",$C66="",LEFT($C66,1)="◆"),99999,IF(OR(ISNUMBER(SEARCH('⚙️ BỘ HƠI'!$H$2,$C66)),ISNUMBER(SEARCH($C66,'⚙️ BỘ HƠI'!$H$2))),ROW()-2,99999))
A67: HH083025 | B67: ISUZU | C67: 4JA1 | E67: 4 | F67: Kiếng | G67: 8-94462-130-0 | H67: IZ IKAZU | I67: Cái | J67: 790000 | K67: 840000 | L67: 900000 | N67: Xy lanh Isuzu 4JA1/ 8-94462-130-0 chromed, kiếng - IZ IKAZU | O67: =IF($N67="","",$N67) | P67: =IF(OR('⚙️ BỘ HƠI'!$H$40=0,'⚙️ BỘ HƠI'!$H$2="",$C67="",LEFT($C67,1)="◆"),99999,IF(OR(ISNUMBER(SEARCH('⚙️ BỘ HƠI'!$H$2,$C67)),ISNUMBER(SEARCH($C67,'⚙️ BỘ HƠI'!$H$2))),ROW()-2,99999))
A68: HH073803 | B68: ISUZU | C68: 4JA1 | E68: 4 | F68: Kiếng | G68: 93*95*156*101*0.9 | H68: IZUMI | I68: Cái | J68: 780000 | K68: 800000 | L68: 850000 | N68: Xy lanh 4JA1 kiếng (93*95*156*101*0.9) - IZUMI | O68: =IF($N68="","",$N68) | P68: =IF(OR('⚙️ BỘ HƠI'!$H$40=0,'⚙️ BỘ HƠI'!$H$2="",$C68="",LEFT($C68,1)="◆"),99999,IF(OR(ISNUMBER(SEARCH('⚙️ BỘ HƠI'!$H$2,$C68)),ISNUMBER(SEARCH($C68,'⚙️ BỘ HƠI'!$H$2))),ROW()-2,99999)) | Q68: ⚠️ HH00894, HH00897, HH081285
A69: HH076235 | B69: ISUZU | C69: 4JB1 | D69: 93 | E69: 4 | F69: Kiếng | H69: MAHLE 8-97176687 | I69: Cái | J69: 1400000 | K69: 1500000 | L69: 1600000 | N69: Xy lanh 4JB1 kiếng - MAHLE 8-97176687 | O69: =IF($N69="","",$N69) | P69: =IF(OR('⚙️ BỘ HƠI'!$H$40=0,'⚙️ BỘ HƠI'!$H$2="",$C69="",LEFT($C69,1)="◆"),99999,IF(OR(ISNUMBER(SEARCH('⚙️ BỘ HƠI'!$H$2,$C69)),ISNUMBER(SEARCH($C69,'⚙️ BỘ HƠI'!$H$2))),ROW()-2,99999))
